Workbook

Sheet 지침
B2: 산업전환부문 정보비공개 신청 평가 참고 지침

Sheet 검토기준
B2: 산업전환부문 정보비공개 신청 검토 기준
B49: 1차 검토 결과_20220602(첫 통보일)
B50: 구분 | C50: 국내평가 | D50: 국내인증 | E50: 국외평가 | F50: 국외인증 | G50: 합계 | H50: 신청 사유 | K50: 검토결과 | M50: 이슈 사항
B51: 내부방침 | C51: 34 | D51: 86 | E51: 9 | F51: 69 | G51: =SUM(C51:F51) -> 198 | H51: 회사 내규, 내부 방침 등 | K51: 보완요청 필요 | M51: 국외사업 : 비공개 신청 건 심의중 처리되지 않고, 정보 확인 가능 > ORS 문의 필요 > 해결(신청사업은 심의중 처리, 차수별 구분)
B52: 개인정보보호 | C52: 3 | D52: 6 | E52: 0 | F52: 0 | G52: =SUM(C52:F52) -> 9 | H52: 사업자 개인정보 | K52: 보완요청 필요 | M52: 국내CDM 사업 중 동 사업을 여러 사업자가 신청한 경우 : 신청한 사업자에 한하여 심의중 처리(한화 울산소재 질산공장, 시화호)
B53: 업체정보보호 | C53: 10 | D53: 3 | E53: 1 | F53: 0 | G53: =SUM(C53:F53) -> 14 | H53: 업무상 비밀 보호 시설 운영 실적 포함 원주시 내부 정보 포함 생산 공정 등 외부 유출에 민감한 자료 포함 보안이 필요한 생산시설 배치도와 기타 생산설비 사진 질산공정 영업 비밀 내용이 반영 발전소 설비 및 관리 세부 정보 PoA 9181 CPA19-30 사업계획서 영업기밀사항등이 포함(사업비용 조달 방법) > 보완요청 후 재확인 필요(클리어스카이파트너스) | K53: 보완요청 필요 | M53: 인증 비공개 신청 : 모니터링 차수 중 하나만 신청하더라도 심의중 처리 (카프로 N2O, 휴캠스 질산공장) > 해결(차수에 따라 구분됨)
B54: 기타 | C54: 1 | D54: 0 | E54: 0 | F54: 0 | G54: =SUM(C54:F54) -> 1 | H54: 배출권에 대한 수익 배분 및 기타 세부 내용 | K54: 확인 필요
C55: =SUM(C51:C54) -> 48 | D55: =SUM(D51:D54) -> 95 | E55: =SUM(E51:E54) -> 10 | F55: =SUM(F51:F54) -> 69 | G55: =SUM(G51:G54) -> 222
B58: 2차 검토 결과_20221013(47차 인증위 통보 반영)
B59: 구분 | C59: 국내평가 | D59: 국내인증 | E59: 국외평가 | F59: 국외인증 | G59: 합계 | H59: 신청 사유 | K59: 검토결과
B60: 내부방침 | C60: 0 | D60: 11 | E60: 0 | F60: 1 | G60: =SUM(C60:F60) -> 12 | H60: 회사 내규, 내부 방침 등 | K60: 보완요청 필요
B61: 개인정보보호 | C61: 0 | D61: 1 | E61: 0 | F61: 0 | G61: =SUM(C61:F61) -> 1 | H61: 사업자 개인정보 | K61: 보완요청 필요
B62: 업체정보보호 | C62: 0 | D62: 0 | E62: 11 | F62: 0 | G62: =SUM(C62:F62) -> 11 | H62: PoA 9181 CPA19-30 사업계획서 영업기밀사항등이 포함(사업비용 조달 방법) > 보완요청 후 재확인 필요(클리어스카이파트너스) | K62: 보완요청 필요(증빙자료는 정보공개 대상 아님)
B63: 기타 | D63: 0 | E63: 0 | F63: 0 | G63: =SUM(C63:F63) -> 0
C64: =SUM(C60:C63) -> 0 | D64: =SUM(D60:D63) -> 12 | E64: =SUM(E60:E63) -> 11 | F64: =SUM(F60:F63) -> 1 | G64: =SUM(G60:G63) -> 24
B66: 변경 사항(6월 2일 대비 10월 13일)
B67: 평가(국내평가 +0) : 신규 승인 0건(신규 비공개 신청 1건)
B68: 평가(국외평가 +11) : 신규 승인 11건 추가
B69: 인증(국내인증 +12) : 신규 승인 12건 추가(신규 비공개 신청 5건)
B70: 인증(국외인증 +1) : 신규 승인 1건 추가
B72: 3차 검토 결과_20221130
B73: 구분 | C73: 국내평가 | D73: 국내인증 | E73: 국외평가 | F73: 국외인증 | G73: 합계 | H73: 신청 사유 | K73: 검토결과
B74: 내부방침 | C74: 1 | D74: 0 | E74: 0 | F74: 0 | G74: =SUM(C74:F74) -> 1 | H74: 회사 내규, 내부 방침 등 | K74: 보완요청 필요
B75: 개인정보보호 | C75: 0 | D75: 0 | E75: 0 | F75: 0 | G75: =SUM(C75:F75) -> 0 | H75: 사업자 개인정보 | K75: 보완요청 필요
B76: 업체정보보호 | C76: 1 | D76: 0 | E76: 0 | F76: 0 | G76: =SUM(C76:F76) -> 1 | H76: 업체정보보호(업무상 비밀) | K76: 보완요청 필요
B77: 기타 | C77: 0 | D77: 0 | E77: 0 | F77: 0 | G77: =SUM(C77:F77) -> 0
C78: =SUM(C74:C77) -> 2 | D78: =SUM(D74:D77) -> 0 | E78: =SUM(E74:E77) -> 0 | F78: =SUM(F74:F77) -> 0 | G78: =SUM(G74:G77) -> 2
B80: 변경 사항(10월 13일 대비 11월 30일)
B81: 평가(국내평가 +2) : 신규 승인 2건 추가(신규 비공개 신청 0건)
B84: 4차 검토 결과_20230419
B85: 구분 | C85: 국내평가 | D85: 국내인증 | E85: 국외평가 | F85: 국외인증 | G85: 합계 | H85: 신청 사유 | K85: 검토결과
B86: 내부방침 | C86: 1 | D86: 5 | E86: 0 | F86: 0 | G86: =SUM(C86:F86) -> 6 | H86: 회사 내규, 내부 방침 등 | K86: 보완요청 필요
B87: 개인정보보호 | C87: 0 | D87: 0 | E87: 0 | F87: 0 | G87: =SUM(C87:F87) -> 0 | H87: 사업자 개인정보 | K87: 보완요청 필요
B88: 업체정보보호 | C88: 1 | D88: 0 | E88: 3 | F88: 0 | G88: =SUM(C88:F88) -> 4 | H88: 업체정보보호(업무상 비밀) | K88: 보완요청 필요
B89: 기타 | C89: 0 | D89: 0 | E89: 0 | F89: 0 | G89: =SUM(C89:F89) -> 0
C90: =SUM(C86:C89) -> 2 | D90: =SUM(D86:D89) -> 5 | E90: =SUM(E86:E89) -> 3 | F90: =SUM(F86:F89) -> 0 | G90: =SUM(G86:G89) -> 10
B92: 변경 사항(11월 30일 대비 03월 27일)
B93: 평가(국내평가 +2) : 신규 승인 1건 추가(신규 비공개 신청 1건)
B94: 평가(국외평가 +3) : 신규 승인 3건 추가(신규 비공개 신청 0건)
B95: 평가(국내인증 +5) : 신규 승인 0건 추가(신규 비공개 신청 5건)
B98: 5차 검토 결과_20230619
B99: 구분 | C99: 국내평가 | D99: 국내인증 | E99: 국외평가 | F99: 국외인증 | G99: 합계 | H99: 신청 사유 | K99: 검토결과
B100: 내부방침 | C100: 0 | D100: 3 | E100: 0 | F100: 0 | G100: =SUM(C100:F100) -> 3 | H100: 회사 내규, 내부 방침 등 | K100: 보완요청 필요
B101: 개인정보보호 | C101: 0 | D101: 0 | E101: 0 | F101: 0 | G101: =SUM(C101:F101) -> 0 | H101: 사업자 개인정보 | K101: 보완요청 필요
B102: 업체정보보호 | C102: 0 | D102: 0 | E102: 0 | F102: 0 | G102: =SUM(C102:F102) -> 0 | H102: 업체정보보호(업무상 비밀) | K102: 보완요청 필요
B103: 기타 | C103: 0 | D103: 0 | E103: 0 | F103: 0 | G103: =SUM(C103:F103) -> 0
C104: =SUM(C100:C103) -> 0 | D104: =SUM(D100:D103) -> 3 | E104: =SUM(E100:E103) -> 0 | F104: =SUM(F100:F103) -> 0 | G104: =SUM(G100:G103) -> 3
B106: 변경 사항(3월 27일 대비 06월 19일)
B107: 인증(국내 +3) : 신규 승인 3건 추가
B110: 6차 검토 결과_20230919
B111: 구분 | C111: 국내평가 | D111: 국내인증 | E111: 국외평가 | F111: 국외인증 | G111: 합계 | H111: 신청 사유 | K111: 검토결과
B112: 내부방침 | C112: 1 | D112: 1 | E112: 0 | F112: 0 | G112: =SUM(C112:F112) -> 2 | H112: 회사 내규, 내부 방침 등 | K112: 보완요청 필요
B113: 개인정보보호 | C113: 0 | D113: 0 | E113: 0 | F113: 0 | G113: =SUM(C113:F113) -> 0 | H113: 사업자 개인정보
B114: 업체정보보호 | C114: 0 | D114: 0 | E114: 0 | F114: 0 | G114: =SUM(C114:F114) -> 0 | H114: 업체정보보호(업무상 비밀)
B115: 기타 | C115: 0 | D115: 0 | E115: 0 | F115: 0 | G115: =SUM(C115:F115) -> 0
B118: 변경 사항(6월 19일 대비 09월 19일)
B119: 평가(국내 +1) : 신규 승인 1건 추가(신규 비공개 신청 1건)
B120: 인증(국내 +1) : 신규 승인 1건 추가(신규 비공개 신청 0건)
B123: 7차 검토 결과_20240329
B124: 구분 | C124: 국내평가 | D124: 국내인증 | E124: 국외평가 | F124: 국외인증 | G124: 합계 | H124: 신청 사유 | K124: 검토결과
B125: 내부방침 | C125: 0 | D125: 0 | E125: 0 | F125: 0 | G125: =SUM(C125:F125) -> 0 | H125: 회사 내규, 내부 방침 등
B126: 개인정보보호 | C126: 0 | D126: 0 | E126: 0 | F126: 0 | G126: =SUM(C126:F126) -> 0 | H126: 사업자 개인정보
B127: 업체정보보호 | C127: 0 | D127: 0 | E127: 0 | F127: 0 | G127: =SUM(C127:F127) -> 0 | H127: 업체정보보호(업무상 비밀)
B128: 기타 | C128: 0 | D128: 0 | E128: 0 | F128: 0 | G128: =SUM(C128:F128) -> 0
B131: 변경 사항(9월 19일 대비 24년 03월 29일)
B132: 평가(국내 +0) : 신규 승인 0건 추가(신규 비공개 신청 3건)
B133: 인증(국내 +0) : 신규 승인 0건 추가(신규 비공개 신청 3건 중 1건 검토 중, 1건 협의검토중, 1건 반려)
B136: 8차 검토 결과_20240614
B137: 구분 | C137: 국내평가 | D137: 국내인증 | E137: 국외평가 | F137: 국외인증 | G137: 합계 | H137: 신청 사유 | K137: 검토결과
B138: 내부방침 | C138: 1 | D138: 1 | E138: 0 | F138: 0 | G138: =SUM(C138:F138) -> 2 | H138: 회사 내규, 내부 방침 등
B139: 개인정보보호 | C139: 0 | D139: 0 | E139: 0 | F139: 0 | G139: =SUM(C139:F139) -> 0 | H139: 사업자 개인정보
B140: 업체정보보호 | C140: 1 | D140: 3 | E140: 0 | F140: 0 | G140: =SUM(C140:F140) -> 4 | H140: 업체정보보호(업무상 비밀)
B141: 기타 | C141: 0 | D141: 0 | E141: 0 | F141: 0 | G141: =SUM(C141:F141) -> 0
G142: =SUM(G138:G141) -> 6
B144: 변경 사항(24년 3월 29일 대비 24년 6월 14일)
B145: 평가(국내 +1) : 신규 승인 1건 추가(신규 비공개 신청 2건)
B146: 인증(국내 +4) : 신규 승인 4건 추가(신규 비공개 신청 1건)
B149: 9차 검토 결과_20241002
B150: 구분 | C150: 국내평가 | D150: 국내인증 | E150: 국외평가 | F150: 국외인증 | G150: 합계 | H150: 신청 사유 | K150: 검토결과
B151: 내부방침 | C151: 0 | D151: 0 | E151: 0 | F151: 0 | G151: =SUM(C151:F151) -> 0 | H151: 회사 내규, 내부 방침 등
B152: 개인정보보호 | C152: 0 | D152: 0 | E152: 0 | F152: 0 | G152: =SUM(C152:F152) -> 0 | H152: 사업자 개인정보
B153: 업체정보보호 | C153: 0 | D153: 0 | E153: 0 | F153: 0 | G153: =SUM(C153:F153) -> 0 | H153: 업체정보보호(업무상 비밀)
B154: 기타 | C154: 0 | D154: 0 | E154: 0 | F154: 0 | G154: =SUM(C154:F154) -> 0
B157: 변경 사항(24년 6월 14일 대비 24년 10월 02일)
B158: 평가(국내 +0) : 신규 승인 0건 추가(신규 비공개 신청 0건), 종결 2건(부산경남우유협동조합, 에이스침대중부공장)
B159: 인증(국내 +0) : 신규 승인 0건 추가(신규 비공개 신청 1건), 종결 1건(에이스침대중부공장)
B161: 10차 검토 결과_20241115
B162: 구분 | C162: 국내평가 | D162: 국내인증 | E162: 국외평가 | F162: 국외인증 | G162: 합계 | H162: 신청 사유 | K162: 검토결과
B163: 내부방침 | C163: 0 | D163: 0 | E163: 0 | F163: 0 | G163: =SUM(C163:F163) -> 0 | H163: 회사 내규, 내부 방침 등
B164: 개인정보보호 | C164: 0 | D164: 0 | E164: 0 | F164: 0 | G164: =SUM(C164:F164) -> 0 | H164: 사업자 개인정보
B165: 업체정보보호 | C165: 0 | D165: 0 | E165: 0 | F165: 0 | G165: =SUM(C165:F165) -> 0 | H165: 업체정보보호(업무상 비밀)
B166: 기타 | C166: 0 | D166: 0 | E166: 0 | F166: 0 | G166: =SUM(C166:F166) -> 0
B169: 변경 사항(24년 10월 02일 대비 24년 11월 15일)
B170: 평가(국내 +0) : 신규 승인 0건 추가(신규 비공개 신청 1건)
B171: 인증(국내 +0) : 신규 승인 0건 추가(신규 비공개 신청 1건)

Sheet 통계
B2: 산업전환부문 정보비공개 신청 평가 현황
B13: 2026.07.07
B14: 구분 | D14: 신청건수 | E14: 정보 비공개 신청 평가 종료 | H14: 평가중 | L14: 평가 불필요
E15: 승인 | F15: 반려 | G15: 소계 | H15: 사업자 | I15: 검토반 | K15: 소계 | L15: 사업 반려 | M15: 정보 비공개 신청 반려 | P15: 소계
H16: 의견 통보 | I16: 의견 보완 | J16: 신규 신청 | M16: 반려 완료 | N16: 사업자 요청 | O16: 보류(반려 필요)
B17: 평가 (정보비공개) | C17: 국내 | D17: =COUNT('(비공개)국내평가'!A:A) -> 106 | E17: =COUNTIF('(비공개)국내평가'!$Q:$Q,"*승인*") -> 6 | F17: =SUM(L17:O17) -> 59 | G17: =SUM(E17:F17) -> 65 | H17: =COUNTIFS('(비공개)국내평가'!Q:Q,"*보완요청*",'(비공개)국내평가'!R:R,"*사업자*") -> 39 | I17: =COUNTIFS('(비공개)국내평가'!Q:Q,"*보완완료*",'(비공개)국내평가'!R:R,"*검토반*") -> 1 | J17: =COUNTIFS('(비공개)국내평가'!Q:Q,"*평가필요*",'(비공개)국내평가'!R:R,"*검토반*") -> 1 | K17: =SUM(H17:J17) -> 41 | L17: =COUNTIF('(비공개)국내평가'!$K:$K,"*반려*")-COUNTIFS('(비공개)국내평가'!K:K,"*반려*",'(비공개)국내평가'!L:L,"사업변경 신청")-COUNTIFS('(비공개)국내평가'!K:K,"*반려*",'(비공개)국내평가'!L:L,"인증유효기간 갱신") -> 39 | M17: =COUNTIFS('(비공개)국내평가'!$Q:$Q,"*반려완료*",'(비공개)국내평가'!R:R,"*종결*") -> 20 | N17: =COUNTIFS('(비공개)국내평가'!$Q:$Q,"*반려요청*",'(비공개)국내평가'!$R:$R,"*검토반*") -> 0 | O17: =COUNTIFS('(비공개)국내평가'!$Q:$Q,"*보류*",'(비공개)국내평가'!$R:$R,"*반려필요*") -> 0 | P17: =SUM(L17:O17) -> 59
C18: 국외 | D18: =COUNT('(비공개)국외평가'!A:A) -> 24 | E18: =COUNTIF('(비공개)국외평가'!$Q:$Q,"*승인*") -> 0 | F18: =SUM(L18:O18) -> 9 | G18: =SUM(E18:F18) -> 9 | H18: =COUNTIFS('(비공개)국외평가'!Q:Q,"*보완요청*",'(비공개)국외평가'!R:R,"*사업자*") -> 15 | I18: =COUNTIFS('(비공개)국외평가'!Q:Q,"*보완완료*",'(비공개)국외평가'!R:R,"*검토반*") -> 0 | J18: =COUNTIFS('(비공개)국외평가'!Q:Q,"*평가필요*",'(비공개)국외평가'!R:R,"*검토반*") -> 0 | K18: =SUM(H18:J18) -> 15 | L18: =COUNTIF('(비공개)국외평가'!$K:$K,"*반려*")-COUNTIFS('(비공개)국외평가'!K:K,"*반려*",'(비공개)국외평가'!L:L,"사업변경 신청")-COUNTIFS('(비공개)국외평가'!K:K,"*반려*",'(비공개)국외평가'!L:L,"인증유효기간 갱신") -> 0 | M18: =COUNTIFS('(비공개)국외평가'!$Q:$Q,"*반려완료*",'(비공개)국외평가'!R:R,"*종결*") -> 9 | N18: =COUNTIFS('(비공개)국외평가'!$Q:$Q,"*반려요청*",'(비공개)국외평가'!$R:$R,"*검토반*") -> 0 | O18: =COUNTIFS('(비공개)국외평가'!$Q:$Q,"*보류*",'(비공개)국외평가'!$R:$R,"*반려필요*") -> 0 | P18: =SUM(L18:O18) -> 9
B19: 인증 (정보비공개) | C19: 국내 | D19: =COUNT('(비공개)국내인증'!B:B) -> 126 | E19: =COUNTIF('(비공개)국내인증'!$S:$S,"*승인*") -> 2 | F19: =SUM(L19:O19) -> 19 | G19: =SUM(E19:F19) -> 21 | H19: =COUNTIFS('(비공개)국내인증'!S:S,"*보완요청*",'(비공개)국내인증'!T:T,"*사업자*") -> 105 | I19: =COUNTIFS('(비공개)국내인증'!S:S,"*보완완료*",'(비공개)국내인증'!T:T,"*검토반*") -> 0 | J19: =COUNTIFS('(비공개)국내인증'!S:S,"*평가필요*",'(비공개)국내인증'!T:T,"*검토반*") -> 0 | K19: =SUM(H19:J19) -> 105 | L19: =COUNTIFS('(비공개)국내인증'!S:S,"*선택*",'(비공개)국내인증'!T:T,"종결") -> 1 | M19: =COUNTIFS('(비공개)국내인증'!$S:$S,"*반려완료*",'(비공개)국내인증'!T:T,"*종결*") -> 4 | N19: =COUNTIFS('(비공개)국내인증'!S:S,"*반려요청*",'(비공개)국내인증'!T:T,"*검토반*") -> 14 | O19: =COUNTIFS('(비공개)국내인증'!S:S,"*보류*",'(비공개)국내인증'!T:T,"*반려필요*") -> 0 | P19: =SUM(L19:O19) -> 19
C20: 국외 | D20: =COUNT('(비공개)국외인증'!B:B) -> 75 | E20: =COUNTIF('(비공개)국외인증'!$U:$U,"*승인*") -> 0 | F20: =SUM(L20:O20) -> 74 | G20: =SUM(E20:F20) -> 74 | H20: =COUNTIFS('(비공개)국외인증'!U:U,"*보완요청*",'(비공개)국외인증'!V:V,"*사업자*") -> 1 | I20: =COUNTIFS('(비공개)국외인증'!U:U,"*보완완료*",'(비공개)국외인증'!V:V,"*검토반*") -> 0 | J20: =COUNTIFS('(비공개)국외인증'!U:U,"*평가필요*",'(비공개)국외인증'!V:V,"*검토반*") -> 0 | K20: =SUM(H20:J20) -> 1 | L20: =COUNTIF('(비공개)국외인증'!$P:$P,"*반려*") -> 5 | M20: =COUNTIFS('(비공개)국외인증'!$U:$U,"*반려완료*",'(비공개)국외인증'!V:V,"*종결*") -> 69 | N20: =COUNTIFS('(비공개)국외인증'!U:U,"*반려요청*",'(비공개)국외인증'!V:V,"*검토반*") -> 0 | O20: =COUNTIFS('(비공개)국외인증'!U:U,"*보류*",'(비공개)국외인증'!V:V,"*반려필요*") -> 0 | P20: =SUM(L20:O20) -> 74
B21: 합계 | D21: =SUM(D17:D20) -> 331 | E21: =SUM(E17:E20) -> 8 | F21: =SUM(F17:F20) -> 161 | G21: =SUM(G17:G20) -> 169 | H21: =SUM(H17:H20) -> 160 | I21: =SUM(I17:I20) -> 1 | J21: =SUM(J17:J20) -> 1 | K21: =SUM(K17:K20) -> 162 | ... P21: =SUM(P17:P20) -> 161
D22: 신청 건수: 평가종료 소계 + 평가중 소계 | H22: 의견통보: 사업자에게 정보비공개 신청 검토 의견 통보 | L22: 사업 반려: 정보비공개 신청하였으나, 외부사업이 평가/인증 단계에서 반려
H23: 의견 보완: 검토 의견 보완 후 재신청 | L23: 반려 완료: 사업자 요청에 의한 반려 완료
H24: 신규 신청: 정보비공개 신청되어 평가 필요 | L24: 사업자 요청: 사업자가 정보 비공개 신청 철회하여 반려 요청
L25: 보류: 평가가 불필요해진 사업
B26: 2026.06.16
B27: 구분 | D27: 신청건수 | E27: 정보 비공개 신청 평가 종료 | H27: 평가중 | L27: 평가 불필요
E28: 승인 | F28: 반려 | G28: 소계 | H28: 사업자 | I28: 검토반 | K28: 소계 | L28: 사업 반려 | M28: 정보 비공개 신청 반려 | P28: 소계
H29: 의견 통보 | I29: 의견 보완 | J29: 신규 신청 | M29: 완료 | N29: 사업자 요청 | O29: 보류(반려 필요)
B30: 평가 (정보비공개) | C30: 국내 | D30: 106 | E30: 6 | F30: 59 | G30: 65 | H30: 39 | I30: 1 | J30: 1 | K30: 41 | L30: 39 | M30: 20 | N30: 0 | O30: 0 | P30: 59
C31: 국외 | D31: 24 | E31: 0 | F31: 9 | G31: 9 | H31: 15 | I31: 0 | J31: 0 | K31: 15 | L31: 0 | M31: 9 | N31: 0 | O31: 0 | P31: 9
B32: 인증 (정보비공개) | C32: 국내 | D32: 126 | E32: 2 | F32: 19 | G32: 21 | H32: 105 | I32: 0 | J32: 0 | K32: 105 | L32: 1 | M32: 4 | N32: 14 | O32: 0 | P32: 19
C33: 국외 | D33: 75 | E33: 0 | F33: 74 | G33: 74 | H33: 1 | I33: 0 | J33: 0 | K33: 1 | L33: 5 | M33: 69 | N33: 0 | O33: 0 | P33: 74
B34: 합계 | D34: 331 | E34: 8 | F34: 161 | G34: 169 | H34: 160 | I34: 1 | J34: 1 | K34: 162 | L34: 45 | M34: 102 | N34: 14 | O34: 0 | P34: 161
D35: =D17-D30 -> 0 | E35: =E17-E30 -> 0 | F35: =F17-F30 -> 0 | G35: =G17-G30 -> 0 | H35: =H17-H30 -> 0 | I35: =I17-I30 -> 0 | J35: =J17-J30 -> 0 | K35: =K17-K30 -> 0 | ... P35: =P17-P30 -> 0
D36: =D18-D31 -> 0 | E36: =E18-E31 -> 0 | F36: =F18-F31 -> 0 | G36: =G18-G31 -> 0 | H36: =H18-H31 -> 0 | I36: =I18-I31 -> 0 | J36: =J18-J31 -> 0 | K36: =K18-K31 -> 0 | ... P36: =P18-P31 -> 0
D37: =D19-D32 -> 0 | E37: =E19-E32 -> 0 | F37: =F19-F32 -> 0 | G37: =G19-G32 -> 0 | H37: =H19-H32 -> 0 | I37: =I19-I32 -> 0 | J37: =J19-J32 -> 0 | K37: =K19-K32 -> 0 | ... P37: =P19-P32 -> 0
D38: =D20-D33 -> 0 | E38: =E20-E33 -> 0 | F38: =F20-F33 -> 0 | G38: =G20-G33 -> 0 | H38: =H20-H33 -> 0 | I38: =I20-I33 -> 0 | J38: =J20-J33 -> 0 | K38: =K20-K33 -> 0 | ... P38: =P20-P33 -> 0
B40: 2024.11.15
B41: 구분 | D41: 신청건수 | E41: 정보 비공개 평가 완료 | H41: 사업 승인 전 | I41: 평가중
E42: 승인 | F42: 반려 | G42: 소계 | I42: 사업 승인 후(정보비공개 평가대상) | M42: 반려 사업 | N42: 소계 (보완/평가중)
I43: 기 평가 완료 (승인 건 제외) | J43: 추가 평가 대상 | K43: 반려 완료
L44: 반려 요청
B45: 평가 (정보비공개) | C45: 국내 | D45: 100 | E45: 2 | F45: 39 | G45: 41 | H45: 6 | I45: 53 | J45: 0 | K45: 1 | L45: 0 | M45: 38 | N45: 52 | O45: 사업 승인 전에 씨큐브 제외, 기 평가 완료에 씨큐브 포함(향후 승인 건수(2건)에 추가될 예정)
C46: 국외 | D46: 24 | E46: 0 | F46: 9 | G46: 9 | H46: 0 | I46: 24 | J46: 0 | K46: 9 | L46: 0 | M46: 0 | N46: 15
B47: 인증 (정보비공개) | C47: 국내 | D47: 126 | E47: 1 | F47: 5 | G47: 6 | H47: 4 | I47: 116 | J47: 0 | K47: 4 | L47: 0 | M47: 1 | N47: 112
C48: 국외 | D48: 75 | E48: 0 | F48: 74 | G48: 74 | H48: 0 | I48: 70 | J48: 0 | K48: 69 | L48: 0 | M48: 5 | N48: 1
B49: 합계 | D49: 325 | E49: 3 | F49: 127 | G49: 130 | H49: 10 | I49: 263 | J49: 0 | K49: 83 | L49: 0 | M49: 44 | N49: 180
B50: * 정보비공개 DB : 2024-06-10 | H50: 사업 승인 전 : 정보비공개 신청했으나, 사업 승인 전 단계
H51: 기 평가 완료 : 신청 사유 평가 후 내용 통보(최종 승인건수 제외)
H52: 추가 평가 대상 : 보완 완료 또는 신규 사업 승인 건이며, 다음 버전에서 "기 평가 완료" 항목으로 이동
H53: 반려 완료 : 사업자 요청에 의한 반려 처리 완료
H54: 반려 요청 : 사업자 요청에 의한 반려 신청
H55: 반려 사업 : 정보비공개 신청하였으나, 사업이 평가/인증 단계에서 반려(반려 필요)
B58: 2024.10.02 기준
B59: 구분 | D59: 신청건수 | E59: 정보 비공개 평가 완료 | H59: 사업 승인 전 | I59: 평가중
E60: 승인 | F60: 반려 | G60: 소계 | I60: 사업 승인 후(정보비공개 평가대상) | M60: 반려 사업 | N60: 소계
I61: 기 평가 완료 | J61: 추가 평가 대상 | K61: 반려 완료
L62: 반려 요청
B63: 평가 (정보비공개) | C63: 국내 | D63: 99 | E63: 2 | F63: 39 | G63: 41 | H63: 6 | I63: 51 | J63: 1 | K63: 1 | L63: 0 | M63: 38 | N63: 51
C64: 해외 | D64: 24 | E64: 0 | F64: 9 | G64: 9 | H64: 0 | I64: 24 | J64: 0 | K64: 9 | L64: 0 | M64: 0 | N64: 15
B65: 인증 (정보비공개) | C65: 국내 | D65: 125 | E65: 1 | F65: 5 | G65: 6 | H65: 3 | I65: 116 | J65: 0 | K65: 4 | L65: 0 | M65: 1 | N65: 112
C66: 해외 | D66: 75 | E66: 0 | F66: 74 | G66: 74 | H66: 0 | I66: 70 | J66: 0 | K66: 69 | L66: 0 | M66: 5 | N66: 1
B67: 합계 | D67: 323 | E67: 3 | F67: 127 | G67: 130 | H67: 9 | I67: 261 | J67: 1 | K67: 83 | L67: 0 | M67: 44 | N67: 179
B69: 평가 (정보비공개) | C69: 국내 | D69: =D45-D63 -> 1 | E69: =E45-E63 -> 0 | F69: =F45-F63 -> 0 | G69: =G45-G63 -> 0 | H69: =H45-H63 -> 0 | I69: =I45-I63 -> 2 | J69: =J45-J63 -> -1 | K69: =K45-K63 -> 0 | ... N69: =N45-N63 -> 1
C70: 해외 | D70: =D46-D64 -> 0 | E70: =E46-E64 -> 0 | F70: =F46-F64 -> 0 | G70: =G46-G64 -> 0 | H70: =H46-H64 -> 0 | I70: =I46-I64 -> 0 | J70: =J46-J64 -> 0 | K70: =K46-K64 -> 0 | ... N70: =N46-N64 -> 0
B71: 인증 (정보비공개) | C71: 국내 | D71: =D47-D65 -> 1 | E71: =E47-E65 -> 0 | F71: =F47-F65 -> 0 | G71: =G47-G65 -> 0 | H71: =H47-H65 -> 1 | I71: =I47-I65 -> 0 | J71: =J47-J65 -> 0 | K71: =K47-K65 -> 0 | ... N71: =N47-N65 -> 0
C72: 해외 | D72: =D48-D66 -> 0 | E72: =E48-E66 -> 0 | F72: =F48-F66 -> 0 | G72: =G48-G66 -> 0 | H72: =H48-H66 -> 0 | I72: =I48-I66 -> 0 | J72: =J48-J66 -> 0 | K72: =K48-K66 -> 0 | ... N72: =N48-N66 -> 0
C73: 합계 | D73: =D49-D67 -> 2 | E73: =E49-E67 -> 0 | F73: =F49-F67 -> 0 | G73: =G49-G67 -> 0 | H73: =H49-H67 -> 1 | I73: =I49-I67 -> 2 | J73: =J49-J67 -> -1 | K73: =K49-K67 -> 0 | ... N73: =N49-N67 -> 1
B78: 2022년 검토 배분
B79: 44693 | C79: 국내평가 | D79: 국내인증 | E79: 국외평가 | F79: 국외인증 | G79: 합계
B80: 에코시안 | C80: 24 | D80: 50 | E80: 10 | F80: 9 | G80: =SUM(C80:F80) -> 93
B81: KECM | C81: 24 | D81: 45 | F81: 60 | G81: =SUM(C81:F81) -> 129
B82: 합계 | C82: =SUM(C80:C81) -> 48 | D82: =SUM(D80:D81) -> 95 | E82: =SUM(E80:E81) -> 10 | F82: =SUM(F80:F81) -> 69 | G82: =SUM(G80:G81) -> 222 | H82: ORS 다운, 2022.05.04
B83: 10월 13일 | C83: 국내평가 | D83: 국내인증 | E83: 국외평가 | F83: 국외인증 | G83: 합계
B84: 에코시안 | D84: 12 | E84: 11 | F84: 1 | G84: =SUM(C84:F84) -> 24
B85: KECM | G85: =SUM(C85:F85) -> 0
B86: 합계 | C86: =SUM(C84:C85) -> 0 | D86: =SUM(D84:D85) -> 12 | E86: =SUM(E84:E85) -> 11 | F86: =SUM(F84:F85) -> 1 | G86: =SUM(G84:G85) -> 24 | H86: ORS 다운, 2022.10.13
B87: 11월 30일 | C87: 국내평가 | D87: 국내인증 | E87: 국외평가 | F87: 국외인증 | G87: 합계
B88: 에코시안 | C88: 2 | G88: =SUM(C88:F88) -> 2
B89: KECM | G89: =SUM(C89:F89) -> 0
B90: 합계 | C90: =SUM(C88:C89) -> 2 | D90: =SUM(D88:D89) -> 0 | E90: =SUM(E88:E89) -> 0 | F90: =SUM(F88:F89) -> 0 | G90: =SUM(G88:G89) -> 2 | H90: ORS 다운, 2022.11.30
B92: 2023년 검토 배분
B93: 03월 | C93: 국내평가 | D93: 국내인증 | E93: 국외평가 | F93: 국외인증 | G93: 합계
B94: 에코시안 | C94: 2 | D94: 5 | E94: 3 | G94: =SUM(C94:F94) -> 10
B95: KECM | G95: =SUM(C95:F95) -> 0
B96: 합계 | C96: =SUM(C94:C95) -> 2 | D96: =SUM(D94:D95) -> 5 | E96: =SUM(E94:E95) -> 3 | F96: =SUM(F94:F95) -> 0 | G96: =SUM(G94:G95) -> 10 | H96: ORS 다운, 2023.03.27
B97: 06월 | C97: 국내평가 | D97: 국내인증 | E97: 국외평가 | F97: 국외인증 | G97: 합계
B98: 에코시안 | D98: 3 | G98: =SUM(C98:F98) -> 3
B99: KECM | G99: =SUM(C99:F99) -> 0
B100: 합계 | C100: =SUM(C98:C99) -> 0 | D100: =SUM(D98:D99) -> 3 | E100: =SUM(E98:E99) -> 0 | F100: =SUM(F98:F99) -> 0 | G100: =SUM(G98:G99) -> 3 | H100: ORS 다운, 2023.06.19
B101: 09월 | C101: 국내평가 | D101: 국내인증 | E101: 국외평가 | F101: 국외인증 | G101: 합계
B102: 에코시안 | C102: 1 | D102: 1 | G102: =SUM(C102:F102) -> 2
B103: KECM | G103: =SUM(C103:F103) -> 0
B104: 합계 | C104: =SUM(C102:C103) -> 1 | D104: =SUM(D102:D103) -> 1 | E104: =SUM(E102:E103) -> 0 | F104: =SUM(F102:F103) -> 0 | G104: =SUM(G102:G103) -> 2 | H104: ORS 다운, 2023.09.19
B105: 12월 | C105: 국내평가 | D105: 국내인증 | E105: 국외평가 | F105: 국외인증 | G105: 합계
B106: 에코시안 | G106: =SUM(C106:F106) -> 0
B107: KECM | G107: =SUM(C107:F107) -> 0
B108: 합계 | C108: =SUM(C106:C107) -> 0 | D108: =SUM(D106:D107) -> 0 | E108: =SUM(E106:E107) -> 0 | F108: =SUM(F106:F107) -> 0 | G108: =SUM(G106:G107) -> 0
B110: 2024년 검토 배분
B111: 03월 | C111: 국내평가 | D111: 국내인증 | E111: 국외평가 | F111: 국외인증 | G111: 합계
B112: 에코시안 | G112: =SUM(C112:F112) -> 0
B113: KECM | G113: =SUM(C113:F113) -> 0
B114: 합계 | C114: =SUM(C112:C113) -> 0 | D114: =SUM(D112:D113) -> 0 | E114: =SUM(E112:E113) -> 0 | F114: =SUM(F112:F113) -> 0 | G114: =SUM(G112:G113) -> 0 | H114: ORS 다운, 2024.03.29
B115: 06월 | C115: 국내평가 | D115: 국내인증 | E115: 국외평가 | F115: 국외인증 | G115: 합계
B116: 에코시안 | C116: 1 | D116: 4 | G116: =SUM(C116:F116) -> 5
B117: KECM | G117: =SUM(C117:F117) -> 0
B118: 합계 | C118: =SUM(C116:C117) -> 1 | D118: =SUM(D116:D117) -> 4 | E118: =SUM(E116:E117) -> 0 | F118: =SUM(F116:F117) -> 0 | G118: =SUM(G116:G117) -> 5 | H118: ORS 다운, 2024.06.10
B119: 09월 | C119: 국내평가 | D119: 국내인증 | E119: 국외평가 | F119: 국외인증 | G119: 합계
B120: 에코시안 | G120: =SUM(C120:F120) -> 0
B121: KECM | G121: =SUM(C121:F121) -> 0
...

Sheet (비공개)국내평가
E1: 정보비공개 DB | I1: 국내평가 DB(참고용)
A2: 번호 | B2: 사업유형 | C2: 사업명 | D2: 업체명 | E2: 정보비공개 신청일 | F2: 관장기관 | G2: 처리일 | H2: 진행상태 | I2: 사업 신청일 | J2: 평가 가능 여부 | K2: 처리이력 | L2: 현재 상태 | M2: h | N2: 진행상태 | O2: 현 위치 | P2: 검토대상 | Q2: 진행상태 | R2: 현 위치 | S2: 업데이트 | T2: 담당자 | U2: 비고 | V2: 권리 | W2: 대외비 자료 | X2: 계약서류 | Y2: 연료 사용량 | Z2: 공정 도식도 | AA2: 영업비밀 | AB2: 내규방침 제출여부 | AC2: 비공개 신청사유 | AD2: 특이사항
A3: 1 | B3: 단일감축사업 | C3: 생태산업개발을 통한 미세먼지 및 온실가스 감축 사업-산단 친환경설비 인프라지원 | D3: (주)신우테크 | E3: =VLOOKUP(C3,'외부사업 비공개승인관리_국내'!$C:$H,4,FALSE) -> 2025-12-15 | F3: =VLOOKUP(C3,'외부사업 비공개승인관리_국내'!$C:$H,5,FALSE) -> 산업통상부 | G3: =VLOOKUP(C3,'외부사업 비공개승인관리_국내'!$C:$H,6,FALSE) -> 2026-01-15 | H3: =VLOOKUP(C3,'외부사업 비공개승인관리_국내'!$C:$H,3,FALSE) -> 보완요청 | I3: =LEFT(VLOOKUP(C3,'국내평가(ORS)'!P:AO,26,0),10) -> 2025-12-15 | J3: =IF(I3=E3,"O","X") -> O | K3: =VLOOKUP(C3, '국내평가(ORS)'!P:AL, 23, 0) -> 평가반려 2025-12-16 | L3: =VLOOKUP(C3, '국내평가(ORS)'!A:AL, 2, 0) -> 반려 | Q3: 반려요청 | R3: 사업자 | S3: 46056 | T3: 에코시안 | U3: 해당 사업이 반려(사업자 요청)되었으므로 철회하도록 통보(26.1.14)
A4: 2 | B4: 묶음감축사업 | C4: 서울시 20212023년 LED 도로조명 교체를 통한 온실가스 감축사업 | D4: 서울특별시 | E4: =VLOOKUP(C4,'외부사업 비공개승인관리_국내'!$C:$H,4,FALSE) -> 2025-11-04 | F4: =VLOOKUP(C4,'외부사업 비공개승인관리_국내'!$C:$H,5,FALSE) -> 산업통상부 | G4: =VLOOKUP(C4,'외부사업 비공개승인관리_국내'!$C:$H,6,FALSE) -> 2026-01-22 | H4: =VLOOKUP(C4,'외부사업 비공개승인관리_국내'!$C:$H,3,FALSE) -> 보완요청 | I4: =LEFT(VLOOKUP(C4,'국내평가(ORS)'!P:AO,26,0),10) -> 2025-11-04 | J4: =IF(I4=E4,"O","X") -> O | K4: =VLOOKUP(C4, '국내평가(ORS)'!P:AL, 23, 0) -> [보완3차]신청 2026-09-08 (9일째) | L4: =VLOOKUP(C4, '국내평가(ORS)'!A:AL, 2, 0) -> 보완3차_검토중 | Q4: 보완요청 | R4: 사업자 | S4: 46044 | T4: KECM | U4: (1차) 「명세서 공개 심사위원회 구성 및 운영에 관한 규정」 [별표1]에 따라 비공개 신청사유를 하기와 같이 보완 요청 드립니다. - 사업계획서(모니터링보고서) 내용 중 보안유지 필요 부분, 위치 및 사유 구체화(증빙자료는 정보공개 대상 아님) - 필요 시 정보 비공개사유에 대한 증빙자료(회사 내규, 계약서, 설비 관련 자료 등)를 제출 요청 단, 투명성 원칙에 따라 민감사항이 사업계획서 및 모니터링보고서, 검증 보고서 내 문서에 포함되지 않아도 되는 경우(필수 작성 항목이 아닌 경우) 해당사항은 증빙자료로만 제출하고 본 비공개신청 건은 철회 신청해주시기 바랍니다. | AC4: 업체정보보호(내부 정보) | AD4: (1차 통보) 2026.1.22
A5: 3 | B5: 단일감축사업 | C5: 명광아스콘의 B-C유에서 LPG로 연료전환을 통한 온실가스 감축 외부사업 | D5: (주)삼천리 | E5: =VLOOKUP(C5,'외부사업 비공개승인관리_국내'!$C:$H,4,FALSE) -> 2025-01-21 | F5: =VLOOKUP(C5,'외부사업 비공개승인관리_국내'!$C:$H,5,FALSE) -> 산업통상부 | G5: =VLOOKUP(C5,'외부사업 비공개승인관리_국내'!$C:$H,6,FALSE) -> 2025-09-08 | H5: =VLOOKUP(C5,'외부사업 비공개승인관리_국내'!$C:$H,3,FALSE) -> 심의완료 | I5: =LEFT(VLOOKUP(C5,'국내평가(ORS)'!P:AO,26,0),10) -> 2025-01-21 | J5: =IF(I5=E5,"O","X") -> O | K5: =VLOOKUP(C5, '국내평가(ORS)'!P:AL, 23, 0) -> [보완3차]착수신고 2026-01-29 | L5: =VLOOKUP(C5, '국내평가(ORS)'!A:AL, 2, 0) -> 승인 | Q5: 심의승인 | R5: 종결 | S5: 45916 | T5: KECM | U5: 기업 경영에 관련된 정보 외부유출 방지 : 사업장 설비 현황, 연료사용량은 기업 경영에 중요한 정보로써 타 업체로의 정보유출 방지 필요 - 설비 현황 (사업계획서 12-14p, 34p) - 연료 사용량 (사업계획서 22-29p)
A6: 4 | B6: 묶음감축사업 | C6: (주)전유산업 외 2개사의 고효율 공기압축기 교체를 통한 온실가스 감축사업 | D6: 에스피앤지주식회사 | E6: =VLOOKUP(C6,'외부사업 비공개승인관리_국내'!$C:$H,4,FALSE) -> 2025-04-21 | F6: =VLOOKUP(C6,'외부사업 비공개승인관리_국내'!$C:$H,5,FALSE) -> 산업통상부 | G6: =VLOOKUP(C6,'외부사업 비공개승인관리_국내'!$C:$H,6,FALSE) -> 2025-05-07 | H6: =VLOOKUP(C6,'외부사업 비공개승인관리_국내'!$C:$H,3,FALSE) -> 반려 | I6: =LEFT(VLOOKUP(C6,'국내평가(ORS)'!P:AO,26,0),10) -> 2022-10-07 | J6: =IF(I6=E6,"O","X") -> X | K6: =VLOOKUP(C6, '국내평가(ORS)'!P:AL, 23, 0) -> [보완3차]착수신고 2026-09-09 | L6: =VLOOKUP(C6, '국내평가(ORS)'!A:AL, 2, 0) -> 승인 | P6: =IF(AND(H6<>"반려", L6<>"반려"),"검토가능","") | Q6: 반려완료 | R6: 종결 | S6: 45833 | T6: KECM | U6: 사업자 반려 요청
A7: 5 | B7: 단일감축사업 | C7: 부산경남우유협동조합 울산공장의 B-C유에서 LPG로 연료전환을 통한 온실가스 감축 외부사업 | D7: (주)삼천리 | E7: =VLOOKUP(C7,'외부사업 비공개승인관리_국내'!$C:$H,4,FALSE) -> 2025-01-07 | F7: =VLOOKUP(C7,'외부사업 비공개승인관리_국내'!$C:$H,5,FALSE) -> 산업통상부 | G7: =VLOOKUP(C7,'외부사업 비공개승인관리_국내'!$C:$H,6,FALSE) -> 2025-09-08 | H7: =VLOOKUP(C7,'외부사업 비공개승인관리_국내'!$C:$H,3,FALSE) -> 심의완료 | I7: =LEFT(VLOOKUP(C7,'국내평가(ORS)'!P:AO,26,0),10) -> 2025-01-07 | J7: =IF(I7=E7,"O","X") -> O | K7: =VLOOKUP(C7, '국내평가(ORS)'!P:AL, 23, 0) -> [보완1차]착수신고 2026-01-29 | L7: =VLOOKUP(C7, '국내평가(ORS)'!A:AL, 2, 0) -> 승인 | Q7: 심의승인 | R7: 종결 | S7: 45916 | T7: 에코시안_남혜원
A8: 6 | B8: 단일감축사업 | C8: 엑시콘 태양광 발전설비 설치 및 자가사용을 통한 온실가스 감축사업 | D8: (주)엑시콘 천안지점 | E8: =VLOOKUP(C8,'외부사업 비공개승인관리_국내'!$C:$H,4,FALSE) -> 2026-05-19 | F8: =VLOOKUP(C8,'외부사업 비공개승인관리_국내'!$C:$H,5,FALSE) -> 기후에너지환경부 | G8: =VLOOKUP(C8,'외부사업 비공개승인관리_국내'!$C:$H,6,FALSE) -> 2026-05-20 | H8: =VLOOKUP(C8,'외부사업 비공개승인관리_국내'!$C:$H,3,FALSE) -> 반려 | I8: =LEFT(VLOOKUP(C8,'국내평가(ORS)'!P:AO,26,0),10) -> 2024-11-18 | J8: =IF(I8=E8,"O","X") -> X | K8: =VLOOKUP(C8, '국내평가(ORS)'!P:AL, 23, 0) -> [보완3차]심의승인 2026-09-08 | L8: =VLOOKUP(C8, '국내평가(ORS)'!A:AL, 2, 0) -> 승인 | P8: =IF(AND(H8<>"반려", L8<>"반려"),"검토가능","") | Q8: 반려완료 | R8: 종결 | S8: 46168 | T8: 에코시안_조은지 | U8: ※ 사업자 요청으로 반려 처리 <신청사유> 기업 경영에 관련된 정보 외부유출 방지 - 사업장 설비 현황, 연료사용량은 기업 경영에 중요한 정보로써 타 업체로의 정보유출 방지 필요 - 설비 현황 (사업계획서 13페이지), 재생에너지 발전설비를 통해 자가 사용된 순 전력량 (사업계획서 20페이지) <1차 통보> ∙ 「명세서 공개 심사위원회 구성 및 운영에 관한 규정」 [별표1]에 따라 비공개 신청사유를 하기와 같이 보완 요청 드립니다. - 사업계획서 내용 중 보안유지 필요 사유 구체화 필요(증빙자료는 정보공개 대상 아님) - 필요 시 정보 비공개사유에 대한 증빙자료 제출 필요하며, 신청사유와 관련된 자료로 첨부(회사 내규, 계약서, 설비 관련 자료 등) ∙ 단, 투명성 원칙에 따라 민감사항이 사업계획서 내 문서에 포함되지 않아도 되는 경우(필수 작성 항목이 아닌 경우) 해당 사항은 증빙자료로만 제출하고 본 비공개 신청건은 철회 신청해주시기 바랍니다. | AC8: 업체정보보호(내부 정보)
A9: 7 | B9: 묶음감축사업 | C9: 주택용 태양광 발전 시스템을 이용한 자가사용 묶음 감축사업 | D9: (주)후시파트너스 | E9: =VLOOKUP(C9,'외부사업 비공개승인관리_국내'!$C:$H,4,FALSE) -> 2024-10-16 | F9: =VLOOKUP(C9,'외부사업 비공개승인관리_국내'!$C:$H,5,FALSE) -> 기후에너지환경부 | G9: =VLOOKUP(C9,'외부사업 비공개승인관리_국내'!$C:$H,6,FALSE) -> 2025-01-09 | H9: =VLOOKUP(C9,'외부사업 비공개승인관리_국내'!$C:$H,3,FALSE) -> 보완요청 | I9: =LEFT(VLOOKUP(C9,'국내평가(ORS)'!P:AO,26,0),10) -> 2024-10-16 | J9: =IF(I9=E9,"O","X") -> O | K9: =VLOOKUP(C9, '국내평가(ORS)'!P:AL, 23, 0) -> 평가반려 2026-07-27 | L9: =VLOOKUP(C9, '국내평가(ORS)'!A:AL, 2, 0) -> 반려 | M9: 승인 전 | N9: 선택 | O9: 선택 | P9: =IF(AND(H9<>"반려", L9<>"반려"),"검토가능","") | Q9: 보완요청 | R9: 사업자 | S9: 45611 | T9: 에코시안_조영우 | U9: 제출서류 미비로 보완 요청. 보완 요청 통보 문구 기재(공단 통보)
A10: 8 | B10: 묶음감축사업 | C10: 2015년 춘천시 도로조명 LED 교체를 통한 묶음 감축사업 | D10: 춘천시 | E10: =VLOOKUP(C10,'외부사업 비공개승인관리_국내'!$C:$H,4,FALSE) -> 2024-07-03 | F10: =VLOOKUP(C10,'외부사업 비공개승인관리_국내'!$C:$H,5,FALSE) -> 산업통상부 | G10: =VLOOKUP(C10,'외부사업 비공개승인관리_국내'!$C:$H,6,FALSE) -> 2025-06-12 | H10: =VLOOKUP(C10,'외부사업 비공개승인관리_국내'!$C:$H,3,FALSE) -> 심의완료 | I10: =LEFT(VLOOKUP(C10,'국내평가(ORS)'!P:AO,26,0),10) -> 2018-01-03 | J10: =IF(I10=E10,"O","X") -> X | K10: =VLOOKUP(C10, '국내평가(ORS)'!P:AL, 23, 0) -> [보완3차]착수신고 2021-09-30 | L10: =VLOOKUP(C10, '국내평가(ORS)'!A:AL, 2, 0) -> 승인 | M10: 검토필요 | N10: 보완요청 | O10: 사업자 | Q10: 심의승인 | R10: 종결 | S10: 45833 | T10: 에코시안_조영우 | U10: 심의 승인 | AC10: 업체정보보호(내부 정보)
A11: 9 | B11: 묶음감축사업 | C11: 2022년 춘천시 도로조명 LED 교체를 통한 감축사업 | D11: 춘천시 | E11: =VLOOKUP(C11,'외부사업 비공개승인관리_국내'!$C:$H,4,FALSE) -> 2025-10-28 | F11: =VLOOKUP(C11,'외부사업 비공개승인관리_국내'!$C:$H,5,FALSE) -> 산업통상부 | G11: =VLOOKUP(C11,'외부사업 비공개승인관리_국내'!$C:$H,6,FALSE) -> 2025-04-28 | H11: =VLOOKUP(C11,'외부사업 비공개승인관리_국내'!$C:$H,3,FALSE) -> 보완완료 | I11: =LEFT(VLOOKUP(C11,'국내평가(ORS)'!P:AO,26,0),10) -> 2023-01-11 | J11: =IF(I11=E11,"O","X") -> X | K11: =VLOOKUP(C11, '국내평가(ORS)'!P:AL, 23, 0) -> [보완3차]문서재제출요청 2026-02-02 | L11: =VLOOKUP(C11, '국내평가(ORS)'!A:AL, 2, 0) -> 보완3차_문서보완중 | M11: 승인 전 | N11: 선택 | O11: 선택 | P11: =IF(AND(H11<>"반려", L11<>"반려"),"검토가능","") -> 검토가능 | Q11: 보완완료 | R11: 검토반 | S11: 45992 | T11: 에코시안 | U11: [1차 통보] ㅇ 「명세서 공개 심사위원회 구성 및 운영에 관한 규정」 [별표1]에 따라 비공개 신청사유를 하기와 같이 보완 요청 드립니다. - 사업계획서(모니터링보고서) 내용 중 보안유지 필요 부분, 위치 및 사유 구체화(증빙자료는 정보공개 대상 아님) - 필요 시 정보 비공개사유에 대한 증빙자료 제출 요청 ㅇ 단, 투명성 원칙에 따라 민감사항이 사업계획서 및 모니터링보고서, 검증 보고서 내 문서에 포함되지 않아도 되는 경우(필수 작성 항목이 아닌 경우) 해당사항은 증빙자료로만 제출하고 본 비공개신청건은 철회 신청해주시기 바랍니다. [1차 보완] 정보비공개 판단 기준은 &lsquo;온실가스배출량명세서 정보의 공개 및 비공개 신청 심사 기준&rsquo;을 준용하고 있는데, 이 규정은 법적으로 제출이 의무화된 온실가스배출관리업체, 할당대상업체의 명세서에 대한 규정임. 그에 비해 업체가 자발적으로 참여하고 제출하는 외부사업의 사업계획서의 비공개 심사에는 업체의 의견을 보다 존중해야 할 것으로 사료됨. 본 외부사업의 사업계획서 상 비공개를 희망하는 부분 및 그 사유를 다음과 같이 기술함. 1.2. 사업의 위치 (3) 사업의 주소, 보안등 번호, 전주번호 - 이 사업의 대상인 도로조명의 주소, 등번호, 전주번호는 중요한 정보이며, 그 목록 전체를 춘천시가 일반에게 공개할 의무는 없으며, 오남용될 가능성도 있어 춘천시는 이 정보의 공개를 원하지 않음 [근거: 공공기관의 정보공개에 관한 법률 제9조제1항제5호] 2. 베이스라인 및 모니터링 방법론, 3. 온실가스 감축량 산정, 4. 모니터링 계획 - 본 외부사업의 베이스라인 및 모니터링 방법, 온실가스 감축량 산정 방법, 모니터링 계획이 춘천시 고유의 특성을 반영하여 구체적으로 기술되어 있기 때문에 정보공개를 원하지 않음. 또한, 이 사업계획서를 작성하기 위하여 춘천시가 오랜 기간 동안 시간과 노력과 예산을 투자하여 작성한 연구성과물이기 때문에 무상으로 이를 일반인에게 공개하는 것은 공평하지 못하며, 시장질서에도 바람직하지 않다고 사료되므로 춘천시는 비공개를 요청함 [근거: 공공기관의 정보공개에 관한 법률 제9조제1항제5호,제7호] 6. 사업자 정보 - 사업자 담당자의 개인 정보 보호 차원에서 이 정보의 공개를 원하지 않음 [근거: 공공기관의 정보공개에 관한 법률 제9조제1항제6호] | AC11: 업체정보보호(내부 정보)
A12: 10 | B12: 묶음감축사업 | C12: 신성이앤에스 영덕군 태양광 발전시설의 리파워링 사업 | D12: 신성이앤에스 | E12: =VLOOKUP(C12,'외부사업 비공개승인관리_국내'!$C:$H,4,FALSE) -> 2024-01-29 | F12: =VLOOKUP(C12,'외부사업 비공개승인관리_국내'!$C:$H,5,FALSE) -> 기후에너지환경부 | G12: =VLOOKUP(C12,'외부사업 비공개승인관리_국내'!$C:$H,6,FALSE) -> 2025-01-09 | H12: =VLOOKUP(C12,'외부사업 비공개승인관리_국내'!$C:$H,3,FALSE) -> 보완요청 | I12: =LEFT(VLOOKUP(C12,'국내평가(ORS)'!P:AO,26,0),10) -> 2024-01-29 | J12: =IF(I12=E12,"O","X") -> O | K12: =VLOOKUP(C12, '국내평가(ORS)'!P:AL, 23, 0) -> [보완1차]보완요청 2024-03-11 | L12: =VLOOKUP(C12, '국내평가(ORS)'!A:AL, 2, 0) -> 보완1차_보완중 | M12: 승인 전 | N12: 선택 | O12: 선택 | P12: =IF(AND(H12<>"반려", L12<>"반려"),"검토가능","") -> 검토가능 | Q12: 보완요청 | R12: 사업자 | S12: 45380 | T12: KECM_조수민 | U12: 제출서류 미비로 보완 요청. 보완 요청 통보 문구 기재(공단 통보)
A13: 11 | B13: 묶음감축사업 | C13: 신성이앤에스 영동군 태양광 발전시설의 리파워링 사업 | D13: 신성이앤에스 | E13: =VLOOKUP(C13,'외부사업 비공개승인관리_국내'!$C:$H,4,FALSE) -> 2024-01-29 | F13: =VLOOKUP(C13,'외부사업 비공개승인관리_국내'!$C:$H,5,FALSE) -> 기후에너지환경부 | G13: =VLOOKUP(C13,'외부사업 비공개승인관리_국내'!$C:$H,6,FALSE) -> 2025-01-09 | H13: =VLOOKUP(C13,'외부사업 비공개승인관리_국내'!$C:$H,3,FALSE) -> 보완요청 | I13: =LEFT(VLOOKUP(C13,'국내평가(ORS)'!P:AO,26,0),10) -> 2024-01-29 | J13: =IF(I13=E13,"O","X") -> O | K13: =VLOOKUP(C13, '국내평가(ORS)'!P:AL, 23, 0) -> [보완2차]보완요청 2024-08-19 | L13: =VLOOKUP(C13, '국내평가(ORS)'!A:AL, 2, 0) -> 보완2차_보완중 | M13: 승인 전 | N13: 선택 | O13: 선택 | P13: =IF(AND(H13<>"반려", L13<>"반려"),"검토가능","") -> 검토가능 | Q13: 보완요청 | R13: 사업자 | S13: 45380 | T13: KECM_조수민 | U13: 제출서류 미비로 보완 요청. 보완 요청 통보 문구 기재(공단 통보)
A14: 12 | B14: 단일감축사업 | C14: 부산경남우유협동조합의 B-C유에서 도시가스(LNG)로 연료전환을 통한 온실가스 배출 외부사업 | D14: 부산경남우유협동조합 | E14: =VLOOKUP(C14,'외부사업 비공개승인관리_국내'!$C:$H,4,FALSE) -> 2024-07-02 | F14: =VLOOKUP(C14,'외부사업 비공개승인관리_국내'!$C:$H,5,FALSE) -> 산업통상부 | G14: =VLOOKUP(C14,'외부사업 비공개승인관리_국내'!$C:$H,6,FALSE) -> 2024-09-19 | H14: =VLOOKUP(C14,'외부사업 비공개승인관리_국내'!$C:$H,3,FALSE) -> 심의완료 | I14: =LEFT(VLOOKUP(C14,'국내평가(ORS)'!P:AO,26,0),10) -> 2023-11-16 | J14: =IF(I14=E14,"O","X") -> X | K14: =VLOOKUP(C14, '국내평가(ORS)'!P:AL, 23, 0) -> [보완3차]심의승인 2024-09-19 | L14: =VLOOKUP(C14, '국내평가(ORS)'!A:AL, 2, 0) -> 승인 | N14: 심의승인 | O14: 종결 | Q14: 심의승인 | R14: 종결 | S14: 45567 | T14: 에코시안_김명은 | AC14: 업체정보보호(내부 정보)
A15: 13 | B15: 단일감축사업 | C15: 씨큐브의 LPG에서 도시가스(LNG)로 연료전환을 통한 온실가스 배출 외부사업 | D15: 씨큐브(주) | E15: =VLOOKUP(C15,'외부사업 비공개승인관리_국내'!$C:$H,4,FALSE) -> 2024-10-11 | F15: =VLOOKUP(C15,'외부사업 비공개승인관리_국내'!$C:$H,5,FALSE) -> 산업통상부 | G15: =VLOOKUP(C15,'외부사업 비공개승인관리_국내'!$C:$H,6,FALSE) -> 2024-12-10 | H15: =VLOOKUP(C15,'외부사업 비공개승인관리_국내'!$C:$H,3,FALSE) -> 심의완료 | I15: =LEFT(VLOOKUP(C15,'국내평가(ORS)'!P:AO,26,0),10) -> 2023-08-18 | J15: =IF(I15=E15,"O","X") -> X | K15: =VLOOKUP(C15, '국내평가(ORS)'!P:AL, 23, 0) -> [보완3차]심의승인 2024-12-10 | L15: =VLOOKUP(C15, '국내평가(ORS)'!A:AL, 2, 0) -> 승인 | M15: 승인 전 | N15: 선택 | O15: 선택 | Q15: 심의승인 | R15: 종결 | S15: 45638 | T15: KECM_이태준 | U15: 사업계획서 내용 중 비공개 필요 부분 정확히 명시 필요(사업계획서 증빙자료는 정보공개 대상 아님) | AC15: 업체정보보호(내부 정보)
A16: 14 | B16: 단일감축사업 | C16: 엠함안(주) 목질계 바이오매스 연료 이용 열 공급을 통한 수용가의 화석연료 절감 및 온실가스 감축사업 | D16: 엠함안 | E16: =VLOOKUP(C16,'외부사업 비공개승인관리_국내'!$C:$H,4,FALSE) -> 2025-02-27 | F16: =VLOOKUP(C16,'외부사업 비공개승인관리_국내'!$C:$H,5,FALSE) -> 산업통상부 | G16: =VLOOKUP(C16,'외부사업 비공개승인관리_국내'!$C:$H,6,FALSE) -> 2025-03-07 | H16: =VLOOKUP(C16,'외부사업 비공개승인관리_국내'!$C:$H,3,FALSE) -> 반려 | I16: =LEFT(VLOOKUP(C16,'국내평가(ORS)'!P:AO,26,0),10) -> 2021-12-22 | J16: =IF(I16=E16,"O","X") -> X | K16: =VLOOKUP(C16, '국내평가(ORS)'!P:AL, 23, 0) -> [보완3차]착수신고 2024-04-16 | L16: =VLOOKUP(C16, '국내평가(ORS)'!A:AL, 2, 0) -> 승인 | M16: 검토필요 | N16: 보완요청 | O16: 사업자 | P16: =IF(AND(H16<>"반려", L16<>"반려"),"검토가능","") | Q16: 반려완료 | R16: 종결 | S16: 45769 | T16: 에코시안_조영우 | U16: 사업자 반려 요청 | AC16: 업체정보보호(업무상 비밀)
A17: 15 | B17: 단일감축사업 | C17: 대림아스콘의 B-C유에서 도시가스(LNG)로 연료전환을 통한 온실가스 배출 감축사업 | D17: 대림아스콘(주) | E17: =VLOOKUP(C17,'외부사업 비공개승인관리_국내'!$C:$H,4,FALSE) -> 2022-06-07 | F17: =VLOOKUP(C17,'외부사업 비공개승인관리_국내'!$C:$H,5,FALSE) -> 산업통상부 | G17: =VLOOKUP(C17,'외부사업 비공개승인관리_국내'!$C:$H,6,FALSE) -> 2023-04-25 | H17: =VLOOKUP(C17,'외부사업 비공개승인관리_국내'!$C:$H,3,FALSE) -> 보완요청 | I17: =LEFT(VLOOKUP(C17,'국내평가(ORS)'!P:AO,26,0),10) -> 2022-06-07 | J17: =IF(I17=E17,"O","X") -> O | K17: =VLOOKUP(C17, '국내평가(ORS)'!P:AL, 23, 0) -> [보완2차]심의승인 2023-03-17 | L17: =VLOOKUP(C17, '국내평가(ORS)'!A:AL, 2, 0) -> 승인 | M17: 검토필요 | N17: 보완요청 | O17: 사업자 | P17: =IF(AND(H17<>"반려", L17<>"반려"),"검토가능","") -> 검토가능 | Q17: 보완요청 | R17: 사업자 | S17: 45012 | T17: 에코시안_조영우 | U17: 사업계획서 내용 중 비공개 필요 부분 정확히 명시 필요(사업계획서 증빙자료는 정보공개 대상 아님)) | AC17: 내부방침
A18: 16 | B18: 묶음감축사업 | C18: 부산 해운대 클린에너지 학교 태양광발전 묶음 감축사업 | D18: 부산광역시교육청 | E18: =VLOOKUP(C18,'외부사업 비공개승인관리_국내'!$C:$H,4,FALSE) -> 2022-06-02 | F18: =VLOOKUP(C18,'외부사업 비공개승인관리_국내'!$C:$H,5,FALSE) -> 기후에너지환경부 | G18: =VLOOKUP(C18,'외부사업 비공개승인관리_국내'!$C:$H,6,FALSE) -> 2022-08-16 | H18: =VLOOKUP(C18,'외부사업 비공개승인관리_국내'!$C:$H,3,FALSE) -> 반려 | I18: =LEFT(VLOOKUP(C18,'국내평가(ORS)'!P:AO,26,0),10) -> 2021-06-21 | J18: =IF(I18=E18,"O","X") -> X | K18: =VLOOKUP(C18, '국내평가(ORS)'!P:AL, 23, 0) -> [보완2차]착수신고 2022-01-06 | L18: =VLOOKUP(C18, '국내평가(ORS)'!A:AL, 2, 0) -> 승인 | M18: 검토필요 | N18: 반려 | O18: 종결 | P18: =IF(AND(H18<>"반려", L18<>"반려"),"검토가능","") | Q18: 반려완료 | R18: 종결 | S18: 10월 13일 | T18: 에코시안_정인혜 | U18: 사업자 반려 요청 | AC18: 개인정보보호
A19: 17 | B19: 단일감축사업 | C19: 동신산업 평택공장의 B-C유에서 LNG로 연료전환을 통한 온실가스 배출 감축사업 | D19: 동신산업(주) | E19: =VLOOKUP(C19,'외부사업 비공개승인관리_국내'!$C:$H,4,FALSE) -> 2021-06-10 | F19: =VLOOKUP(C19,'외부사업 비공개승인관리_국내'!$C:$H,5,FALSE) -> 산업통상부 | G19: =VLOOKUP(C19,'외부사업 비공개승인관리_국내'!$C:$H,6,FALSE) -> 2022-06-02 | H19: =VLOOKUP(C19,'외부사업 비공개승인관리_국내'!$C:$H,3,FALSE) -> 보완요청 | I19: =LEFT(VLOOKUP(C19,'국내평가(ORS)'!P:AO,26,0),10) -> 2017-08-08 | J19: =IF(I19=E19,"O","X") -> X | K19: =VLOOKUP(C19, '국내평가(ORS)'!P:AL, 23, 0) -> [보완1차]착수신고 2021-05-26 | L19: =VLOOKUP(C19, '국내평가(ORS)'!A:AL, 2, 0) -> 승인 | M19: 검토필요 | N19: 보완요청 | O19: 사업자 | P19: =IF(AND(H19<>"반려", L19<>"반려"),"검토가능","") -> 검토가능 | Q19: 보완요청 | R19: 사업자 | S19: 5월 26일 | T19: 에코시안_정인혜 | U19: 사업계획서 내 보안유지 필요부분 구체화 필요 | AC19: 내부방침
A20: 18 | B20: 프로그램감축사업 | C20: 서울시사회복지협의회 태양광발전설비 설치를 통한 프로그램 온실가스 배출 감축사업 | D20: 사회복지법인 서울특별시사회복지 | E20: =VLOOKUP(C20,'외부사업 비공개승인관리_국내'!$C:$H,4,FALSE) -> 2021-05-03 | F20: =VLOOKUP(C20,'외부사업 비공개승인관리_국내'!$C:$H,5,FALSE) -> 기후에너지환경부 | G20: =VLOOKUP(C20,'외부사업 비공개승인관리_국내'!$C:$H,6,FALSE) -> 2025-02-25 | H20: =VLOOKUP(C20,'외부사업 비공개승인관리_국내'!$C:$H,3,FALSE) -> 반려 | I20: =LEFT(VLOOKUP(C20,'국내평가(ORS)'!P:AO,26,0),10) -> 2021-05-03 | J20: =IF(I20=E20,"O","X") -> O | K20: =VLOOKUP(C20, '국내평가(ORS)'!P:AL, 23, 0) -> 평가반려 2023-03-20 | L20: =VLOOKUP(C20, '국내평가(ORS)'!A:AL, 2, 0) -> 반려 | M20: X | N20: 선택 | O20: 선택 | P20: =IF(AND(H20<>"반려", L20<>"반려"),"검토가능","") | Q20: 선택 | R20: 종결 | S20: 5월 26일
A21: 19 | B21: 프로그램감축사업 | C21: 서울시사회복지협의회 태양광발전설비 설치를 통한 프로그램 온실가스 배출 감축사업 | D21: 사회복지법인 서울특별시사회복지 | E21: =VLOOKUP(C21,'외부사업 비공개승인관리_국내'!$C:$H,4,FALSE) -> 2021-05-03 | F21: =VLOOKUP(C21,'외부사업 비공개승인관리_국내'!$C:$H,5,FALSE) -> 기후에너지환경부 | G21: =VLOOKUP(C21,'외부사업 비공개승인관리_국내'!$C:$H,6,FALSE) -> 2025-02-25 | H21: =VLOOKUP(C21,'외부사업 비공개승인관리_국내'!$C:$H,3,FALSE) -> 반려 | I21: =LEFT(VLOOKUP(C21,'국내평가(ORS)'!P:AO,26,0),10) -> 2021-05-03 | J21: =IF(I21=E21,"O","X") -> O | K21: =VLOOKUP(C21, '국내평가(ORS)'!P:AL, 23, 0) -> 평가반려 2023-03-20 | L21: =VLOOKUP(C21, '국내평가(ORS)'!A:AL, 2, 0) -> 반려 | M21: X | N21: 선택 | O21: 선택 | P21: =IF(AND(H21<>"반려", L21<>"반려"),"검토가능","") | Q21: 선택 | R21: 종결 | S21: 5월 26일
A22: 20 | B22: 묶음감축사업 | C22: 공동폐수처리장의 고효율 터보블로워 도입을 통한 온실가스 감축사업 | D22: 부산녹산표면처리조합 | E22: =VLOOKUP(C22,'외부사업 비공개승인관리_국내'!$C:$H,4,FALSE) -> 2021-04-15 | F22: =VLOOKUP(C22,'외부사업 비공개승인관리_국내'!$C:$H,5,FALSE) -> 산업통상부 | G22: =VLOOKUP(C22,'외부사업 비공개승인관리_국내'!$C:$H,6,FALSE) -> 2025-02-25 | H22: =VLOOKUP(C22,'외부사업 비공개승인관리_국내'!$C:$H,3,FALSE) -> 반려 | I22: =LEFT(VLOOKUP(C22,'국내평가(ORS)'!P:AO,26,0),10) -> 2021-04-15 | J22: =IF(I22=E22,"O","X") -> O | K22: =VLOOKUP(C22, '국내평가(ORS)'!P:AL, 23, 0) -> 평가반려 2021-08-12 | L22: =VLOOKUP(C22, '국내평가(ORS)'!A:AL, 2, 0) -> 반려 | M22: X | N22: 선택 | O22: 선택 | P22: =IF(AND(H22<>"반려", L22<>"반려"),"검토가능","") | Q22: 선택 | R22: 종결 | S22: 5월 26일
A23: 21 | B23: 단일감축사업 | C23: 한미약품의 경유에서 LNG로 연료전환을 통한 온실가스 배출 감축사업 | D23: 한미약품(주) | E23: =VLOOKUP(C23,'외부사업 비공개승인관리_국내'!$C:$H,4,FALSE) -> 2021-02-04 | F23: =VLOOKUP(C23,'외부사업 비공개승인관리_국내'!$C:$H,5,FALSE) -> 산업통상부 | G23: =VLOOKUP(C23,'외부사업 비공개승인관리_국내'!$C:$H,6,FALSE) -> 2022-06-02 | H23: =VLOOKUP(C23,'외부사업 비공개승인관리_국내'!$C:$H,3,FALSE) -> 보완요청 | I23: =LEFT(VLOOKUP(C23,'국내평가(ORS)'!P:AO,26,0),10) -> 2017-08-11 | J23: =IF(I23=E23,"O","X") -> X | K23: =VLOOKUP(C23, '국내평가(ORS)'!P:AL, 23, 0) -> [보완2차]착수신고 2021-02-09 | L23: =VLOOKUP(C23, '국내평가(ORS)'!A:AL, 2, 0) -> 승인 | M23: 검토필요 | N23: 보완요청 | O23: 사업자 | P23: =IF(AND(H23<>"반려", L23<>"반려"),"검토가능","") -> 검토가능 | Q23: 보완요청 | R23: 사업자 | S23: 5월 26일 | T23: 에코시안_정인혜 | U23: 사업계획서 내 보안유지 필요부분 구체화 필요 | AC23: 내부방침
A24: 22 | B24: 단일감축사업 | C24: 검상산업단지 스팀생산 노후 LNG보일러 교체사업 | D24: 주식회사에코시안 | E24: =VLOOKUP(C24,'외부사업 비공개승인관리_국내'!$C:$H,4,FALSE) -> 2020-12-21 | F24: =VLOOKUP(C24,'외부사업 비공개승인관리_국내'!$C:$H,5,FALSE) -> 산업통상부 | G24: =VLOOKUP(C24,'외부사업 비공개승인관리_국내'!$C:$H,6,FALSE) -> 2025-02-25 | H24: =VLOOKUP(C24,'외부사업 비공개승인관리_국내'!$C:$H,3,FALSE) -> 반려 | I24: =LEFT(VLOOKUP(C24,'국내평가(ORS)'!P:AO,26,0),10) -> 2020-12-21 | J24: =IF(I24=E24,"O","X") -> O | K24: =VLOOKUP(C24, '국내평가(ORS)'!P:AL, 23, 0) -> [보완1차]평가반려 2021-05-28 | L24: =VLOOKUP(C24, '국내평가(ORS)'!A:AL, 2, 0) -> 반려 | M24: X | N24: 선택 | O24: 선택 | P24: =IF(AND(H24<>"반려", L24<>"반려"),"검토가능","") | Q24: 선택 | R24: 종결 | S24: 5월 26일
A25: 23 | B25: 단일감축사업 | C25: 태형기업(주) 양주사업장의 B-C유에서 도시가스(LNG)로 연료전환을 통한 온실가스(CO2) 배출 감축사업 | D25: 태형기업(주) | E25: =VLOOKUP(C25,'외부사업 비공개승인관리_국내'!$C:$H,4,FALSE) -> 2020-10-27 | F25: =VLOOKUP(C25,'외부사업 비공개승인관리_국내'!$C:$H,5,FALSE) -> 산업통상부 | G25: =VLOOKUP(C25,'외부사업 비공개승인관리_국내'!$C:$H,6,FALSE) -> 2022-06-02 | H25: =VLOOKUP(C25,'외부사업 비공개승인관리_국내'!$C:$H,3,FALSE) -> 보완요청 | I25: =LEFT(VLOOKUP(C25,'국내평가(ORS)'!P:AO,26,0),10) -> 2017-12-27 | J25: =IF(I25=E25,"O","X") -> X | K25: =VLOOKUP(C25, '국내평가(ORS)'!P:AL, 23, 0) -> [보완2차]착수신고 2021-08-25 | L25: =VLOOKUP(C25, '국내평가(ORS)'!A:AL, 2, 0) -> 승인 | M25: 검토필요 | N25: 보완요청 | O25: 사업자 | P25: =IF(AND(H25<>"반려", L25<>"반려"),"검토가능","") -> 검토가능 | Q25: 보완요청 | R25: 사업자 | S25: 5월 26일 | T25: 에코시안_정인혜 | U25: 사업계획서 내 보안유지 필요부분 구체화 필요 | AC25: 내부방침
A26: 24 | B26: 단일감축사업 | C26: (주)선일로에스의 B-A유에서 LNG로 연료전환을 통한 온실가스 배출 감축사업 | D26: (주)선일로에스 | E26: =VLOOKUP(C26,'외부사업 비공개승인관리_국내'!$C:$H,4,FALSE) -> 2020-10-05 | F26: =VLOOKUP(C26,'외부사업 비공개승인관리_국내'!$C:$H,5,FALSE) -> 산업통상부 | G26: =VLOOKUP(C26,'외부사업 비공개승인관리_국내'!$C:$H,6,FALSE) -> 2022-06-02 | H26: =VLOOKUP(C26,'외부사업 비공개승인관리_국내'!$C:$H,3,FALSE) -> 보완요청 | I26: =LEFT(VLOOKUP(C26,'국내평가(ORS)'!P:AO,26,0),10) -> 2017-12-07 | J26: =IF(I26=E26,"O","X") -> X | K26: =VLOOKUP(C26, '국내평가(ORS)'!P:AL, 23, 0) -> [보완3차]착수신고 2022-01-04 | L26: =VLOOKUP(C26, '국내평가(ORS)'!A:AL, 2, 0) -> 승인 | M26: 검토필요 | N26: 보완요청 | O26: 사업자 | P26: =IF(AND(H26<>"반려", L26<>"반려"),"검토가능","") -> 검토가능 | Q26: 보완요청 | R26: 사업자 | S26: 5월 26일 | T26: 에코시안_정인혜 | U26: 사업계획서 내 보안유지 필요부분 구체화 필요 | AC26: 내부방침
A27: 25 | B27: 단일감축사업 | C27: (주)덕산의 신재 및 재생 드라이어의 B-C유에서 도시가스(LNG)로 연료전환을 통한 온실가스 배출 감축사업 | D27: (주) 덕 산 | E27: =VLOOKUP(C27,'외부사업 비공개승인관리_국내'!$C:$H,4,FALSE) -> 2020-09-29 | F27: =VLOOKUP(C27,'외부사업 비공개승인관리_국내'!$C:$H,5,FALSE) -> 산업통상부 | G27: =VLOOKUP(C27,'외부사업 비공개승인관리_국내'!$C:$H,6,FALSE) -> 2022-06-02 | H27: =VLOOKUP(C27,'외부사업 비공개승인관리_국내'!$C:$H,3,FALSE) -> 보완요청 | I27: =LEFT(VLOOKUP(C27,'국내평가(ORS)'!P:AO,26,0),10) -> 2020-09-29 | J27: =IF(I27=E27,"O","X") -> O | K27: =VLOOKUP(C27, '국내평가(ORS)'!P:AL, 23, 0) -> [보완1차]착수신고 2022-05-30 | L27: =VLOOKUP(C27, '국내평가(ORS)'!A:AL, 2, 0) -> 승인 | M27: 검토필요 | N27: 보완요청 | O27: 사업자 | P27: =IF(AND(H27<>"반려", L27<>"반려"),"검토가능","") -> 검토가능 | Q27: 선택 | R27: 선택 | S27: 5월 26일 | T27: 에코시안_박세은 | U27: 사업계획서 내 보안유지 필요부분 구체화 필요 | AC27: 내부방침 | AD27: 이력이 반려이므로 사업반려에 포함됨
A28: 26 | B28: 단일감축사업 | C28: 에스오엠의 정제유에서 도시가스(LNG)로 연료전환을 통한 온실가스 배출 감축사업 | D28: 에스오엠 | E28: =VLOOKUP(C28,'외부사업 비공개승인관리_국내'!$C:$H,4,FALSE) -> 2020-09-21 | F28: =VLOOKUP(C28,'외부사업 비공개승인관리_국내'!$C:$H,5,FALSE) -> 산업통상부 | G28: =VLOOKUP(C28,'외부사업 비공개승인관리_국내'!$C:$H,6,FALSE) -> 2022-06-02 | H28: =VLOOKUP(C28,'외부사업 비공개승인관리_국내'!$C:$H,3,FALSE) -> 보완요청 | I28: =LEFT(VLOOKUP(C28,'국내평가(ORS)'!P:AO,26,0),10) -> 2020-09-21 | J28: =IF(I28=E28,"O","X") -> O | K28: =VLOOKUP(C28, '국내평가(ORS)'!P:AL, 23, 0) -> [보완3차]착수신고 2022-10-20 | L28: =VLOOKUP(C28, '국내평가(ORS)'!A:AL, 2, 0) -> 승인 | M28: 검토필요 | N28: 보완요청 | O28: 사업자 | P28: =IF(AND(H28<>"반려", L28<>"반려"),"검토가능","") -> 검토가능 | Q28: 보완요청 | R28: 사업자 | S28: 5월 26일 | T28: 에코시안_박세은 | U28: 사업계획서 내 보안유지 필요부분 구체화 필요 | AC28: 내부방침
A29: 27 | B29: 단일감축사업 | C29: 구미시 LED 가로등 교체를 통한 전력사용량 절감 및 온실가스 감축사업 | D29: 자이에스앤디(주) | E29: =VLOOKUP(C29,'외부사업 비공개승인관리_국내'!$C:$H,4,FALSE) -> 2020-09-09 | F29: =VLOOKUP(C29,'외부사업 비공개승인관리_국내'!$C:$H,5,FALSE) -> 산업통상부 | G29: =VLOOKUP(C29,'외부사업 비공개승인관리_국내'!$C:$H,6,FALSE) -> 2025-02-25 | H29: =VLOOKUP(C29,'외부사업 비공개승인관리_국내'!$C:$H,3,FALSE) -> 반려 | I29: =LEFT(VLOOKUP(C29,'국내평가(ORS)'!P:AO,26,0),10) -> 2020-09-09 | J29: =IF(I29=E29,"O","X") -> O | K29: =VLOOKUP(C29, '국내평가(ORS)'!P:AL, 23, 0) -> 평가반려 2021-07-14 | L29: =VLOOKUP(C29, '국내평가(ORS)'!A:AL, 2, 0) -> 반려 | M29: X | N29: 선택 | O29: 선택 | P29: =IF(AND(H29<>"반려", L29<>"반려"),"검토가능","") | Q29: 선택 | R29: 종결 | S29: 5월 26일
A30: 28 | B30: 단일감축사업 | C30: 부천수지의 B-C유에서 도시가스(LNG)로 연료전환을 통한 온실가스 배출 감축사업 | D30: (주)부천수지 | E30: =VLOOKUP(C30,'외부사업 비공개승인관리_국내'!$C:$H,4,FALSE) -> 2020-07-06 | F30: =VLOOKUP(C30,'외부사업 비공개승인관리_국내'!$C:$H,5,FALSE) -> 산업통상부 | G30: =VLOOKUP(C30,'외부사업 비공개승인관리_국내'!$C:$H,6,FALSE) -> 2022-06-02 | H30: =VLOOKUP(C30,'외부사업 비공개승인관리_국내'!$C:$H,3,FALSE) -> 보완요청 | I30: =LEFT(VLOOKUP(C30,'국내평가(ORS)'!P:AO,26,0),10) -> 2020-07-06 | J30: =IF(I30=E30,"O","X") -> O | K30: =VLOOKUP(C30, '국내평가(ORS)'!P:AL, 23, 0) -> [보완1차]착수신고 2022-06-10 | L30: =VLOOKUP(C30, '국내평가(ORS)'!A:AL, 2, 0) -> 승인 | M30: 검토필요 | N30: 보완요청 | O30: 사업자 | P30: =IF(AND(H30<>"반려", L30<>"반려"),"검토가능","") -> 검토가능 | Q30: 보완요청 | R30: 사업자 | S30: 5월 26일 | T30: 에코시안_박세은 | U30: 사업계획서 내 보안유지 필요부분 구체화 필요 | AC30: 내부방침
A31: 29 | B31: 단일감축사업 | C31: 서울금속공업의 정제유에서 LNG로 연료전환을 통한 온실가스 배출 감축사업 | D31: 서울금속공업(주) | E31: =VLOOKUP(C31,'외부사업 비공개승인관리_국내'!$C:$H,4,FALSE) -> 2020-06-24 | F31: =VLOOKUP(C31,'외부사업 비공개승인관리_국내'!$C:$H,5,FALSE) -> 산업통상부 | G31: =VLOOKUP(C31,'외부사업 비공개승인관리_국내'!$C:$H,6,FALSE) -> 2026-02-06 | H31: =VLOOKUP(C31,'외부사업 비공개승인관리_국내'!$C:$H,3,FALSE) -> 보완요청 | I31: =LEFT(VLOOKUP(C31,'국내평가(ORS)'!P:AO,26,0),10) -> 2017-12-29 | J31: =IF(I31=E31,"O","X") -> X | K31: =VLOOKUP(C31, '국내평가(ORS)'!P:AL, 23, 0) -> 평가반려 2021-05-17 | L31: =VLOOKUP(C31, '국내평가(ORS)'!A:AL, 2, 0) -> 반려 | M31: X | N31: 선택 | O31: 선택 | P31: =IF(AND(H31<>"반려", L31<>"반려"),"검토가능","") | Q31: 보완요청 | R31: 사업자 | S31: 5월 26일 | T31: 미정 | U31: 기 승인 사업, 사업변경신청 후 변경신청이 반려되었으나, 승인된 사업의 정보비공개 평가 필요 | AC31: 내부방침 | AD31: 사업 반려가 아니라 변경신청 반려임
A32: 30 | B32: 단일감축사업 | C32: 우성세라믹스공업의 LPG에서 LNG로 연료전환을 통한 온실가스 배출 감축사업 | D32: 우성세라믹스공업(주) | E32: =VLOOKUP(C32,'외부사업 비공개승인관리_국내'!$C:$H,4,FALSE) -> 2020-06-24 | F32: =VLOOKUP(C32,'외부사업 비공개승인관리_국내'!$C:$H,5,FALSE) -> 산업통상부 | G32: =VLOOKUP(C32,'외부사업 비공개승인관리_국내'!$C:$H,6,FALSE) -> 2022-06-02 | H32: =VLOOKUP(C32,'외부사업 비공개승인관리_국내'!$C:$H,3,FALSE) -> 보완요청 | I32: =LEFT(VLOOKUP(C32,'국내평가(ORS)'!P:AO,26,0),10) -> 2017-12-07 | J32: =IF(I32=E32,"O","X") -> X | K32: =VLOOKUP(C32, '국내평가(ORS)'!P:AL, 23, 0) -> [보완2차]착수신고 2021-04-02 | L32: =VLOOKUP(C32, '국내평가(ORS)'!A:AL, 2, 0) -> 승인 | M32: 검토필요 | N32: 보완요청 | O32: 사업자 | P32: =IF(AND(H32<>"반려", L32<>"반려"),"검토가능","") -> 검토가능 | Q32: 보완요청 | R32: 사업자 | S32: 5월 26일 | T32: 에코시안_박세은 | U32: 사업계획서 내 보안유지 필요부분 구체화 필요 | AC32: 내부방침
A33: 31 | B33: 단일감축사업 | C33: 덕성 인천사업장의 B-A유 및 B-C유에서 LNG로 연료전환을 통한 온실가스 배출 감축사업 | D33: (주)덕성 | E33: =VLOOKUP(C33,'외부사업 비공개승인관리_국내'!$C:$H,4,FALSE) -> 2020-04-27 | F33: =VLOOKUP(C33,'외부사업 비공개승인관리_국내'!$C:$H,5,FALSE) -> 산업통상부 | G33: =VLOOKUP(C33,'외부사업 비공개승인관리_국내'!$C:$H,6,FALSE) -> 2022-06-02 | H33: =VLOOKUP(C33,'외부사업 비공개승인관리_국내'!$C:$H,3,FALSE) -> 보완요청 | I33: =LEFT(VLOOKUP(C33,'국내평가(ORS)'!P:AO,26,0),10) -> 2018-10-17 | J33: =IF(I33=E33,"O","X") -> X | K33: =VLOOKUP(C33, '국내평가(ORS)'!P:AL, 23, 0) -> [보완3차]착수신고 2021-03-22 | L33: =VLOOKUP(C33, '국내평가(ORS)'!A:AL, 2, 0) -> 승인 | M33: 검토필요 | N33: 보완요청 | O33: 사업자 | P33: =IF(AND(H33<>"반려", L33<>"반려"),"검토가능","") -> 검토가능 | Q33: 보완요청 | R33: 사업자 | S33: 5월 26일 | T33: 에코시안_박세은 | U33: 사업계획서 내 보안유지 필요부분 구체화 필요 | AC33: 내부방침
A34: 32 | B34: 단일감축사업 | C34: 덕성 수원사업장의 B-A유에서 LNG로 연료전환을 통한 온실가스 배출 감축사업 | D34: (주)덕성 | E34: =VLOOKUP(C34,'외부사업 비공개승인관리_국내'!$C:$H,4,FALSE) -> 2020-04-27 | F34: =VLOOKUP(C34,'외부사업 비공개승인관리_국내'!$C:$H,5,FALSE) -> 산업통상부 | G34: =VLOOKUP(C34,'외부사업 비공개승인관리_국내'!$C:$H,6,FALSE) -> 2022-06-02 | H34: =VLOOKUP(C34,'외부사업 비공개승인관리_국내'!$C:$H,3,FALSE) -> 보완요청 | I34: =LEFT(VLOOKUP(C34,'국내평가(ORS)'!P:AO,26,0),10) -> 2017-12-26 | J34: =IF(I34=E34,"O","X") -> X | K34: =VLOOKUP(C34, '국내평가(ORS)'!P:AL, 23, 0) -> [보완3차]착수신고 2020-04-27 | L34: =VLOOKUP(C34, '국내평가(ORS)'!A:AL, 2, 0) -> 승인 | M34: 검토필요 | N34: 보완요청 | O34: 사업자 | P34: =IF(AND(H34<>"반려", L34<>"반려"),"검토가능","") -> 검토가능 | Q34: 보완요청 | R34: 사업자 | S34: 5월 26일 | T34: 에코시안_박세은 | U34: 사업계획서 내 보안유지 필요부분 구체화 필요 | AC34: 내부방침
A35: 33 | B35: 단일감축사업 | C35: 부옥물산의 B-C유에서 LNG로 연료전환을 통한 온실가스 배출 감축사업 | D35: 부옥물산(주) | E35: =VLOOKUP(C35,'외부사업 비공개승인관리_국내'!$C:$H,4,FALSE) -> 2020-04-14 | F35: =VLOOKUP(C35,'외부사업 비공개승인관리_국내'!$C:$H,5,FALSE) -> 산업통상부 | G35: =VLOOKUP(C35,'외부사업 비공개승인관리_국내'!$C:$H,6,FALSE) -> 2022-06-02 | H35: =VLOOKUP(C35,'외부사업 비공개승인관리_국내'!$C:$H,3,FALSE) -> 보완요청 | I35: =LEFT(VLOOKUP(C35,'국내평가(ORS)'!P:AO,26,0),10) -> 2018-10-04 | J35: =IF(I35=E35,"O","X") -> X | K35: =VLOOKUP(C35, '국내평가(ORS)'!P:AL, 23, 0) -> [보완3차]착수신고 2020-04-14 | L35: =VLOOKUP(C35, '국내평가(ORS)'!A:AL, 2, 0) -> 승인 | M35: 검토필요 | N35: 보완요청 | O35: 사업자 | P35: =IF(AND(H35<>"반려", L35<>"반려"),"검토가능","") -> 검토가능 | Q35: 보완요청 | R35: 사업자 | S35: 5월 26일 | T35: 에코시안_박세은 | U35: 사업계획서 내 보안유지 필요부분 구체화 필요 | AC35: 내부방침
A36: 34 | B36: 단일감축사업 | C36: 삼승텍스타일의 LPG에서 LNG로 연료전환을 통한 온실가스 배출 감축사업 | D36: 삼승텍스타일[주] | E36: =VLOOKUP(C36,'외부사업 비공개승인관리_국내'!$C:$H,4,FALSE) -> 2020-03-06 | F36: =VLOOKUP(C36,'외부사업 비공개승인관리_국내'!$C:$H,5,FALSE) -> 산업통상부 | G36: =VLOOKUP(C36,'외부사업 비공개승인관리_국내'!$C:$H,6,FALSE) -> 2025-02-25 | H36: =VLOOKUP(C36,'외부사업 비공개승인관리_국내'!$C:$H,3,FALSE) -> 반려 | I36: =LEFT(VLOOKUP(C36,'국내평가(ORS)'!P:AO,26,0),10) -> 2020-03-06 | J36: =IF(I36=E36,"O","X") -> O | K36: =VLOOKUP(C36, '국내평가(ORS)'!P:AL, 23, 0) -> 평가반려 2021-05-10 | L36: =VLOOKUP(C36, '국내평가(ORS)'!A:AL, 2, 0) -> 반려 | M36: X | N36: 선택 | O36: 선택 | P36: =IF(AND(H36<>"반려", L36<>"반려"),"검토가능","") | Q36: 선택 | R36: 종결 | S36: 5월 26일
A37: 35 | B37: 단일감축사업 | C37: 휴켐스(주) 신설 6질산 공장에서 발생하는 아산화질소(N2O) 배출량 저감사업 | D37: 휴켐스 주식회사 | E37: =VLOOKUP(C37,'외부사업 비공개승인관리_국내'!$C:$H,4,FALSE) -> 2020-02-24 | F37: =VLOOKUP(C37,'외부사업 비공개승인관리_국내'!$C:$H,5,FALSE) -> 산업통상부 | G37: =VLOOKUP(C37,'외부사업 비공개승인관리_국내'!$C:$H,6,FALSE) -> 2025-02-25 | H37: =VLOOKUP(C37,'외부사업 비공개승인관리_국내'!$C:$H,3,FALSE) -> 반려 | I37: =LEFT(VLOOKUP(C37,'국내평가(ORS)'!P:AO,26,0),10) -> 2020-02-24 | J37: =IF(I37=E37,"O","X") -> O | K37: =VLOOKUP(C37, '국내평가(ORS)'!P:AL, 23, 0) -> 평가반려 2020-05-21 | L37: =VLOOKUP(C37, '국내평가(ORS)'!A:AL, 2, 0) -> 반려 | M37: X | N37: 선택 | O37: 선택 | P37: =IF(AND(H37<>"반려", L37<>"반려"),"검토가능","") | Q37: 선택 | R37: 종결 | S37: 5월 26일
A38: 36 | B38: 묶음감축사업 | C38: 2019년 인천광역시 보안등 LED 교체 묶음 감축사업 | D38: 인천광역시 | E38: =VLOOKUP(C38,'외부사업 비공개승인관리_국내'!$C:$H,4,FALSE) -> 2019-12-31 | F38: =VLOOKUP(C38,'외부사업 비공개승인관리_국내'!$C:$H,5,FALSE) -> 산업통상부 | G38: =VLOOKUP(C38,'외부사업 비공개승인관리_국내'!$C:$H,6,FALSE) -> 2025-01-09 | H38: =VLOOKUP(C38,'외부사업 비공개승인관리_국내'!$C:$H,3,FALSE) -> 보완요청 | I38: =LEFT(VLOOKUP(C38,'국내평가(ORS)'!P:AO,26,0),10) -> 2019-12-31 | J38: =IF(I38=E38,"O","X") -> O | K38: =VLOOKUP(C38, '국내평가(ORS)'!P:AL, 23, 0) -> [보완3차]문서재제출요청 2022-10-20 | L38: =VLOOKUP(C38, '국내평가(ORS)'!A:AL, 2, 0) -> 보완3차_문서보완중 | M38: 승인 전 | N38: 선택 | O38: 선택 | P38: =IF(AND(H38<>"반려", L38<>"반려"),"검토가능","") -> 검토가능 | Q38: 보완요청 | R38: 사업자 | S38: 45665 | T38: 미정 | U38: 제출서류 미비로 보완 요청. 보완 요청 통보 문구 기재(공단 통보)
A39: 37 | B39: 묶음감축사업 | C39: 2019년 인천광역시 도로조명 LED 교체 묶음 감축사업 | D39: 인천광역시 | E39: =VLOOKUP(C39,'외부사업 비공개승인관리_국내'!$C:$H,4,FALSE) -> 2019-12-31 | F39: =VLOOKUP(C39,'외부사업 비공개승인관리_국내'!$C:$H,5,FALSE) -> 산업통상부 | G39: =VLOOKUP(C39,'외부사업 비공개승인관리_국내'!$C:$H,6,FALSE) -> 2025-01-09 | H39: =VLOOKUP(C39,'외부사업 비공개승인관리_국내'!$C:$H,3,FALSE) -> 보완요청 | I39: =LEFT(VLOOKUP(C39,'국내평가(ORS)'!P:AO,26,0),10) -> 2019-12-31 | J39: =IF(I39=E39,"O","X") -> O | K39: =VLOOKUP(C39, '국내평가(ORS)'!P:AL, 23, 0) -> [보완3차]문서재제출요청 2022-10-18 | L39: =VLOOKUP(C39, '국내평가(ORS)'!A:AL, 2, 0) -> 보완3차_문서보완중 | M39: 승인 전 | N39: 선택 | O39: 선택 | P39: =IF(AND(H39<>"반려", L39<>"반려"),"검토가능","") -> 검토가능 | Q39: 보완요청 | R39: 사업자 | S39: 45665 | T39: 미정 | U39: 제출서류 미비로 보완 요청. 보완 요청 통보 문구 기재(공단 통보)
A40: 38 | B40: 프로그램감축사업 | C40: 인천광역시 주택 태양광 발전설비 보급 프로그램 감축사업 | D40: 인천광역시 | E40: =VLOOKUP(C40,'외부사업 비공개승인관리_국내'!$C:$H,4,FALSE) -> 2019-12-31 | F40: =VLOOKUP(C40,'외부사업 비공개승인관리_국내'!$C:$H,5,FALSE) -> 기후에너지환경부 | G40: =VLOOKUP(C40,'외부사업 비공개승인관리_국내'!$C:$H,6,FALSE) -> 2025-02-25 | H40: =VLOOKUP(C40,'외부사업 비공개승인관리_국내'!$C:$H,3,FALSE) -> 반려 | I40: =LEFT(VLOOKUP(C40,'국내평가(ORS)'!P:AO,26,0),10) -> 2021-12-27 | J40: =IF(I40=E40,"O","X") -> X | K40: =VLOOKUP(C40, '국내평가(ORS)'!P:AL, 23, 0) -> 문서재제출요청 2022-08-24 | L40: =VLOOKUP(C40, '국내평가(ORS)'!A:AL, 2, 0) -> 문서재제출 | M40: X | N40: 선택 | O40: 선택 | P40: =IF(AND(H40<>"반려", L40<>"반려"),"검토가능","") | Q40: 선택 | R40: 종결 | S40: 5월 26일
A41: 39 | B41: 단일감축사업 | C41: 롯데케미칼㈜ 공정폐열의 ㈜스마트에너지팩토리 공정스팀 활용사업 | D41: 비케이이엔지·스마트에너지팩토리 공정 폐열 스팀 활용 사업 | E41: =VLOOKUP(C41,'외부사업 비공개승인관리_국내'!$C:$H,4,FALSE) -> 2019-12-25 | F41: =VLOOKUP(C41,'외부사업 비공개승인관리_국내'!$C:$H,5,FALSE) -> 산업통상부 | G41: =VLOOKUP(C41,'외부사업 비공개승인관리_국내'!$C:$H,6,FALSE) -> 2025-02-25 | H41: =VLOOKUP(C41,'외부사업 비공개승인관리_국내'!$C:$H,3,FALSE) -> 반려 | I41: =LEFT(VLOOKUP(C41,'국내평가(ORS)'!P:AO,26,0),10) -> 2019-12-25 | J41: =IF(I41=E41,"O","X") -> O | K41: =VLOOKUP(C41, '국내평가(ORS)'!P:AL, 23, 0) -> [보완1차]평가반려 2021-11-03 | L41: =VLOOKUP(C41, '국내평가(ORS)'!A:AL, 2, 0) -> 반려 | M41: X | N41: 선택 | O41: 선택 | P41: =IF(AND(H41<>"반려", L41<>"반려"),"검토가능","") | Q41: 선택 | R41: 종결 | S41: 5월 26일
A42: 40 | B42: 프로그램감축사업 | C42: (주)엘지화학 자가 소비용 태양광 발전설비의 설치 지원을 통한 프로그램 감축사업 | D42: 주식회사 엘지화학 | E42: =VLOOKUP(C42,'외부사업 비공개승인관리_국내'!$C:$H,4,FALSE) -> 2019-12-19 | F42: =VLOOKUP(C42,'외부사업 비공개승인관리_국내'!$C:$H,5,FALSE) -> 기후에너지환경부 | G42: =VLOOKUP(C42,'외부사업 비공개승인관리_국내'!$C:$H,6,FALSE) -> 2022-06-02 | H42: =VLOOKUP(C42,'외부사업 비공개승인관리_국내'!$C:$H,3,FALSE) -> 보완요청 | I42: =LEFT(VLOOKUP(C42,'국내평가(ORS)'!P:AO,26,0),10) -> 2022-09-05 | J42: =IF(I42=E42,"O","X") -> X | K42: =VLOOKUP(C42, '국내평가(ORS)'!P:AL, 23, 0) -> [보완3차]착수신고 2025-01-03 | L42: =VLOOKUP(C42, '국내평가(ORS)'!A:AL, 2, 0) -> 승인 | M42: 검토필요 | N42: 보완요청 | O42: 사업자 | P42: =IF(AND(H42<>"반려", L42<>"반려"),"검토가능","") -> 검토가능 | Q42: 보완요청 | R42: 사업자 | S42: 5월 26일 | T42: 에코시안_박세은 | U42: 해당 사유로 승인 가능여부 확인 필요(사유: 생산 공정 등 외부 유출에 민감한 자료 포함) * 생산공정 특이사항 확인 불가 | AC42: 업체정보보호(공정)
A43: 41 | B43: 프로그램감축사업 | C43: 고효율인덕션히터 도입을 통한 온실가스 감축 사업 | D43: 한국산업단지공단 | E43: =VLOOKUP(C43,'외부사업 비공개승인관리_국내'!$C:$H,4,FALSE) -> 2019-12-17 | F43: =VLOOKUP(C43,'외부사업 비공개승인관리_국내'!$C:$H,5,FALSE) -> 산업통상부 | G43: =VLOOKUP(C43,'외부사업 비공개승인관리_국내'!$C:$H,6,FALSE) -> 2025-02-25 | H43: =VLOOKUP(C43,'외부사업 비공개승인관리_국내'!$C:$H,3,FALSE) -> 반려 | I43: =LEFT(VLOOKUP(C43,'국내평가(ORS)'!P:AO,26,0),10) -> 2019-12-17 | J43: =IF(I43=E43,"O","X") -> O | K43: =VLOOKUP(C43, '국내평가(ORS)'!P:AL, 23, 0) -> 평가반려 2021-06-07 | L43: =VLOOKUP(C43, '국내평가(ORS)'!A:AL, 2, 0) -> 반려 | M43: X | N43: 선택 | O43: 선택 | P43: =IF(AND(H43<>"반려", L43<>"반려"),"검토가능","") | Q43: 선택 | R43: 종결 | S43: 5월 26일
A44: 42 | B44: 프로그램감축사업 | C44: 고효율인덕션히터 도입을 통한 온실가스 감축 사업 | D44: 한국산업단지공단 | E44: =VLOOKUP(C44,'외부사업 비공개승인관리_국내'!$C:$H,4,FALSE) -> 2019-12-17 | F44: =VLOOKUP(C44,'외부사업 비공개승인관리_국내'!$C:$H,5,FALSE) -> 산업통상부 | G44: =VLOOKUP(C44,'외부사업 비공개승인관리_국내'!$C:$H,6,FALSE) -> 2025-02-25 | H44: =VLOOKUP(C44,'외부사업 비공개승인관리_국내'!$C:$H,3,FALSE) -> 반려 | I44: =LEFT(VLOOKUP(C44,'국내평가(ORS)'!P:AO,26,0),10) -> 2019-12-17 | J44: =IF(I44=E44,"O","X") -> O | K44: =VLOOKUP(C44, '국내평가(ORS)'!P:AL, 23, 0) -> 평가반려 2021-06-07 | L44: =VLOOKUP(C44, '국내평가(ORS)'!A:AL, 2, 0) -> 반려 | M44: X | N44: 선택 | O44: 선택 | P44: =IF(AND(H44<>"반려", L44<>"반려"),"검토가능","") | Q44: 선택 | R44: 종결 | S44: 5월 26일
A45: 43 | B45: 프로그램감축사업 | C45: 고효율인덕션히터 도입을 통한 온실가스 감축 사업 | D45: 한국산업단지공단 | E45: =VLOOKUP(C45,'외부사업 비공개승인관리_국내'!$C:$H,4,FALSE) -> 2019-12-17 | F45: =VLOOKUP(C45,'외부사업 비공개승인관리_국내'!$C:$H,5,FALSE) -> 산업통상부 | G45: =VLOOKUP(C45,'외부사업 비공개승인관리_국내'!$C:$H,6,FALSE) -> 2025-02-25 | H45: =VLOOKUP(C45,'외부사업 비공개승인관리_국내'!$C:$H,3,FALSE) -> 반려 | I45: =LEFT(VLOOKUP(C45,'국내평가(ORS)'!P:AO,26,0),10) -> 2019-12-17 | J45: =IF(I45=E45,"O","X") -> O | K45: =VLOOKUP(C45, '국내평가(ORS)'!P:AL, 23, 0) -> 평가반려 2021-06-07 | L45: =VLOOKUP(C45, '국내평가(ORS)'!A:AL, 2, 0) -> 반려 | M45: X | N45: 선택 | O45: 선택 | P45: =IF(AND(H45<>"반려", L45<>"반려"),"검토가능","") | Q45: 선택 | R45: 종결 | S45: 5월 26일
A46: 44 | B46: 프로그램감축사업 | C46: 고효율인덕션히터 도입을 통한 온실가스 감축 사업 | D46: 한국산업단지공단 | E46: =VLOOKUP(C46,'외부사업 비공개승인관리_국내'!$C:$H,4,FALSE) -> 2019-12-17 | F46: =VLOOKUP(C46,'외부사업 비공개승인관리_국내'!$C:$H,5,FALSE) -> 산업통상부 | G46: =VLOOKUP(C46,'외부사업 비공개승인관리_국내'!$C:$H,6,FALSE) -> 2025-02-25 | H46: =VLOOKUP(C46,'외부사업 비공개승인관리_국내'!$C:$H,3,FALSE) -> 반려 | I46: =LEFT(VLOOKUP(C46,'국내평가(ORS)'!P:AO,26,0),10) -> 2019-12-17 | J46: =IF(I46=E46,"O","X") -> O | K46: =VLOOKUP(C46, '국내평가(ORS)'!P:AL, 23, 0) -> 평가반려 2021-06-07 | L46: =VLOOKUP(C46, '국내평가(ORS)'!A:AL, 2, 0) -> 반려 | M46: X | N46: 선택 | O46: 선택 | P46: =IF(AND(H46<>"반려", L46<>"반려"),"검토가능","") | Q46: 선택 | R46: 종결 | S46: 5월 26일
A47: 45 | B47: 프로그램감축사업 | C47: 고효율인덕션히터 도입을 통한 온실가스 감축 사업 | D47: 한국산업단지공단 | E47: =VLOOKUP(C47,'외부사업 비공개승인관리_국내'!$C:$H,4,FALSE) -> 2019-12-17 | F47: =VLOOKUP(C47,'외부사업 비공개승인관리_국내'!$C:$H,5,FALSE) -> 산업통상부 | G47: =VLOOKUP(C47,'외부사업 비공개승인관리_국내'!$C:$H,6,FALSE) -> 2025-02-25 | H47: =VLOOKUP(C47,'외부사업 비공개승인관리_국내'!$C:$H,3,FALSE) -> 반려 | I47: =LEFT(VLOOKUP(C47,'국내평가(ORS)'!P:AO,26,0),10) -> 2019-12-17 | J47: =IF(I47=E47,"O","X") -> O | K47: =VLOOKUP(C47, '국내평가(ORS)'!P:AL, 23, 0) -> 평가반려 2021-06-07 | L47: =VLOOKUP(C47, '국내평가(ORS)'!A:AL, 2, 0) -> 반려 | M47: X | N47: 선택 | O47: 선택 | P47: =IF(AND(H47<>"반려", L47<>"반려"),"검토가능","") | Q47: 선택 | R47: 종결 | S47: 5월 26일
A48: 46 | B48: 프로그램감축사업 | C48: 고효율인덕션히터 도입을 통한 온실가스 감축 사업 | D48: 한국산업단지공단 | E48: =VLOOKUP(C48,'외부사업 비공개승인관리_국내'!$C:$H,4,FALSE) -> 2019-12-17 | F48: =VLOOKUP(C48,'외부사업 비공개승인관리_국내'!$C:$H,5,FALSE) -> 산업통상부 | G48: =VLOOKUP(C48,'외부사업 비공개승인관리_국내'!$C:$H,6,FALSE) -> 2025-02-25 | H48: =VLOOKUP(C48,'외부사업 비공개승인관리_국내'!$C:$H,3,FALSE) -> 반려 | I48: =LEFT(VLOOKUP(C48,'국내평가(ORS)'!P:AO,26,0),10) -> 2019-12-17 | J48: =IF(I48=E48,"O","X") -> O | K48: =VLOOKUP(C48, '국내평가(ORS)'!P:AL, 23, 0) -> 평가반려 2021-06-07 | L48: =VLOOKUP(C48, '국내평가(ORS)'!A:AL, 2, 0) -> 반려 | M48: X | N48: 선택 | O48: 선택 | P48: =IF(AND(H48<>"반려", L48<>"반려"),"검토가능","") | Q48: 선택 | R48: 종결 | S48: 5월 26일
A49: 47 | B49: 단일감축사업 | C49: 신원산업 열교환기 설치를 통한 온실가스 감축사업 | D49: 신원산업주식회사 | E49: =VLOOKUP(C49,'외부사업 비공개승인관리_국내'!$C:$H,4,FALSE) -> 2019-12-16 | F49: =VLOOKUP(C49,'외부사업 비공개승인관리_국내'!$C:$H,5,FALSE) -> 산업통상부 | G49: =VLOOKUP(C49,'외부사업 비공개승인관리_국내'!$C:$H,6,FALSE) -> 2025-02-25 | H49: =VLOOKUP(C49,'외부사업 비공개승인관리_국내'!$C:$H,3,FALSE) -> 반려 | I49: =LEFT(VLOOKUP(C49,'국내평가(ORS)'!P:AO,26,0),10) -> 2019-12-16 | J49: =IF(I49=E49,"O","X") -> O | K49: =VLOOKUP(C49, '국내평가(ORS)'!P:AL, 23, 0) -> [보완1차]평가반려 2021-07-14 | L49: =VLOOKUP(C49, '국내평가(ORS)'!A:AL, 2, 0) -> 반려 | M49: X | N49: 선택 | O49: 선택 | P49: =IF(AND(H49<>"반려", L49<>"반려"),"검토가능","") | Q49: 선택 | R49: 종결 | S49: 5월 26일
A50: 48 | B50: 단일감축사업 | C50: 영덕산업의 LPG에서 도시가스(LNG)로 연료전환을 통한 온실가스 배출 감축사업 | D50: 영덕산업(주) | E50: =VLOOKUP(C50,'외부사업 비공개승인관리_국내'!$C:$H,4,FALSE) -> 2019-12-12 | F50: =VLOOKUP(C50,'외부사업 비공개승인관리_국내'!$C:$H,5,FALSE) -> 산업통상부 | G50: =VLOOKUP(C50,'외부사업 비공개승인관리_국내'!$C:$H,6,FALSE) -> 2025-02-25 | H50: =VLOOKUP(C50,'외부사업 비공개승인관리_국내'!$C:$H,3,FALSE) -> 반려 | I50: =LEFT(VLOOKUP(C50,'국내평가(ORS)'!P:AO,26,0),10) -> 2019-12-12 | J50: =IF(I50=E50,"O","X") -> O | K50: =VLOOKUP(C50, '국내평가(ORS)'!P:AL, 23, 0) -> [보완1차]평가반려 2021-05-10 | L50: =VLOOKUP(C50, '국내평가(ORS)'!A:AL, 2, 0) -> 반려 | M50: X | N50: 선택 | O50: 선택 | P50: =IF(AND(H50<>"반려", L50<>"반려"),"검토가능","") | Q50: 선택 | R50: 종결 | S50: 5월 26일
A51: 49 | B51: 단일감축사업 | C51: 원주시 보안등 LED교체 ESCO용역사업 | D51: 원주시 | E51: =VLOOKUP(C51,'외부사업 비공개승인관리_국내'!$C:$H,4,FALSE) -> 2024-08-20 | F51: =VLOOKUP(C51,'외부사업 비공개승인관리_국내'!$C:$H,5,FALSE) -> 산업통상부 | G51: =VLOOKUP(C51,'외부사업 비공개승인관리_국내'!$C:$H,6,FALSE) -> 2022-06-02 | H51: =VLOOKUP(C51,'외부사업 비공개승인관리_국내'!$C:$H,3,FALSE) -> 보완완료 | I51: =LEFT(VLOOKUP(C51,'국내평가(ORS)'!P:AO,26,0),10) -> 2023-04-25 | J51: =IF(I51=E51,"O","X") -> X | K51: =VLOOKUP(C51, '국내평가(ORS)'!P:AL, 23, 0) -> [보완2차]협의통보 2025-01-21 | L51: =VLOOKUP(C51, '국내평가(ORS)'!A:AL, 2, 0) -> 인증유효기간 갱신 | M51: 검토필요 | N51: 보완요청 | O51: 사업자 | P51: =IF(AND(H51<>"반려", L51<>"반려"),"검토가능","") -> 검토가능 | Q51: 평가필요 | R51: 검토반 | S51: 5월 26일 | T51: KECM | U51: [통보의견] 비공개 신청사유를 하기와 같이 보완 요청 드립니다. - 사업계획서 내용 중 보안유지 필요부분 및 사유 구체화 [보완의견] 본 외부사업의 사업계획서 상 비공개를 희망하는 부분 및 그 사유를 다음과 같이 기술함. 1.2. 사업의 위치 (3) 사업의 주소, 보안등 번호, 전주번호 - 이 사업의 대상인 도로조명의 주소, 등번호, 전주번호는 중요한 정보이며, 그 목록 전체를 원주시가 일반에게 공개할 의무는 없으며, 오남용될 가능성도 있어 원주시는 이 정보의 공개를 원하지 않음 [근거: 공공기관의 정보공개에 관한 법률 제9조제1항제5호] 2. 베이스라인 및 모니터링 방법론, 3. 온실가스 감축량 산정, 4. 모니터링 계획 - 본 외부사업의 베이스라인 및 모니터링 방법, 온실가스 감축량 산정 방법, 모니터링 계획이 원주시 고유의 특성을 반영하여 구체적으로 기술되어 있기 때문에 정보공개를 원하지 않음. 또한, 이 사업계획서를 작성하기 위하여 원주시가 오랜 기간 동안 시간과 노력과 예산을 투자하여 작성한 연구성과물이기 때문에 무상으로 이를 일반인에게 공개하는 것은 공평하지 못하며, 시장질서에도 바람직하지 않다고 사료되므로 원주시는 비공개를 요청함 [근거: 공공기관의 정보공개에 관한 법률 제9조제1항제5호,제7호] 6. 사업자 정보 - 사업자 담당자의 개인 정보 보호 차원에서 이 정보의 공개를 원하지 않음 [근거: 공공기관의 정보공개에 관한 법률 제9조제1항제6호] | AC51: 업체정보보호(내부 정보) | AD51: 승인 후 유효기간갱신 신청건
A52: 50 | B52: 단일감축사업 | C52: (주)엘림 188.7kW 태양광 발전사업 | D52: (주)엘림 | E52: =VLOOKUP(C52,'외부사업 비공개승인관리_국내'!$C:$H,4,FALSE) -> 2019-11-27 | F52: =VLOOKUP(C52,'외부사업 비공개승인관리_국내'!$C:$H,5,FALSE) -> 기후에너지환경부 | G52: =VLOOKUP(C52,'외부사업 비공개승인관리_국내'!$C:$H,6,FALSE) -> 2025-02-25 | H52: =VLOOKUP(C52,'외부사업 비공개승인관리_국내'!$C:$H,3,FALSE) -> 반려 | I52: =LEFT(VLOOKUP(C52,'국내평가(ORS)'!P:AO,26,0),10) -> 2019-11-27 | J52: =IF(I52=E52,"O","X") -> O | K52: =VLOOKUP(C52, '국내평가(ORS)'!P:AL, 23, 0) -> 평가반려 2021-11-03 | L52: =VLOOKUP(C52, '국내평가(ORS)'!A:AL, 2, 0) -> 반려 | M52: X | N52: 선택 | O52: 선택 | P52: =IF(AND(H52<>"반려", L52<>"반려"),"검토가능","") | Q52: 선택 | R52: 종결 | S52: 5월 26일
A53: 51 | B53: 프로그램감축사업 | C53: 용탕온도관리시스템 도입을 통한 온실가스 감축 사업 | D53: 한국산업단지공단 | E53: =VLOOKUP(C53,'외부사업 비공개승인관리_국내'!$C:$H,4,FALSE) -> 2019-11-01 | F53: =VLOOKUP(C53,'외부사업 비공개승인관리_국내'!$C:$H,5,FALSE) -> 산업통상부 | G53: =VLOOKUP(C53,'외부사업 비공개승인관리_국내'!$C:$H,6,FALSE) -> 2025-02-25 | H53: =VLOOKUP(C53,'외부사업 비공개승인관리_국내'!$C:$H,3,FALSE) -> 반려 | I53: =LEFT(VLOOKUP(C53,'국내평가(ORS)'!P:AO,26,0),10) -> 2019-11-01 | J53: =IF(I53=E53,"O","X") -> O | K53: =VLOOKUP(C53, '국내평가(ORS)'!P:AL, 23, 0) -> 평가반려 2021-06-07 | L53: =VLOOKUP(C53, '국내평가(ORS)'!A:AL, 2, 0) -> 반려 | M53: X | N53: 선택 | O53: 선택 | P53: =IF(AND(H53<>"반려", L53<>"반려"),"검토가능","") | Q53: 선택 | R53: 종결 | S53: 5월 26일
A54: 52 | B54: 프로그램감축사업 | C54: 용탕온도관리시스템 도입을 통한 온실가스 감축 사업 | D54: 한국산업단지공단 | E54: =VLOOKUP(C54,'외부사업 비공개승인관리_국내'!$C:$H,4,FALSE) -> 2019-11-01 | F54: =VLOOKUP(C54,'외부사업 비공개승인관리_국내'!$C:$H,5,FALSE) -> 산업통상부 | G54: =VLOOKUP(C54,'외부사업 비공개승인관리_국내'!$C:$H,6,FALSE) -> 2025-02-25 | H54: =VLOOKUP(C54,'외부사업 비공개승인관리_국내'!$C:$H,3,FALSE) -> 반려 | I54: =LEFT(VLOOKUP(C54,'국내평가(ORS)'!P:AO,26,0),10) -> 2019-11-01 | J54: =IF(I54=E54,"O","X") -> O | K54: =VLOOKUP(C54, '국내평가(ORS)'!P:AL, 23, 0) -> 평가반려 2021-06-07 | L54: =VLOOKUP(C54, '국내평가(ORS)'!A:AL, 2, 0) -> 반려 | M54: X | N54: 선택 | O54: 선택 | P54: =IF(AND(H54<>"반려", L54<>"반려"),"검토가능","") | Q54: 선택 | R54: 종결 | S54: 5월 26일
A55: 53 | B55: 프로그램감축사업 | C55: 용탕온도관리시스템 도입을 통한 온실가스 감축 사업 | D55: 한국산업단지공단 | E55: =VLOOKUP(C55,'외부사업 비공개승인관리_국내'!$C:$H,4,FALSE) -> 2019-11-01 | F55: =VLOOKUP(C55,'외부사업 비공개승인관리_국내'!$C:$H,5,FALSE) -> 산업통상부 | G55: =VLOOKUP(C55,'외부사업 비공개승인관리_국내'!$C:$H,6,FALSE) -> 2025-02-25 | H55: =VLOOKUP(C55,'외부사업 비공개승인관리_국내'!$C:$H,3,FALSE) -> 반려 | I55: =LEFT(VLOOKUP(C55,'국내평가(ORS)'!P:AO,26,0),10) -> 2019-11-01 | J55: =IF(I55=E55,"O","X") -> O | K55: =VLOOKUP(C55, '국내평가(ORS)'!P:AL, 23, 0) -> 평가반려 2021-06-07 | L55: =VLOOKUP(C55, '국내평가(ORS)'!A:AL, 2, 0) -> 반려 | M55: X | N55: 선택 | O55: 선택 | P55: =IF(AND(H55<>"반려", L55<>"반려"),"검토가능","") | Q55: 선택 | R55: 종결 | S55: 5월 26일
A56: 54 | B56: 프로그램감축사업 | C56: 용탕온도관리시스템 도입을 통한 온실가스 감축 사업 | D56: 한국산업단지공단 | E56: =VLOOKUP(C56,'외부사업 비공개승인관리_국내'!$C:$H,4,FALSE) -> 2019-11-01 | F56: =VLOOKUP(C56,'외부사업 비공개승인관리_국내'!$C:$H,5,FALSE) -> 산업통상부 | G56: =VLOOKUP(C56,'외부사업 비공개승인관리_국내'!$C:$H,6,FALSE) -> 2025-02-25 | H56: =VLOOKUP(C56,'외부사업 비공개승인관리_국내'!$C:$H,3,FALSE) -> 반려 | I56: =LEFT(VLOOKUP(C56,'국내평가(ORS)'!P:AO,26,0),10) -> 2019-11-01 | J56: =IF(I56=E56,"O","X") -> O | K56: =VLOOKUP(C56, '국내평가(ORS)'!P:AL, 23, 0) -> 평가반려 2021-06-07 | L56: =VLOOKUP(C56, '국내평가(ORS)'!A:AL, 2, 0) -> 반려 | M56: X | N56: 선택 | O56: 선택 | P56: =IF(AND(H56<>"반려", L56<>"반려"),"검토가능","") | Q56: 선택 | R56: 종결 | S56: 5월 26일
A57: 55 | B57: 프로그램감축사업 | C57: 용탕온도관리시스템 도입을 통한 온실가스 감축 사업 | D57: 한국산업단지공단 | E57: =VLOOKUP(C57,'외부사업 비공개승인관리_국내'!$C:$H,4,FALSE) -> 2019-11-01 | F57: =VLOOKUP(C57,'외부사업 비공개승인관리_국내'!$C:$H,5,FALSE) -> 산업통상부 | G57: =VLOOKUP(C57,'외부사업 비공개승인관리_국내'!$C:$H,6,FALSE) -> 2025-02-25 | H57: =VLOOKUP(C57,'외부사업 비공개승인관리_국내'!$C:$H,3,FALSE) -> 반려 | I57: =LEFT(VLOOKUP(C57,'국내평가(ORS)'!P:AO,26,0),10) -> 2019-11-01 | J57: =IF(I57=E57,"O","X") -> O | K57: =VLOOKUP(C57, '국내평가(ORS)'!P:AL, 23, 0) -> 평가반려 2021-06-07 | L57: =VLOOKUP(C57, '국내평가(ORS)'!A:AL, 2, 0) -> 반려 | M57: X | N57: 선택 | O57: 선택 | P57: =IF(AND(H57<>"반려", L57<>"반려"),"검토가능","") | Q57: 선택 | R57: 종결 | S57: 5월 26일
A58: 56 | B58: 프로그램감축사업 | C58: ㈜엘지화학 자가 소비용 태양광 발전설비의 설치 지원을 통한 프로그램 감축사업 | D58: 주식회사 엘지화학 | E58: =VLOOKUP(C58,'외부사업 비공개승인관리_국내'!$C:$H,4,FALSE) -> 2019-10-11 | F58: =VLOOKUP(C58,'외부사업 비공개승인관리_국내'!$C:$H,5,FALSE) -> 기후에너지환경부 | G58: =VLOOKUP(C58,'외부사업 비공개승인관리_국내'!$C:$H,6,FALSE) -> 2025-02-25 | H58: =VLOOKUP(C58,'외부사업 비공개승인관리_국내'!$C:$H,3,FALSE) -> 반려 | I58: =LEFT(VLOOKUP(C58,'국내평가(ORS)'!P:AO,26,0),10) -> 2019-12-19 | J58: =IF(I58=E58,"O","X") -> X | K58: =VLOOKUP(C58, '국내평가(ORS)'!P:AL, 23, 0) -> [보완3차]평가반려 2021-11-29 | L58: =VLOOKUP(C58, '국내평가(ORS)'!A:AL, 2, 0) -> 반려 | M58: X | N58: 선택 | O58: 선택 | P58: =IF(AND(H58<>"반려", L58<>"반려"),"검토가능","") | Q58: 선택 | R58: 종결 | S58: 5월 26일 | U58: 19년 12월 19일 신청 사업 ORS 반려 필요
A59: 57 | B59: 단일감축사업 | C59: 대평산업개발의 정제유 및 B-C유에서 도시가스(LNG)로의 연료전환을 통한 온실가스 배출 감축사업 | D59: (주)대평산업개발 | E59: =VLOOKUP(C59,'외부사업 비공개승인관리_국내'!$C:$H,4,FALSE) -> 2019-08-23 | F59: =VLOOKUP(C59,'외부사업 비공개승인관리_국내'!$C:$H,5,FALSE) -> 산업통상부 | G59: =VLOOKUP(C59,'외부사업 비공개승인관리_국내'!$C:$H,6,FALSE) -> 2022-06-02 | H59: =VLOOKUP(C59,'외부사업 비공개승인관리_국내'!$C:$H,3,FALSE) -> 보완요청 | I59: =LEFT(VLOOKUP(C59,'국내평가(ORS)'!P:AO,26,0),10) -> 2025-07-08 | J59: =IF(I59=E59,"O","X") -> X | K59: =VLOOKUP(C59, '국내평가(ORS)'!P:AL, 23, 0) -> [보완2차]보완요청 2025-11-05 | L59: =VLOOKUP(C59, '국내평가(ORS)'!A:AL, 2, 0) -> 인증유효기간 갱신 | M59: 검토필요 | N59: 보완요청 | O59: 사업자 | P59: =IF(AND(H59<>"반려", L59<>"반려"),"검토가능","") -> 검토가능 | Q59: 보완요청 | R59: 사업자 | S59: 5월 26일 | T59: 에코시안_박세은 | U59: 사업계획서 내 보안유지 필요부분 구체화 필요 | AC59: 내부방침
A60: 58 | B60: 단일감축사업 | C60: 덕산지에스의 부생연료유 2호에서 도시가스(LNG)로의 연료전환을 통한 온실가스 배출 감축사업 | D60: (주)덕산지에스 | E60: =VLOOKUP(C60,'외부사업 비공개승인관리_국내'!$C:$H,4,FALSE) -> 2019-07-29 | F60: =VLOOKUP(C60,'외부사업 비공개승인관리_국내'!$C:$H,5,FALSE) -> 산업통상부 | G60: =VLOOKUP(C60,'외부사업 비공개승인관리_국내'!$C:$H,6,FALSE) -> 2022-06-02 | H60: =VLOOKUP(C60,'외부사업 비공개승인관리_국내'!$C:$H,3,FALSE) -> 보완요청 | I60: =LEFT(VLOOKUP(C60,'국내평가(ORS)'!P:AO,26,0),10) -> 2019-07-29 | J60: =IF(I60=E60,"O","X") -> O | K60: =VLOOKUP(C60, '국내평가(ORS)'!P:AL, 23, 0) -> [보완2차]착수신고 2022-05-16 | L60: =VLOOKUP(C60, '국내평가(ORS)'!A:AL, 2, 0) -> 승인 | M60: 검토필요 | N60: 보완요청 | O60: 사업자 | P60: =IF(AND(H60<>"반려", L60<>"반려"),"검토가능","") -> 검토가능 | Q60: 보완요청 | R60: 사업자 | S60: 5월 26일 | T60: 에코시안_박세은 | U60: 사업계획서 내 보안유지 필요부분 구체화 필요 | AC60: 내부방침
A61: 59 | B61: 단일감축사업 | C61: 남부산업의 이온정제유에서 LNG로 연료전환을 통한 온실가스 배출 감축사업 | D61: 남부산업[주] | E61: =VLOOKUP(C61,'외부사업 비공개승인관리_국내'!$C:$H,4,FALSE) -> 2019-07-17 | F61: =VLOOKUP(C61,'외부사업 비공개승인관리_국내'!$C:$H,5,FALSE) -> 산업통상부 | G61: =VLOOKUP(C61,'외부사업 비공개승인관리_국내'!$C:$H,6,FALSE) -> 2022-06-02 | H61: =VLOOKUP(C61,'외부사업 비공개승인관리_국내'!$C:$H,3,FALSE) -> 보완요청 | I61: =LEFT(VLOOKUP(C61,'국내평가(ORS)'!P:AO,26,0),10) -> 2019-07-17 | J61: =IF(I61=E61,"O","X") -> O | K61: =VLOOKUP(C61, '국내평가(ORS)'!P:AL, 23, 0) -> [보완1차]착수신고 2021-09-29 | L61: =VLOOKUP(C61, '국내평가(ORS)'!A:AL, 2, 0) -> 승인 | M61: 검토필요 | N61: 보완요청 | O61: 사업자 | P61: =IF(AND(H61<>"반려", L61<>"반려"),"검토가능","") -> 검토가능 | Q61: 보완요청 | R61: 사업자 | S61: 5월 26일 | T61: 에코시안_박세은 | U61: 사업계획서 내 보안유지 필요부분 구체화 필요 | AC61: 내부방침
A62: 60 | B62: 단일감축사업 | C62: 현대리바트의 부생연료 1호에서 LNG로 연료전환을 통한 온실가스 배출 감축사업 | D62: (주)현대리바트 | E62: =VLOOKUP(C62,'외부사업 비공개승인관리_국내'!$C:$H,4,FALSE) -> 2019-06-13 | F62: =VLOOKUP(C62,'외부사업 비공개승인관리_국내'!$C:$H,5,FALSE) -> 산업통상부 | G62: =VLOOKUP(C62,'외부사업 비공개승인관리_국내'!$C:$H,6,FALSE) -> 2022-06-02 | H62: =VLOOKUP(C62,'외부사업 비공개승인관리_국내'!$C:$H,3,FALSE) -> 보완요청 | I62: =LEFT(VLOOKUP(C62,'국내평가(ORS)'!P:AO,26,0),10) -> 2019-06-13 | J62: =IF(I62=E62,"O","X") -> O | K62: =VLOOKUP(C62, '국내평가(ORS)'!P:AL, 23, 0) -> 착수신고 2021-05-24 | L62: =VLOOKUP(C62, '국내평가(ORS)'!A:AL, 2, 0) -> 승인 | M62: 검토필요 | N62: 보완요청 | O62: 사업자 | P62: =IF(AND(H62<>"반려", L62<>"반려"),"검토가능","") -> 검토가능 | Q62: 보완요청 | R62: 사업자 | S62: 5월 26일 | T62: 에코시안_박세은 | U62: 사업계획서 내 보안유지 필요부분 구체화 필요 | AC62: 내부방침
A63: 61 | B63: 단일감축사업 | C63: 삼일이노팩의 B-C유에서 LNG로 연료전환을 통한 온실가스 배출 감축사업 | D63: 주식회사 삼일이노팩 | E63: =VLOOKUP(C63,'외부사업 비공개승인관리_국내'!$C:$H,4,FALSE) -> 2019-05-14 | F63: =VLOOKUP(C63,'외부사업 비공개승인관리_국내'!$C:$H,5,FALSE) -> 산업통상부 | G63: =VLOOKUP(C63,'외부사업 비공개승인관리_국내'!$C:$H,6,FALSE) -> 2022-06-02 | H63: =VLOOKUP(C63,'외부사업 비공개승인관리_국내'!$C:$H,3,FALSE) -> 보완요청 | I63: =LEFT(VLOOKUP(C63,'국내평가(ORS)'!P:AO,26,0),10) -> 2019-05-14 | J63: =IF(I63=E63,"O","X") -> O | K63: =VLOOKUP(C63, '국내평가(ORS)'!P:AL, 23, 0) -> 착수신고 2021-02-09 | L63: =VLOOKUP(C63, '국내평가(ORS)'!A:AL, 2, 0) -> 승인 | M63: 검토필요 | N63: 보완요청 | O63: 사업자 | P63: =IF(AND(H63<>"반려", L63<>"반려"),"검토가능","") -> 검토가능 | Q63: 보완요청 | R63: 사업자 | S63: 5월 26일 | T63: 에코시안_박세은 | U63: 사업계획서 내 보안유지 필요부분 구체화 필요 | AC63: 내부방침
A64: 62 | B64: 단일감축사업 | C64: 이연제약 진천공장의 B-C유에서 LNG로의 연료전환을 통한 온실가스 배출 감축사업 | D64: 이연제약(주) | E64: =VLOOKUP(C64,'외부사업 비공개승인관리_국내'!$C:$H,4,FALSE) -> 2019-04-02 | F64: =VLOOKUP(C64,'외부사업 비공개승인관리_국내'!$C:$H,5,FALSE) -> 산업통상부 | G64: =VLOOKUP(C64,'외부사업 비공개승인관리_국내'!$C:$H,6,FALSE) -> 2022-06-02 | H64: =VLOOKUP(C64,'외부사업 비공개승인관리_국내'!$C:$H,3,FALSE) -> 보완요청 | I64: =LEFT(VLOOKUP(C64,'국내평가(ORS)'!P:AO,26,0),10) -> 2019-04-02 | J64: =IF(I64=E64,"O","X") -> O | K64: =VLOOKUP(C64, '국내평가(ORS)'!P:AL, 23, 0) -> [보완1차]착수신고 2022-02-10 | L64: =VLOOKUP(C64, '국내평가(ORS)'!A:AL, 2, 0) -> 승인 | M64: 검토필요 | N64: 보완요청 | O64: 사업자 | P64: =IF(AND(H64<>"반려", L64<>"반려"),"검토가능","") -> 검토가능 | Q64: 보완요청 | R64: 사업자 | S64: 5월 26일 | T64: 에코시안_박세은 | U64: 사업계획서 내 보안유지 필요부분 구체화 필요 | AC64: 내부방침
A65: 63 | B65: 단일감축사업 | C65: 에이스침대 여주공장의 B-C유에서 도시가스(LNG)로 연료전환을 통한 온실가스 배출 감축사업 | D65: (주)에이스침대중부공장 | E65: =VLOOKUP(C65,'외부사업 비공개승인관리_국내'!$C:$H,4,FALSE) -> 2019-04-02 | F65: =VLOOKUP(C65,'외부사업 비공개승인관리_국내'!$C:$H,5,FALSE) -> 산업통상부 | G65: =VLOOKUP(C65,'외부사업 비공개승인관리_국내'!$C:$H,6,FALSE) -> 2023-03-27 | H65: =VLOOKUP(C65,'외부사업 비공개승인관리_국내'!$C:$H,3,FALSE) -> 보완요청 | I65: =LEFT(VLOOKUP(C65,'국내평가(ORS)'!P:AO,26,0),10) -> 2019-04-02 | J65: =IF(I65=E65,"O","X") -> O | K65: =VLOOKUP(C65, '국내평가(ORS)'!P:AL, 23, 0) -> [보완3차]착수신고 2022-10-17 | L65: =VLOOKUP(C65, '국내평가(ORS)'!A:AL, 2, 0) -> 승인 | M65: 검토필요 | N65: 보완요청 | O65: 사업자 | P65: =IF(AND(H65<>"반려", L65<>"반려"),"검토가능","") -> 검토가능 | Q65: 보완요청 | R65: 사업자 | S65: 11월 30일 | U65: 사업계획서 내 보안유지 필요부분 구체화 필요 | AC65: 내부방침
A66: 64 | B66: 단일감축사업 | C66: 에이스침대 중부공장의 B-C유에서 도시가스(LNG)로 연료전환을 통한 온실가스 배출 감축사업 | D66: (주)에이스침대중부공장 | E66: =VLOOKUP(C66,'외부사업 비공개승인관리_국내'!$C:$H,4,FALSE) -> 2024-07-16 | F66: =VLOOKUP(C66,'외부사업 비공개승인관리_국내'!$C:$H,5,FALSE) -> 산업통상부 | G66: =VLOOKUP(C66,'외부사업 비공개승인관리_국내'!$C:$H,6,FALSE) -> 2024-09-19 | H66: =VLOOKUP(C66,'외부사업 비공개승인관리_국내'!$C:$H,3,FALSE) -> 심의완료 | I66: =LEFT(VLOOKUP(C66,'국내평가(ORS)'!P:AO,26,0),10) -> 2019-04-02 | J66: =IF(I66=E66,"O","X") -> X | K66: =VLOOKUP(C66, '국내평가(ORS)'!P:AL, 23, 0) -> [보완3차]착수신고 2024-01-12 | L66: =VLOOKUP(C66, '국내평가(ORS)'!A:AL, 2, 0) -> 승인 | N66: 심의승인 | O66: 종결 | Q66: 심의승인 | R66: 종결 | S66: 45567 | T66: 에코시안_조은지 | AC66: 내부방침
A67: 65 | B67: 단일감축사업 | C67: 부일레미콘의 B-C유에서 도시가스(LNG)로 연료전환을 통한 온실가스 배출 감축사업 | D67: (주)부일레미콘 | E67: =VLOOKUP(C67,'외부사업 비공개승인관리_국내'!$C:$H,4,FALSE) -> 2019-04-02 | F67: =VLOOKUP(C67,'외부사업 비공개승인관리_국내'!$C:$H,5,FALSE) -> 산업통상부 | G67: =VLOOKUP(C67,'외부사업 비공개승인관리_국내'!$C:$H,6,FALSE) -> 2022-06-02 | H67: =VLOOKUP(C67,'외부사업 비공개승인관리_국내'!$C:$H,3,FALSE) -> 보완요청 | I67: =LEFT(VLOOKUP(C67,'국내평가(ORS)'!P:AO,26,0),10) -> 2019-04-02 | J67: =IF(I67=E67,"O","X") -> O | K67: =VLOOKUP(C67, '국내평가(ORS)'!P:AL, 23, 0) -> [보완1차]착수신고 2021-12-17 | L67: =VLOOKUP(C67, '국내평가(ORS)'!A:AL, 2, 0) -> 승인 | M67: 검토필요 | N67: 보완요청 | O67: 사업자 | P67: =IF(AND(H67<>"반려", L67<>"반려"),"검토가능","") -> 검토가능 | Q67: 보완요청 | R67: 사업자 | S67: 5월 26일 | T67: 에코시안_박세은 | U67: 사업계획서 내 보안유지 필요부분 구체화 필요 | AC67: 내부방침
A68: 66 | B68: 프로그램감축사업 | C68: 고효율 공기압축기 도입을 통한 온실가스 감축사업 | D68: 한국산업단지공단 | E68: =VLOOKUP(C68,'외부사업 비공개승인관리_국내'!$C:$H,4,FALSE) -> 2018-12-03 | F68: =VLOOKUP(C68,'외부사업 비공개승인관리_국내'!$C:$H,5,FALSE) -> 산업통상부 | G68: =VLOOKUP(C68,'외부사업 비공개승인관리_국내'!$C:$H,6,FALSE) -> 2025-02-25 | H68: =VLOOKUP(C68,'외부사업 비공개승인관리_국내'!$C:$H,3,FALSE) -> 반려 | I68: =LEFT(VLOOKUP(C68,'국내평가(ORS)'!P:AO,26,0),10) -> 2018-12-03 | J68: =IF(I68=E68,"O","X") -> O | K68: =VLOOKUP(C68, '국내평가(ORS)'!P:AL, 23, 0) -> 평가반려 2021-06-07 | L68: =VLOOKUP(C68, '국내평가(ORS)'!A:AL, 2, 0) -> 반려 | M68: X | N68: 선택 | O68: 선택 | P68: =IF(AND(H68<>"반려", L68<>"반려"),"검토가능","") | Q68: 선택 | R68: 종결 | S68: 5월 26일
A69: 67 | B69: 프로그램감축사업 | C69: 서울시 태양광 미니발전소 보급사업에 의한 온실가스 배출량 감축사업 | D69: 서울특별시 | E69: =VLOOKUP(C69,'외부사업 비공개승인관리_국내'!$C:$H,4,FALSE) -> 2018-11-08 | F69: =VLOOKUP(C69,'외부사업 비공개승인관리_국내'!$C:$H,5,FALSE) -> 기후에너지환경부 | G69: =VLOOKUP(C69,'외부사업 비공개승인관리_국내'!$C:$H,6,FALSE) -> 2025-02-25 | H69: =VLOOKUP(C69,'외부사업 비공개승인관리_국내'!$C:$H,3,FALSE) -> 반려 | I69: =LEFT(VLOOKUP(C69,'국내평가(ORS)'!P:AO,26,0),10) -> 2018-11-08 | J69: =IF(I69=E69,"O","X") -> O | K69: =VLOOKUP(C69, '국내평가(ORS)'!P:AL, 23, 0) -> [보완1차]평가반려 2021-11-08 | L69: =VLOOKUP(C69, '국내평가(ORS)'!A:AL, 2, 0) -> 반려 | M69: X | N69: 선택 | O69: 선택 | P69: =IF(AND(H69<>"반려", L69<>"반려"),"검토가능","") | Q69: 선택 | R69: 종결 | S69: 5월 26일
A70: 68 | B70: 단일감축사업 | C70: (주)동방전기에서의 가스절연개폐장치 검사용 SF6 회수․정제 및 재사용을 통한 SF6 감축사업 | D70: 한국전력공사 | E70: =VLOOKUP(C70,'외부사업 비공개승인관리_국내'!$C:$H,4,FALSE) -> 2018-10-23 | F70: =VLOOKUP(C70,'외부사업 비공개승인관리_국내'!$C:$H,5,FALSE) -> 산업통상부 | G70: =VLOOKUP(C70,'외부사업 비공개승인관리_국내'!$C:$H,6,FALSE) -> 2025-02-25 | H70: =VLOOKUP(C70,'외부사업 비공개승인관리_국내'!$C:$H,3,FALSE) -> 반려 | I70: =LEFT(VLOOKUP(C70,'국내평가(ORS)'!P:AO,26,0),10) -> 2018-10-23 | J70: =IF(I70=E70,"O","X") -> O | K70: =VLOOKUP(C70, '국내평가(ORS)'!P:AL, 23, 0) -> [보완1차]평가반려 2021-12-23 | L70: =VLOOKUP(C70, '국내평가(ORS)'!A:AL, 2, 0) -> 반려 | M70: X | N70: 선택 | O70: 선택 | P70: =IF(AND(H70<>"반려", L70<>"반려"),"검토가능","") | Q70: 선택 | R70: 종결 | S70: 5월 26일
A71: 69 | B71: 단일감축사업 | C71: 제천 장락 주공 1단지 아파트 연료전환을 통한 온실가스 감축사업 | D71: 한국토지주택공사 | E71: =VLOOKUP(C71,'외부사업 비공개승인관리_국내'!$C:$H,4,FALSE) -> 2025-08-06 | F71: =VLOOKUP(C71,'외부사업 비공개승인관리_국내'!$C:$H,5,FALSE) -> 산업통상부 | G71: =VLOOKUP(C71,'외부사업 비공개승인관리_국내'!$C:$H,6,FALSE) -> 2026-02-06 | H71: =VLOOKUP(C71,'외부사업 비공개승인관리_국내'!$C:$H,3,FALSE) -> 반려 | I71: =LEFT(VLOOKUP(C71,'국내평가(ORS)'!P:AO,26,0),10) -> 2017-06-09 | J71: =IF(I71=E71,"O","X") -> X | K71: =VLOOKUP(C71, '국내평가(ORS)'!P:AL, 23, 0) -> 착수신고 2018-08-07 | L71: =VLOOKUP(C71, '국내평가(ORS)'!A:AL, 2, 0) -> 승인 | M71: 검토필요 | N71: 보완요청 | O71: 사업자 | P71: =IF(AND(H71<>"반려", L71<>"반려"),"검토가능","") | Q71: 반려완료 | R71: 종결 | S71: 46079 | T71: 에코시안_남혜원 | U71: 외부사업 사업계획서에 대한 정보 비공개 신청을 철회합니다. | AC71: 내부방침
A72: 70 | B72: 단일감축사업 | C72: 부천 춘의단지 아파트 연료전환을 통한 온실가스 감축사업 | D72: 한국토지주택공사 | E72: =VLOOKUP(C72,'외부사업 비공개승인관리_국내'!$C:$H,4,FALSE) -> 2025-10-15 | F72: =VLOOKUP(C72,'외부사업 비공개승인관리_국내'!$C:$H,5,FALSE) -> 산업통상부 | G72: =VLOOKUP(C72,'외부사업 비공개승인관리_국내'!$C:$H,6,FALSE) -> 2026-02-06 | H72: =VLOOKUP(C72,'외부사업 비공개승인관리_국내'!$C:$H,3,FALSE) -> 반려 | I72: =LEFT(VLOOKUP(C72,'국내평가(ORS)'!P:AO,26,0),10) -> 2017-06-09 | J72: =IF(I72=E72,"O","X") -> X | K72: =VLOOKUP(C72, '국내평가(ORS)'!P:AL, 23, 0) -> 착수신고 2018-08-07 | L72: =VLOOKUP(C72, '국내평가(ORS)'!A:AL, 2, 0) -> 승인 | M72: 검토필요 | N72: 보완요청 | O72: 사업자 | P72: =IF(AND(H72<>"반려", L72<>"반려"),"검토가능","") | Q72: 반려완료 | R72: 종결 | S72: 46079 | T72: 에코시안 | U72: 외부사업 사업계획서에 대한 정보 비공개 신청을 철회합니다. | AC72: 내부방침
A73: 71 | B73: 단일감축사업 | C73: 서울 월계 주공1단지 아파트 연료전환을 통한 온실가스 감축사업 | D73: 한국토지주택공사 | E73: =VLOOKUP(C73,'외부사업 비공개승인관리_국내'!$C:$H,4,FALSE) -> 2025-10-15 | F73: =VLOOKUP(C73,'외부사업 비공개승인관리_국내'!$C:$H,5,FALSE) -> 산업통상부 | G73: =VLOOKUP(C73,'외부사업 비공개승인관리_국내'!$C:$H,6,FALSE) -> 2026-02-06 | H73: =VLOOKUP(C73,'외부사업 비공개승인관리_국내'!$C:$H,3,FALSE) -> 반려 | I73: =LEFT(VLOOKUP(C73,'국내평가(ORS)'!P:AO,26,0),10) -> 2017-06-09 | J73: =IF(I73=E73,"O","X") -> X | K73: =VLOOKUP(C73, '국내평가(ORS)'!P:AL, 23, 0) -> 착수신고 2018-08-07 | L73: =VLOOKUP(C73, '국내평가(ORS)'!A:AL, 2, 0) -> 승인 | M73: 검토필요 | N73: 보완요청 | O73: 사업자 | P73: =IF(AND(H73<>"반려", L73<>"반려"),"검토가능","") | Q73: 반려완료 | R73: 종결 | S73: 46079 | T73: 에코시안 | U73: 외부사업 사업계획서에 대한 정보 비공개 신청을 철회합니다. | AC73: 내부방침
A74: 72 | B74: 단일감축사업 | C74: 서울 우면아파트 연료전환을 통한 온실가스 감축사업 | D74: 한국토지주택공사 | E74: =VLOOKUP(C74,'외부사업 비공개승인관리_국내'!$C:$H,4,FALSE) -> 2025-10-15 | F74: =VLOOKUP(C74,'외부사업 비공개승인관리_국내'!$C:$H,5,FALSE) -> 산업통상부 | G74: =VLOOKUP(C74,'외부사업 비공개승인관리_국내'!$C:$H,6,FALSE) -> 2026-02-06 | H74: =VLOOKUP(C74,'외부사업 비공개승인관리_국내'!$C:$H,3,FALSE) -> 반려 | I74: =LEFT(VLOOKUP(C74,'국내평가(ORS)'!P:AO,26,0),10) -> 2017-06-09 | J74: =IF(I74=E74,"O","X") -> X | K74: =VLOOKUP(C74, '국내평가(ORS)'!P:AL, 23, 0) -> 착수신고 2018-08-07 | L74: =VLOOKUP(C74, '국내평가(ORS)'!A:AL, 2, 0) -> 승인 | M74: 검토필요 | N74: 보완요청 | O74: 사업자 | P74: =IF(AND(H74<>"반려", L74<>"반려"),"검토가능","") | Q74: 반려완료 | R74: 종결 | S74: 46079 | T74: KECM | U74: 외부사업 사업계획서에 대한 정보 비공개 신청을 철회합니다. | V74: X | W74: X | X74: O | Y74: O | Z74: X | AA74: X | AB74: X | AC74: 내부방침
A75: 73 | B75: 단일감축사업 | C75: 서울 번동 주공 5단지 아파트 연료전환을 통한 온실가스 감축사업 | D75: 한국토지주택공사 | E75: =VLOOKUP(C75,'외부사업 비공개승인관리_국내'!$C:$H,4,FALSE) -> 2025-10-15 | F75: =VLOOKUP(C75,'외부사업 비공개승인관리_국내'!$C:$H,5,FALSE) -> 산업통상부 | G75: =VLOOKUP(C75,'외부사업 비공개승인관리_국내'!$C:$H,6,FALSE) -> 2026-02-06 | H75: =VLOOKUP(C75,'외부사업 비공개승인관리_국내'!$C:$H,3,FALSE) -> 반려 | I75: =LEFT(VLOOKUP(C75,'국내평가(ORS)'!P:AO,26,0),10) -> 2017-06-09 | J75: =IF(I75=E75,"O","X") -> X | K75: =VLOOKUP(C75, '국내평가(ORS)'!P:AL, 23, 0) -> 착수신고 2018-08-07 | L75: =VLOOKUP(C75, '국내평가(ORS)'!A:AL, 2, 0) -> 승인 | M75: 검토필요 | N75: 보완요청 | O75: 사업자 | P75: =IF(AND(H75<>"반려", L75<>"반려"),"검토가능","") | Q75: 반려완료 | R75: 종결 | S75: 46079 | T75: KECM | U75: 외부사업 사업계획서에 대한 정보 비공개 신청을 철회합니다. | V75: X | W75: X | X75: O | Y75: O | Z75: X | AA75: X | AB75: X | AC75: 내부방침
A76: 74 | B76: 단일감축사업 | C76: 서울 번동 주공3단지 아파트연료전환을 통한 온실가스 감축사업 | D76: 한국토지주택공사 | E76: =VLOOKUP(C76,'외부사업 비공개승인관리_국내'!$C:$H,4,FALSE) -> 2025-10-15 | F76: =VLOOKUP(C76,'외부사업 비공개승인관리_국내'!$C:$H,5,FALSE) -> 산업통상부 | G76: =VLOOKUP(C76,'외부사업 비공개승인관리_국내'!$C:$H,6,FALSE) -> 2026-02-06 | H76: =VLOOKUP(C76,'외부사업 비공개승인관리_국내'!$C:$H,3,FALSE) -> 반려 | I76: =LEFT(VLOOKUP(C76,'국내평가(ORS)'!P:AO,26,0),10) -> 2017-06-09 | J76: =IF(I76=E76,"O","X") -> X | K76: =VLOOKUP(C76, '국내평가(ORS)'!P:AL, 23, 0) -> 착수신고 2018-08-07 | L76: =VLOOKUP(C76, '국내평가(ORS)'!A:AL, 2, 0) -> 승인 | M76: 검토필요 | N76: 보완요청 | O76: 사업자 | P76: =IF(AND(H76<>"반려", L76<>"반려"),"검토가능","") | Q76: 반려완료 | R76: 종결 | S76: 46079 | T76: KECM | U76: 외부사업 사업계획서에 대한 정보 비공개 신청을 철회합니다. | V76: X | W76: X | X76: O | Y76: O | Z76: X | AA76: X | AB76: X | AC76: 내부방침
A77: 75 | B77: 단일감축사업 | C77: 서울 번동 주공2단지 아파트 연료전환을 통한 온실가스 감축사업 | D77: 한국토지주택공사 | E77: =VLOOKUP(C77,'외부사업 비공개승인관리_국내'!$C:$H,4,FALSE) -> 2025-10-15 | F77: =VLOOKUP(C77,'외부사업 비공개승인관리_국내'!$C:$H,5,FALSE) -> 산업통상부 | G77: =VLOOKUP(C77,'외부사업 비공개승인관리_국내'!$C:$H,6,FALSE) -> 2026-02-06 | H77: =VLOOKUP(C77,'외부사업 비공개승인관리_국내'!$C:$H,3,FALSE) -> 반려 | I77: =LEFT(VLOOKUP(C77,'국내평가(ORS)'!P:AO,26,0),10) -> 2017-06-09 | J77: =IF(I77=E77,"O","X") -> X | K77: =VLOOKUP(C77, '국내평가(ORS)'!P:AL, 23, 0) -> 착수신고 2018-08-07 | L77: =VLOOKUP(C77, '국내평가(ORS)'!A:AL, 2, 0) -> 승인 | M77: 검토필요 | N77: 보완요청 | O77: 사업자 | P77: =IF(AND(H77<>"반려", L77<>"반려"),"검토가능","") | Q77: 반려완료 | R77: 종결 | S77: 46079 | T77: KECM | U77: 외부사업 사업계획서에 대한 정보 비공개 신청을 철회합니다. | V77: X | W77: X | X77: O | Y77: O | Z77: X | AA77: X | AB77: X | AC77: 내부방침
A78: 76 | B78: 단일감축사업 | C78: 광주 하남 주공 1차 아파트 연료전환을 통한 온실가스 감축사업 | D78: 한국토지주택공사 | E78: =VLOOKUP(C78,'외부사업 비공개승인관리_국내'!$C:$H,4,FALSE) -> 2025-10-15 | F78: =VLOOKUP(C78,'외부사업 비공개승인관리_국내'!$C:$H,5,FALSE) -> 산업통상부 | G78: =VLOOKUP(C78,'외부사업 비공개승인관리_국내'!$C:$H,6,FALSE) -> 2026-02-06 | H78: =VLOOKUP(C78,'외부사업 비공개승인관리_국내'!$C:$H,3,FALSE) -> 반려 | I78: =LEFT(VLOOKUP(C78,'국내평가(ORS)'!P:AO,26,0),10) -> 2025-02-19 | J78: =IF(I78=E78,"O","X") -> X | K78: =VLOOKUP(C78, '국내평가(ORS)'!P:AL, 23, 0) -> [보완3차]협의통보 2025-10-29 | L78: =VLOOKUP(C78, '국내평가(ORS)'!A:AL, 2, 0) -> 인증유효기간 갱신 | M78: 검토필요 | N78: 보완요청 | O78: 사업자 | P78: =IF(AND(H78<>"반려", L78<>"반려"),"검토가능","") | Q78: 반려완료 | R78: 종결 | S78: 46079 | T78: KECM | U78: 외부사업 사업계획서에 대한 정보 비공개 신청을 철회합니다. | V78: X | W78: X | X78: O | Y78: O | Z78: X | AA78: X | AB78: X | AC78: 내부방침
A79: 77 | B79: 단일감축사업 | C79: 광주 우산 주공 3단지 아파트 연료전환을 통한 온실가스 감축사업 | D79: 한국토지주택공사 | E79: =VLOOKUP(C79,'외부사업 비공개승인관리_국내'!$C:$H,4,FALSE) -> 2025-10-15 | F79: =VLOOKUP(C79,'외부사업 비공개승인관리_국내'!$C:$H,5,FALSE) -> 산업통상부 | G79: =VLOOKUP(C79,'외부사업 비공개승인관리_국내'!$C:$H,6,FALSE) -> 2026-02-06 | H79: =VLOOKUP(C79,'외부사업 비공개승인관리_국내'!$C:$H,3,FALSE) -> 반려 | I79: =LEFT(VLOOKUP(C79,'국내평가(ORS)'!P:AO,26,0),10) -> 2025-02-19 | J79: =IF(I79=E79,"O","X") -> X | K79: =VLOOKUP(C79, '국내평가(ORS)'!P:AL, 23, 0) -> [보완3차]신청 2026-01-20 | L79: =VLOOKUP(C79, '국내평가(ORS)'!A:AL, 2, 0) -> 인증유효기간 갱신 | M79: 검토필요 | N79: 보완요청 | O79: 사업자 | P79: =IF(AND(H79<>"반려", L79<>"반려"),"검토가능","") | Q79: 반려완료 | R79: 종결 | S79: 46079 | T79: KECM | U79: 외부사업 사업계획서에 대한 정보 비공개 신청을 철회합니다. | V79: X | W79: X | X79: O | Y79: O | Z79: X | AA79: X | AB79: X | AC79: 내부방침
A80: 78 | B80: 단일감축사업 | C80: 광주 오치 주공 1단지 아파트 연료전환을 통한 온실가스 감축사업 | D80: 한국토지주택공사 | E80: =VLOOKUP(C80,'외부사업 비공개승인관리_국내'!$C:$H,4,FALSE) -> 2025-10-15 | F80: =VLOOKUP(C80,'외부사업 비공개승인관리_국내'!$C:$H,5,FALSE) -> 산업통상부 | G80: =VLOOKUP(C80,'외부사업 비공개승인관리_국내'!$C:$H,6,FALSE) -> 2026-02-06 | H80: =VLOOKUP(C80,'외부사업 비공개승인관리_국내'!$C:$H,3,FALSE) -> 반려 | I80: =LEFT(VLOOKUP(C80,'국내평가(ORS)'!P:AO,26,0),10) -> 2025-02-12 | J80: =IF(I80=E80,"O","X") -> X | K80: =VLOOKUP(C80, '국내평가(ORS)'!P:AL, 23, 0) -> [보완3차]협의통보 2025-10-29 | L80: =VLOOKUP(C80, '국내평가(ORS)'!A:AL, 2, 0) -> 인증유효기간 갱신 | M80: 검토필요 | N80: 보완요청 | O80: 사업자 | P80: =IF(AND(H80<>"반려", L80<>"반려"),"검토가능","") | Q80: 반려완료 | R80: 종결 | S80: 46079 | T80: KECM | U80: 외부사업 사업계획서에 대한 정보 비공개 신청을 철회합니다. | V80: X | W80: X | X80: O | Y80: O | Z80: X | AA80: X | AB80: X | AC80: 내부방침
A81: 79 | B81: 단일감축사업 | C81: 광주 쌍촌 주공 아파트 연료전환을 통한 온실가스 감축사업 | D81: 한국토지주택공사 | E81: =VLOOKUP(C81,'외부사업 비공개승인관리_국내'!$C:$H,4,FALSE) -> 2025-10-15 | F81: =VLOOKUP(C81,'외부사업 비공개승인관리_국내'!$C:$H,5,FALSE) -> 산업통상부 | G81: =VLOOKUP(C81,'외부사업 비공개승인관리_국내'!$C:$H,6,FALSE) -> 2026-02-06 | H81: =VLOOKUP(C81,'외부사업 비공개승인관리_국내'!$C:$H,3,FALSE) -> 반려 | I81: =LEFT(VLOOKUP(C81,'국내평가(ORS)'!P:AO,26,0),10) -> 2025-02-19 | J81: =IF(I81=E81,"O","X") -> X | K81: =VLOOKUP(C81, '국내평가(ORS)'!P:AL, 23, 0) -> [보완3차]협의통보 2025-10-29 | L81: =VLOOKUP(C81, '국내평가(ORS)'!A:AL, 2, 0) -> 인증유효기간 갱신 | M81: 검토필요 | N81: 보완요청 | O81: 사업자 | P81: =IF(AND(H81<>"반려", L81<>"반려"),"검토가능","") | Q81: 반려완료 | R81: 종결 | S81: 46079 | T81: KECM | U81: 외부사업 사업계획서에 대한 정보 비공개 신청을 철회합니다. | V81: X | W81: X | X81: O | Y81: O | Z81: X | AA81: X | AB81: X | AC81: 내부방침
A82: 80 | B82: 단일감축사업 | C82: 광주 두암 주공 4단지 아파트 연료전환을 통한 온실가스 감축사업 | D82: 한국토지주택공사 | E82: =VLOOKUP(C82,'외부사업 비공개승인관리_국내'!$C:$H,4,FALSE) -> 2025-10-15 | F82: =VLOOKUP(C82,'외부사업 비공개승인관리_국내'!$C:$H,5,FALSE) -> 산업통상부 | G82: =VLOOKUP(C82,'외부사업 비공개승인관리_국내'!$C:$H,6,FALSE) -> 2026-02-06 | H82: =VLOOKUP(C82,'외부사업 비공개승인관리_국내'!$C:$H,3,FALSE) -> 반려 | I82: =LEFT(VLOOKUP(C82,'국내평가(ORS)'!P:AO,26,0),10) -> 2025-02-19 | J82: =IF(I82=E82,"O","X") -> X | K82: =VLOOKUP(C82, '국내평가(ORS)'!P:AL, 23, 0) -> [보완4차]협의통보 2025-10-29 | L82: =VLOOKUP(C82, '국내평가(ORS)'!A:AL, 2, 0) -> 인증유효기간 갱신 | M82: 검토필요 | N82: 보완요청 | O82: 사업자 | P82: =IF(AND(H82<>"반려", L82<>"반려"),"검토가능","") | Q82: 반려완료 | R82: 종결 | S82: 46079 | T82: KECM | U82: 외부사업 사업계획서에 대한 정보 비공개 신청을 철회합니다. | V82: X | W82: X | X82: O | Y82: O | Z82: X | AA82: X | AB82: X | AC82: 내부방침
A83: 81 | B83: 단일감축사업 | C83: 광주 두암 주공 2단지 아파트 연료전환을 통한 온실가스 감축사업 | D83: 한국토지주택공사 | E83: =VLOOKUP(C83,'외부사업 비공개승인관리_국내'!$C:$H,4,FALSE) -> 2025-10-15 | F83: =VLOOKUP(C83,'외부사업 비공개승인관리_국내'!$C:$H,5,FALSE) -> 산업통상부 | G83: =VLOOKUP(C83,'외부사업 비공개승인관리_국내'!$C:$H,6,FALSE) -> 2026-02-06 | H83: =VLOOKUP(C83,'외부사업 비공개승인관리_국내'!$C:$H,3,FALSE) -> 반려 | I83: =LEFT(VLOOKUP(C83,'국내평가(ORS)'!P:AO,26,0),10) -> 2025-02-19 | J83: =IF(I83=E83,"O","X") -> X | K83: =VLOOKUP(C83, '국내평가(ORS)'!P:AL, 23, 0) -> [보완3차]협의통보 2025-10-29 | L83: =VLOOKUP(C83, '국내평가(ORS)'!A:AL, 2, 0) -> 인증유효기간 갱신 | M83: 검토필요 | N83: 보완요청 | O83: 사업자 | P83: =IF(AND(H83<>"반려", L83<>"반려"),"검토가능","") | Q83: 반려완료 | R83: 종결 | S83: 46079 | T83: KECM | U83: 외부사업 사업계획서에 대한 정보 비공개 신청을 철회합니다. | V83: X | W83: X | X83: O | Y83: O | Z83: X | AA83: X | AB83: X | AC83: 내부방침
A84: 82 | B84: 단일감축사업 | C84: 광주 각화 주공아파트 연료전환을 통한 온실가스 감축사업 | D84: 한국토지주택공사 | E84: =VLOOKUP(C84,'외부사업 비공개승인관리_국내'!$C:$H,4,FALSE) -> 2025-10-15 | F84: =VLOOKUP(C84,'외부사업 비공개승인관리_국내'!$C:$H,5,FALSE) -> 산업통상부 | G84: =VLOOKUP(C84,'외부사업 비공개승인관리_국내'!$C:$H,6,FALSE) -> 2026-02-06 | H84: =VLOOKUP(C84,'외부사업 비공개승인관리_국내'!$C:$H,3,FALSE) -> 반려 | I84: =LEFT(VLOOKUP(C84,'국내평가(ORS)'!P:AO,26,0),10) -> 2025-02-19 | J84: =IF(I84=E84,"O","X") -> X | K84: =VLOOKUP(C84, '국내평가(ORS)'!P:AL, 23, 0) -> [보완3차]신청 2026-03-11 | L84: =VLOOKUP(C84, '국내평가(ORS)'!A:AL, 2, 0) -> 인증유효기간 갱신 | M84: 검토필요 | N84: 보완요청 | O84: 사업자 | P84: =IF(AND(H84<>"반려", L84<>"반려"),"검토가능","") | Q84: 반려완료 | R84: 종결 | S84: 46079 | T84: KECM | U84: 외부사업 사업계획서에 대한 정보 비공개 신청을 철회합니다. | V84: X | W84: X | X84: O | Y84: O | Z84: X | AA84: X | AB84: X | AC84: 내부방침
A85: 83 | B85: 단일감축사업 | C85: 동해천곡5관리소 온수보일러 연료전환(B-C유->LNG)을 통한 온실가스 배출 감축사업 | D85: 한국토지주택공사 | E85: =VLOOKUP(C85,'외부사업 비공개승인관리_국내'!$C:$H,4,FALSE) -> 2025-10-15 | F85: =VLOOKUP(C85,'외부사업 비공개승인관리_국내'!$C:$H,5,FALSE) -> 산업통상부 | G85: =VLOOKUP(C85,'외부사업 비공개승인관리_국내'!$C:$H,6,FALSE) -> 2026-02-06 | H85: =VLOOKUP(C85,'외부사업 비공개승인관리_국내'!$C:$H,3,FALSE) -> 반려 | I85: =LEFT(VLOOKUP(C85,'국내평가(ORS)'!P:AO,26,0),10) -> 2026-02-13 | J85: =IF(I85=E85,"O","X") -> X | K85: =VLOOKUP(C85, '국내평가(ORS)'!P:AL, 23, 0) -> [보완2차]신청 2026-04-23 | L85: =VLOOKUP(C85, '국내평가(ORS)'!A:AL, 2, 0) -> 인증유효기간 갱신 | M85: 검토필요 | N85: 보완요청 | O85: 사업자 | P85: =IF(AND(H85<>"반려", L85<>"반려"),"검토가능","") | Q85: 반려완료 | R85: 종결 | S85: 46079 | T85: KECM | U85: 외부사업 사업계획서에 대한 정보 비공개 신청을 철회합니다. | V85: X | W85: X | X85: O | Y85: O | Z85: X | AA85: X | AB85: X | AC85: 내부방침
A86: 84 | B86: 단일감축사업 | C86: 석사3관리소 온수보일러 연료전환(B-C유->LNG)을 통한 온실가스 배출 감축사업 | D86: 한국토지주택공사 | E86: =VLOOKUP(C86,'외부사업 비공개승인관리_국내'!$C:$H,4,FALSE) -> 2025-10-15 | F86: =VLOOKUP(C86,'외부사업 비공개승인관리_국내'!$C:$H,5,FALSE) -> 산업통상부 | G86: =VLOOKUP(C86,'외부사업 비공개승인관리_국내'!$C:$H,6,FALSE) -> 2026-02-06 | H86: =VLOOKUP(C86,'외부사업 비공개승인관리_국내'!$C:$H,3,FALSE) -> 반려 | I86: =LEFT(VLOOKUP(C86,'국내평가(ORS)'!P:AO,26,0),10) -> 2026-02-13 | J86: =IF(I86=E86,"O","X") -> X | K86: =VLOOKUP(C86, '국내평가(ORS)'!P:AL, 23, 0) -> [보완2차]신청 2026-04-23 | L86: =VLOOKUP(C86, '국내평가(ORS)'!A:AL, 2, 0) -> 인증유효기간 갱신 | M86: 검토필요 | N86: 보완요청 | O86: 사업자 | P86: =IF(AND(H86<>"반려", L86<>"반려"),"검토가능","") | Q86: 반려완료 | R86: 종결 | S86: 46079 | T86: KECM | U86: 외부사업 사업계획서에 대한 정보 비공개 신청을 철회합니다. | V86: X | W86: X | X86: X | Y86: O | Z86: X | AA86: X | AB86: X | AC86: 내부방침
A87: 85 | B87: 단일감축사업 | C87: 동서발전 당진 소수력 프로젝트 | D87: 한국동서발전 주식회사 | E87: =VLOOKUP(C87,'외부사업 비공개승인관리_국내'!$C:$H,4,FALSE) -> 2018-07-04 | F87: =VLOOKUP(C87,'외부사업 비공개승인관리_국내'!$C:$H,5,FALSE) -> 기후에너지환경부 | G87: =VLOOKUP(C87,'외부사업 비공개승인관리_국내'!$C:$H,6,FALSE) -> 2022-06-02 | H87: =VLOOKUP(C87,'외부사업 비공개승인관리_국내'!$C:$H,3,FALSE) -> 보완요청 | I87: =LEFT(VLOOKUP(C87,'국내평가(ORS)'!P:AO,26,0),10) -> 2017-01-16 | J87: =IF(I87=E87,"O","X") -> X | K87: =VLOOKUP(C87, '국내평가(ORS)'!P:AL, 23, 0) -> [보완1차]착수신고 2017-03-22 | L87: =VLOOKUP(C87, '국내평가(ORS)'!A:AL, 2, 0) -> 승인 | M87: 검토필요 | N87: 보완요청 | O87: 사업자 | P87: =IF(AND(H87<>"반려", L87<>"반려"),"검토가능","") -> 검토가능 | Q87: 보완요청 | R87: 사업자 | S87: 5월 26일 | T87: KECM_이태준 | U87: 사업계획서 내 보안유지 필요부분 구체화 필요(업무상 비밀보호) | V87: X | W87: X | X87: X | Y87: O | Z87: X | AA87: X | AB87: X | AC87: 업체정보보호(업무상 비밀)
A88: 86 | B88: 단일감축사업 | C88: 부일화학의 B-C유에서 LNG로 연료전환을 통한 온실가스 배출 감축사업 | D88: 부일화학(주) | E88: =VLOOKUP(C88,'외부사업 비공개승인관리_국내'!$C:$H,4,FALSE) -> 2017-12-29 | F88: =VLOOKUP(C88,'외부사업 비공개승인관리_국내'!$C:$H,5,FALSE) -> 산업통상부 | G88: =VLOOKUP(C88,'외부사업 비공개승인관리_국내'!$C:$H,6,FALSE) -> 2022-06-02 | H88: =VLOOKUP(C88,'외부사업 비공개승인관리_국내'!$C:$H,3,FALSE) -> 보완요청 | I88: =LEFT(VLOOKUP(C88,'국내평가(ORS)'!P:AO,26,0),10) -> 2017-12-29 | J88: =IF(I88=E88,"O","X") -> O | K88: =VLOOKUP(C88, '국내평가(ORS)'!P:AL, 23, 0) -> [보완1차]착수신고 2020-08-24 | L88: =VLOOKUP(C88, '국내평가(ORS)'!A:AL, 2, 0) -> 승인 | M88: 검토필요 | N88: 보완요청 | O88: 사업자 | P88: =IF(AND(H88<>"반려", L88<>"반려"),"검토가능","") -> 검토가능 | Q88: 보완요청 | R88: 사업자 | S88: 5월 26일 | T88: KECM_이태준 | U88: 사업계획서 내 보안유지 필요부분 구체화 필요(사업 정보 포함) | V88: X | W88: X | X88: O | Y88: O | Z88: X | AA88: X | AB88: X | AC88: 업체정보보호(업무상 비밀) | AD88: 사업명과 상이
A89: 87 | B89: 단일감축사업 | C89: 마니커 동두천지점의 B-C유에서 LNG로 연료전환을 통한 온실가스 배출 감축사업 | D89: (주)마니커 동두천지점 | E89: =VLOOKUP(C89,'외부사업 비공개승인관리_국내'!$C:$H,4,FALSE) -> 2017-12-29 | F89: =VLOOKUP(C89,'외부사업 비공개승인관리_국내'!$C:$H,5,FALSE) -> 산업통상부 | G89: =VLOOKUP(C89,'외부사업 비공개승인관리_국내'!$C:$H,6,FALSE) -> 2022-06-02 | H89: =VLOOKUP(C89,'외부사업 비공개승인관리_국내'!$C:$H,3,FALSE) -> 보완요청 | I89: =LEFT(VLOOKUP(C89,'국내평가(ORS)'!P:AO,26,0),10) -> 2017-12-29 | J89: =IF(I89=E89,"O","X") -> O | K89: =VLOOKUP(C89, '국내평가(ORS)'!P:AL, 23, 0) -> [보완2차]착수신고 2020-09-02 | L89: =VLOOKUP(C89, '국내평가(ORS)'!A:AL, 2, 0) -> 승인 | M89: 검토필요 | N89: 보완요청 | O89: 사업자 | P89: =IF(AND(H89<>"반려", L89<>"반려"),"검토가능","") -> 검토가능 | Q89: 보완요청 | R89: 사업자 | S89: 5월 26일 | T89: KECM_이태준 | U89: 사업계획서 내 보안유지 필요부분 구체화 필요(사업 정보 포함) | V89: X | W89: X | X89: O | Y89: O | Z89: X | AA89: X | AB89: X | AC89: 업체정보보호(업무상 비밀) | AD89: 사업명과 상이
A90: 88 | B90: 묶음감축사업 | C90: 한국 경기도 지역의 천연가스 연료전환 번들링 사업 | D90: (주)영진 | E90: =VLOOKUP(C90,'외부사업 비공개승인관리_국내'!$C:$H,4,FALSE) -> 2017-12-18 | F90: =VLOOKUP(C90,'외부사업 비공개승인관리_국내'!$C:$H,5,FALSE) -> 산업통상부 | G90: =VLOOKUP(C90,'외부사업 비공개승인관리_국내'!$C:$H,6,FALSE) -> 2022-06-02 | H90: =VLOOKUP(C90,'외부사업 비공개승인관리_국내'!$C:$H,3,FALSE) -> 보완요청 | I90: =LEFT(VLOOKUP(C90,'국내평가(ORS)'!P:AO,26,0),10) -> 2017-12-14 | J90: =IF(I90=E90,"O","X") -> X | K90: =VLOOKUP(C90, '국내평가(ORS)'!P:AL, 23, 0) -> [보완1차]착수신고 2019-06-12 | L90: =VLOOKUP(C90, '국내평가(ORS)'!A:AL, 2, 0) -> 승인 | M90: 검토필요 | N90: 보완요청 | O90: 사업자 | P90: =IF(AND(H90<>"반려", L90<>"반려"),"검토가능","") -> 검토가능 | Q90: 보완요청 | R90: 사업자 | S90: 5월 26일 | T90: KECM_이태준 | U90: 사업계획서 내 보안유지 필요부분 구체화 필요(개인 정보 보호) | V90: X | W90: X | X90: O | Y90: O | Z90: O | AA90: X | AB90: X | AC90: 개인정보보호
A91: 89 | B91: 단일감축사업 | C91: 인제군 내린천요양원 태양광 발전설비 설치 및 자가 사용을 통한 온실가스 배출 감축사업 | D91: 인제군청 | E91: =VLOOKUP(C91,'외부사업 비공개승인관리_국내'!$C:$H,4,FALSE) -> 2017-12-14 | F91: =VLOOKUP(C91,'외부사업 비공개승인관리_국내'!$C:$H,5,FALSE) -> 기후에너지환경부 | G91: =VLOOKUP(C91,'외부사업 비공개승인관리_국내'!$C:$H,6,FALSE) -> 2025-02-25 | H91: =VLOOKUP(C91,'외부사업 비공개승인관리_국내'!$C:$H,3,FALSE) -> 반려 | I91: =LEFT(VLOOKUP(C91,'국내평가(ORS)'!P:AO,26,0),10) -> 2017-12-14 | J91: =IF(I91=E91,"O","X") -> O | K91: =VLOOKUP(C91, '국내평가(ORS)'!P:AL, 23, 0) -> 평가반려 2021-06-24 | L91: =VLOOKUP(C91, '국내평가(ORS)'!A:AL, 2, 0) -> 반려 | M91: X | N91: 선택 | O91: 선택 | P91: =IF(AND(H91<>"반려", L91<>"반려"),"검토가능","") | Q91: 선택 | R91: 종결 | S91: 5월 26일
A92: 90 | B92: 단일감축사업 | C92: 인제군 실버홈 태양광 발전설비 설치 및 자가 사용을 통한 온실가스 배출 감축사업 | D92: 인제군청 | E92: =VLOOKUP(C92,'외부사업 비공개승인관리_국내'!$C:$H,4,FALSE) -> 2017-12-14 | F92: =VLOOKUP(C92,'외부사업 비공개승인관리_국내'!$C:$H,5,FALSE) -> 기후에너지환경부 | G92: =VLOOKUP(C92,'외부사업 비공개승인관리_국내'!$C:$H,6,FALSE) -> 2025-02-25 | H92: =VLOOKUP(C92,'외부사업 비공개승인관리_국내'!$C:$H,3,FALSE) -> 반려 | I92: =LEFT(VLOOKUP(C92,'국내평가(ORS)'!P:AO,26,0),10) -> 2017-12-14 | J92: =IF(I92=E92,"O","X") -> O | K92: =VLOOKUP(C92, '국내평가(ORS)'!P:AL, 23, 0) -> 평가반려 2021-06-24 | L92: =VLOOKUP(C92, '국내평가(ORS)'!A:AL, 2, 0) -> 반려 | M92: X | N92: 선택 | O92: 선택 | P92: =IF(AND(H92<>"반려", L92<>"반려"),"검토가능","") | Q92: 선택 | R92: 종결 | S92: 5월 26일
A93: 91 | B93: 단일감축사업 | C93: 인제군 애향원 태양광 발전설비 설치 및 자가 사용을 통한 온실가스 배출 감축사업 | D93: 인제군청 | E93: =VLOOKUP(C93,'외부사업 비공개승인관리_국내'!$C:$H,4,FALSE) -> 2017-12-14 | F93: =VLOOKUP(C93,'외부사업 비공개승인관리_국내'!$C:$H,5,FALSE) -> 기후에너지환경부 | G93: =VLOOKUP(C93,'외부사업 비공개승인관리_국내'!$C:$H,6,FALSE) -> 2025-02-25 | H93: =VLOOKUP(C93,'외부사업 비공개승인관리_국내'!$C:$H,3,FALSE) -> 반려 | I93: =LEFT(VLOOKUP(C93,'국내평가(ORS)'!P:AO,26,0),10) -> 2017-12-14 | J93: =IF(I93=E93,"O","X") -> O | K93: =VLOOKUP(C93, '국내평가(ORS)'!P:AL, 23, 0) -> 평가반려 2021-06-24 | L93: =VLOOKUP(C93, '국내평가(ORS)'!A:AL, 2, 0) -> 반려 | M93: X | N93: 선택 | O93: 선택 | P93: =IF(AND(H93<>"반려", L93<>"반려"),"검토가능","") | Q93: 선택 | R93: 종결 | S93: 5월 26일
A94: 92 | B94: 단일감축사업 | C94: 속초시 목우재터널 고효율 도로조명 교체를 통한 온실가스 배출감축 사업 | D94: 속초시청 | E94: =VLOOKUP(C94,'외부사업 비공개승인관리_국내'!$C:$H,4,FALSE) -> 2017-12-14 | F94: =VLOOKUP(C94,'외부사업 비공개승인관리_국내'!$C:$H,5,FALSE) -> 산업통상부 | G94: =VLOOKUP(C94,'외부사업 비공개승인관리_국내'!$C:$H,6,FALSE) -> 2025-02-25 | H94: =VLOOKUP(C94,'외부사업 비공개승인관리_국내'!$C:$H,3,FALSE) -> 반려 | I94: =LEFT(VLOOKUP(C94,'국내평가(ORS)'!P:AO,26,0),10) -> 2017-12-14 | J94: =IF(I94=E94,"O","X") -> O | K94: =VLOOKUP(C94, '국내평가(ORS)'!P:AL, 23, 0) -> [보완1차]평가반려 2021-06-24 | L94: =VLOOKUP(C94, '국내평가(ORS)'!A:AL, 2, 0) -> 반려 | M94: X | N94: 선택 | O94: 선택 | P94: =IF(AND(H94<>"반려", L94<>"반려"),"검토가능","") | Q94: 선택 | R94: 종결 | S94: 5월 26일
A95: 93 | B95: 단일감축사업 | C95: 태림포장의 B-C유에서 LNG로 연료전환을 통한 온실가스 배출 감축사업 | D95: 태림포장 | E95: =VLOOKUP(C95,'외부사업 비공개승인관리_국내'!$C:$H,4,FALSE) -> 2017-11-03 | F95: =VLOOKUP(C95,'외부사업 비공개승인관리_국내'!$C:$H,5,FALSE) -> 산업통상부 | G95: =VLOOKUP(C95,'외부사업 비공개승인관리_국내'!$C:$H,6,FALSE) -> 2022-06-02 | H95: =VLOOKUP(C95,'외부사업 비공개승인관리_국내'!$C:$H,3,FALSE) -> 보완요청 | I95: =LEFT(VLOOKUP(C95,'국내평가(ORS)'!P:AO,26,0),10) -> 2017-11-03 | J95: =IF(I95=E95,"O","X") -> O | K95: =VLOOKUP(C95, '국내평가(ORS)'!P:AL, 23, 0) -> 심의승인 2022-03-22 | L95: =VLOOKUP(C95, '국내평가(ORS)'!A:AL, 2, 0) -> 승인 | M95: 검토필요 | N95: 보완요청 | O95: 사업자 | P95: =IF(AND(H95<>"반려", L95<>"반려"),"검토가능","") -> 검토가능 | Q95: 보완요청 | R95: 사업자 | S95: 5월 26일 | T95: KECM_이태준 | U95: 사업계획서 내 보안유지 필요부분 구체화 필요(업체 개인 정보) | V95: X | W95: X | X95: X | Y95: O | Z95: O | AA95: X | AB95: X | AC95: 개인정보보호 | AD95: 사업명과 상이
A96: 94 | B96: 묶음감축사업 | C96: 2016년 서울시 건물형 미니발전소 설치 및 자가사용 묶음감축사업 | D96: 서울특별시 | E96: =VLOOKUP(C96,'외부사업 비공개승인관리_국내'!$C:$H,4,FALSE) -> 2017-10-17 | F96: =VLOOKUP(C96,'외부사업 비공개승인관리_국내'!$C:$H,5,FALSE) -> 기후에너지환경부 | G96: =VLOOKUP(C96,'외부사업 비공개승인관리_국내'!$C:$H,6,FALSE) -> 2025-02-25 | H96: =VLOOKUP(C96,'외부사업 비공개승인관리_국내'!$C:$H,3,FALSE) -> 반려 | I96: =LEFT(VLOOKUP(C96,'국내평가(ORS)'!P:AO,26,0),10) -> 2017-10-17 | J96: =IF(I96=E96,"O","X") -> O | K96: =VLOOKUP(C96, '국내평가(ORS)'!P:AL, 23, 0) -> [보완1차]평가반려 2021-06-09 | L96: =VLOOKUP(C96, '국내평가(ORS)'!A:AL, 2, 0) -> 반려 | M96: X | N96: 선택 | O96: 선택 | P96: =IF(AND(H96<>"반려", L96<>"반려"),"검토가능","") | Q96: 선택 | R96: 종결 | S96: 5월 26일
A97: 95 | B97: 프로그램감축사업 | C97: 삼천리 도시가스 공급 권역의 연료전환을 통한 프로그램 감축사업 | D97: (주)삼천리 | E97: =VLOOKUP(C97,'외부사업 비공개승인관리_국내'!$C:$H,4,FALSE) -> 2017-05-26 | F97: =VLOOKUP(C97,'외부사업 비공개승인관리_국내'!$C:$H,5,FALSE) -> 산업통상부 | G97: =VLOOKUP(C97,'외부사업 비공개승인관리_국내'!$C:$H,6,FALSE) -> 2022-06-02 | H97: =VLOOKUP(C97,'외부사업 비공개승인관리_국내'!$C:$H,3,FALSE) -> 보완요청 | I97: =LEFT(VLOOKUP(C97,'국내평가(ORS)'!P:AO,26,0),10) -> 2026-01-29 | J97: =IF(I97=E97,"O","X") -> X | K97: =VLOOKUP(C97, '국내평가(ORS)'!P:AL, 23, 0) -> [보완1차]보완요청 2026-03-19 | L97: =VLOOKUP(C97, '국내평가(ORS)'!A:AL, 2, 0) -> 인증유효기간 갱신 | M97: 검토필요 | N97: 보완요청 | O97: 사업자 | P97: =IF(AND(H97<>"반려", L97<>"반려"),"검토가능","") -> 검토가능 | Q97: 보완요청 | R97: 사업자 | S97: 5월 26일 | T97: KECM_이태준 | U97: 해당 사유로 승인 가능여부 확인 필요(사유: 배출권에 대한 수익 배분 및 기타 세부 내용 비공개 신청) * 사업계획서 : 삼천리, 에코아이 업무 담당 및 배출권 수익 관련 언급되어 있음 | V97: X | W97: X | X97: O | Y97: X | Z97: X | AA97: X | AB97: X | AC97: 기타(배출권 수익 배분) | AD97: 사업명과 상이
A98: 96 | B98: 묶음감축사업 | C98: 2015년 건물형 태양광 미니발전소 설치 및 자가사용 사업 | D98: 서울특별시 | E98: =VLOOKUP(C98,'외부사업 비공개승인관리_국내'!$C:$H,4,FALSE) -> 2017-10-17 | F98: =VLOOKUP(C98,'외부사업 비공개승인관리_국내'!$C:$H,5,FALSE) -> 기후에너지환경부 | G98: =VLOOKUP(C98,'외부사업 비공개승인관리_국내'!$C:$H,6,FALSE) -> 2025-02-25 | H98: =VLOOKUP(C98,'외부사업 비공개승인관리_국내'!$C:$H,3,FALSE) -> 반려 | I98: =LEFT(VLOOKUP(C98,'국내평가(ORS)'!P:AO,26,0),10) -> 2017-10-17 | J98: =IF(I98=E98,"O","X") -> O | K98: =VLOOKUP(C98, '국내평가(ORS)'!P:AL, 23, 0) -> [보완1차]평가반려 2021-06-07 | L98: =VLOOKUP(C98, '국내평가(ORS)'!A:AL, 2, 0) -> 반려 | M98: X | N98: 선택 | O98: 선택 | P98: =IF(AND(H98<>"반려", L98<>"반려"),"검토가능","") | Q98: 선택 | R98: 종결 | S98: 5월 26일
A99: 97 | B99: 단일감축사업 | C99: 황산공정 미활용 폐열 회수 및 공급을 통한 화석연료 사용 절감 및 온실가스 배출 감축사업 | D99: 엘에스니꼬 동제련 주식회사 | E99: =VLOOKUP(C99,'외부사업 비공개승인관리_국내'!$C:$H,4,FALSE) -> 2017-09-20 | F99: =VLOOKUP(C99,'외부사업 비공개승인관리_국내'!$C:$H,5,FALSE) -> 산업통상부 | G99: =VLOOKUP(C99,'외부사업 비공개승인관리_국내'!$C:$H,6,FALSE) -> 2022-06-02 | H99: =VLOOKUP(C99,'외부사업 비공개승인관리_국내'!$C:$H,3,FALSE) -> 보완요청 | I99: =LEFT(VLOOKUP(C99,'국내평가(ORS)'!P:AO,26,0),10) -> 2020-02-27 | J99: =IF(I99=E99,"O","X") -> X | K99: =VLOOKUP(C99, '국내평가(ORS)'!P:AL, 23, 0) -> 심의승인 2021-06-30 | L99: =VLOOKUP(C99, '국내평가(ORS)'!A:AL, 2, 0) -> 인증유효기간 갱신 | M99: 검토필요 | N99: 보완요청 | O99: 사업자 | P99: =IF(AND(H99<>"반려", L99<>"반려"),"검토가능","") -> 검토가능 | Q99: 보완요청 | R99: 사업자 | S99: 5월 26일 | T99: KECM_이태준 | U99: 사업계획서 내 보안유지 필요부분 구체화 필요(고객사 영업 비밀) | V99: X | W99: X | X99: X | Y99: O | Z99: O | AA99: X | AB99: X | AC99: 업체정보보호(업무상 비밀)
A100: 98 | B100: 단일감축사업 | C100: 영미산업(주) 보일러 연료 BC유 및 부생연료1호를 LNG로의 전환을 통한 온실가스 감축사업 | D100: 영미산업(주) | E100: =VLOOKUP(C100,'외부사업 비공개승인관리_국내'!$C:$H,4,FALSE) -> 2017-07-19 | F100: =VLOOKUP(C100,'외부사업 비공개승인관리_국내'!$C:$H,5,FALSE) -> 산업통상부 | G100: =VLOOKUP(C100,'외부사업 비공개승인관리_국내'!$C:$H,6,FALSE) -> 2022-06-02 | H100: =VLOOKUP(C100,'외부사업 비공개승인관리_국내'!$C:$H,3,FALSE) -> 보완요청 | I100: =LEFT(VLOOKUP(C100,'국내평가(ORS)'!P:AO,26,0),10) -> 2017-07-19 | J100: =IF(I100=E100,"O","X") -> O | K100: =VLOOKUP(C100, '국내평가(ORS)'!P:AL, 23, 0) -> [보완3차]심의승인 2021-09-27 | L100: =VLOOKUP(C100, '국내평가(ORS)'!A:AL, 2, 0) -> 승인 | M100: 검토필요 | N100: 보완요청 | O100: 사업자 | P100: =IF(AND(H100<>"반려", L100<>"반려"),"검토가능","") -> 검토가능 | Q100: 보완요청 | R100: 사업자 | S100: 5월 26일 | T100: KECM_이태준 | U100: 사업계획서 내 보안유지 필요부분 구체화 필요(보안이 필요한 생산시설 배치도와 기타 생산설비 사진 등이 다수 삽입) * 사업계획서 내 식용유 생산공정 시설배치도 기재 | V100: X | W100: X | X100: X | Y100: O | Z100: O | AA100: X | AB100: - | AC100: 업체정보보호(업무상 비밀) | AD100: 사업명과 상이
...

Sheet (비공개)국내인증
F1: 정보비공개 DB | L1: 국내인증 DB(참고용)
A2: 검증 | B2: 번호 | C2: 사업유형 | D2: 사업명 | E2: 업체명 | F2: 유효기간 | G2: 모니터링차수 | H2: 정보비공개 신청일 | I2: 관장기관 | J2: 처리일 | K2: 진행상태 | L2: 차수 | M2: 모니터링 기간 시작일 | N2: 사업 신청일 | O2: 평가 가능 여부 | P2: 검토대상 | Q2: 진행상태 | R2: 현 위치 | S2: 진행상태 | T2: 현 위치 | U2: 업데이트 | V2: 담당자 | W2: 비고 | X2: 권리 | Y2: 대외비 자료 | Z2: 계약서류 | AA2: 연료 사용량 | AB2: 공정 도식도 | AC2: 영업비밀 | AD2: 내규방침 제출여부 | AE2: 비공개 신청사유 | AF2: 특이사항
A3: =D3&L3&M3 -> 원주시 보안등 LED교체 ESCO용역사업1차2016-10-31 | B3: 1 | C3: 단일감축사업 | D3: 원주시 보안등 LED교체 ESCO용역사업 | E3: 원주시 | F3: =VLOOKUP(D3,'인증실적 비공개승인관리_국내'!$D:$K,3,FALSE) -> 2016-10-31~2023-10-30 | G3: =VLOOKUP(D3,'인증실적 비공개승인관리_국내'!$D:$K,4,FALSE) -> 1차 (2016-10-31~2016-10-31) | H3: =VLOOKUP(D3,'인증실적 비공개승인관리_국내'!$D:$K,6,FALSE) -> 2026-05-20 | I3: =VLOOKUP(D3,'인증실적 비공개승인관리_국내'!$D:$K,7,FALSE) -> 산업통상부 | J3: =VLOOKUP(D3,'인증실적 비공개승인관리_국내'!$D:$K,8,FALSE) -> 2026-05-22 | K3: =VLOOKUP(A3,'인증실적 비공개승인관리_국내'!$A:$N,8,FALSE) -> 보완요청 | L3: =LEFT(G3,FIND("차",G3)) -> 1차 | M3: =MID(G3,FINDB("(",G3),10) -> 2016-10-31 | N3: =LEFT(VLOOKUP(D3,'국내인증(ORS)'!O:BI,38,0),10) -> 2024-10-30 | O3: =IF(N3=#REF!,"O","X") -> #REF! | P3: 승인 전 | Q3: 선택 | R3: 선택 | S3: 보완요청 | T3: 사업자 | U3: 45992 | V3: 에코시안_남혜원 | W3: <신청사유> 본 외부사업의 사업계획서 상 비공개를 희망하는 부분 및 그 사유를 다음과 같이 기술함. 1.2. 사업의 위치 (1) 사업의 주소, 보안등 관리번호 - 이 사업의 대상인 도로조명의 주소, 등번호는 중요한 정보이며, 그 목록 전체를 원 주시가 일반에게 공개할 의무는 없으며, 오남용될 가능성도 있어 원주시는 이 정보의 공개를 원하지 않음 [근거: 공공기관의 정보공개에 관한 법률 제9조제1항제5호] 4. 모니터링 데이터 및 지표 - 본 외부사업의 베이스라인 및 모니터링 방법 등이 원주시 고유의 특성을 반영하여 구체적으로 기술되어 있기 때문에 정보공개를 원하지 않음. 또한, 이 보고서를 작성하기 위하여 원주시가 오랜 기간 동안 시간과 노력과 예산을 투자하여 작성한 영구성과물이기 때문에 무상으로 이를 일반인에게 공개하는 것은 공평하지 못하며, 시장질서에도 바람직하지 않다고 사료되므로 원주시는 비공개를 요청함 [근거: 공공기관의 정보공개에 관한 법률 제9조제1항제5호,제7호] <1차 통보> ∙ 「명세서 공개 심사위원회 구성 및 운영에 관한 규정」 [별표1]에 따라 비공개 신청사유를 하기와 같이 보완 요청 드립니다. - 모니터링보고서, 검증 보고서 내용 중 보안유지 필요 부분, 위치(page) 및 사유 구체화(증빙자료는 정보공개 대상 아님) - 필요 시 정보 비공개사유에 대한 증빙자료 제출 요청 ∙ 단, 투명성 원칙에 따라 민감사항이 모니터링보고서, 검증 보고서 내 문서에 포함되지 않아도 되는 경우(필수 작성 항목이 아닌 경우) 해당 사항은 증빙자료로만 제출하고 본 비공개 신청건은 철회 신청해주시기 바랍니다. | AE3: 업체정보보호(내부 정보)
A4: =D4&L4&M4 -> 2015년 춘천시 도로조명 LED 교체를 통한 묶음 감축사업1차2015-10-30 | B4: 2 | C4: 묶음감축사업 | D4: 2015년 춘천시 도로조명 LED 교체를 통한 묶음 감축사업 | E4: 춘천시 | F4: 2015-10-30~2025-10-29 | G4: 1차 (2015-10-30~2015-10-30) | H4: =VLOOKUP(D4,'인증실적 비공개승인관리_국내'!$D:$K,6,FALSE) -> 2024-08-26 | I4: =VLOOKUP(D4,'인증실적 비공개승인관리_국내'!$D:$K,7,FALSE) -> 산업통상부 | J4: =VLOOKUP(D4,'인증실적 비공개승인관리_국내'!$D:$K,8,FALSE) -> 2025-06-12 | K4: =VLOOKUP(A4,'인증실적 비공개승인관리_국내'!$A:$N,8,FALSE) -> 심의완료 | L4: =LEFT(G4,FIND("차",G4)) -> 1차 | M4: =MID(G4,FINDB("(",G4),10) -> 2015-10-30 | N4: =LEFT(VLOOKUP(D4,'국내인증(ORS)'!O:BI,38,0),10) -> 2023-01-11 | O4: =IF(N4=#REF!,"O","X") -> #REF! | P4: 승인 전 | Q4: 선택 | R4: 선택 | S4: 심의승인 | T4: 종결 | U4: 45833 | V4: 에코시안_조영우 | W4: 심의 승인
A5: =D5&L5&M5 -> 에이스침대 중부공장의 B-C유에서 도시가스(LNG)로 연료전환을 통한 온실가스 배출 감축사업1차2010-10-11 | B5: 3 | C5: 단일감축사업 | D5: 에이스침대 중부공장의 B-C유에서 도시가스(LNG)로 연료전환을 통한 온실가스 배출 감축사업 | E5: (주)에이스침대중부공장 | F5: 2010-10-11~2020-10-10 | G5: 1차 (2010-10-11~2010-10-11) | H5: =VLOOKUP(D5,'인증실적 비공개승인관리_국내'!$D:$K,6,FALSE) -> 2024-07-17 | I5: =VLOOKUP(D5,'인증실적 비공개승인관리_국내'!$D:$K,7,FALSE) -> 산업통상부 | J5: =VLOOKUP(D5,'인증실적 비공개승인관리_국내'!$D:$K,8,FALSE) -> 2024-09-19 | K5: =VLOOKUP(A5,'인증실적 비공개승인관리_국내'!$A:$N,8,FALSE) -> 심의완료 | L5: =LEFT(G5,FIND("차",G5)) -> 1차 | M5: =MID(G5,FINDB("(",G5),10) -> 2010-10-11 | N5: =LEFT(VLOOKUP(D5,'국내인증(ORS)'!O:BI,38,0),10) -> 2024-01-12 | O5: =IF(N5=#REF!,"O","X") -> #REF! | Q5: 심의승인 | R5: 종결 | S5: 심의승인 | T5: 종결 | U5: 45567 | V5: 에코시안_조은지 | AF5: 검토 기준 변경 전 승인 사업
A6: =D6&L6&M6 -> 카프로 N2O 저감 사업10차2021-01-01 | B6: 4 | C6: 단일감축사업 | D6: 카프로 N2O 저감 사업 | E6: 주식회사 카프로 | F6: 2011-06-09~2021-06-08 | G6: 10차 (2021-01-01~2021-01-01) | H6: =VLOOKUP(D6,'인증실적 비공개승인관리_국내'!$D:$K,6,FALSE) -> 2024-01-24 | I6: =VLOOKUP(D6,'인증실적 비공개승인관리_국내'!$D:$K,7,FALSE) -> 산업통상부 | J6: =VLOOKUP(D6,'인증실적 비공개승인관리_국내'!$D:$K,8,FALSE) -> 2024-06-17 | K6: =VLOOKUP(A6,'인증실적 비공개승인관리_국내'!$A:$N,8,FALSE) -> 보완요청 | L6: =LEFT(G6,FIND("차",G6)) -> 10차 | M6: =MID(G6,FINDB("(",G6),10) -> 2021-01-01 | N6: =LEFT(VLOOKUP(D6,'국내인증(ORS)'!O:BI,38,0),10) -> 2022-05-31 | O6: =IF(N6=#REF!,"O","X") -> #REF! | P6: 검토필요 | Q6: 보완요청 | R6: 사업자 | S6: 보완요청 | T6: 사업자 | U6: 45457 | V6: 에코시안_조영우 | W6: 모니터링보고서 및 검증보고서 내 비공개 필요 부분 정확히 명시 필요(모니터링보고서 증빙자료는 정보공개 대상 아님) | AE6: 업체정보보호(업무상 비밀)
A7: =D7&L7&M7 -> 덕성 인천사업장의 B-A유 및 B-C유에서 LNG로 연료전환을 통한 온실가스 배출 감축사업2차2020-11-01 | B7: 5 | C7: 단일감축사업 | D7: 덕성 인천사업장의 B-A유 및 B-C유에서 LNG로 연료전환을 통한 온실가스 배출 감축사업 | E7: (주)덕성 | F7: 2012-12-19~2022-12-18 | G7: 2차 (2020-11-01~2020-11-01) | H7: =VLOOKUP(D7,'인증실적 비공개승인관리_국내'!$D:$K,6,FALSE) -> 2023-11-24 | I7: =VLOOKUP(D7,'인증실적 비공개승인관리_국내'!$D:$K,7,FALSE) -> 산업통상부 | J7: =VLOOKUP(D7,'인증실적 비공개승인관리_국내'!$D:$K,8,FALSE) -> 2024-06-17 | K7: =VLOOKUP(A7,'인증실적 비공개승인관리_국내'!$A:$N,8,FALSE) -> 보완요청 | L7: =LEFT(G7,FIND("차",G7)) -> 2차 | M7: =MID(G7,FINDB("(",G7),10) -> 2020-11-01 | N7: =LEFT(VLOOKUP(D7,'국내인증(ORS)'!O:BI,38,0),10) -> 2023-09-25 | O7: =IF(N7=#REF!,"O","X") -> #REF! | P7: 검토필요 | Q7: 보완요청 | R7: 사업자 | S7: 보완요청 | T7: 사업자 | U7: 45457 | V7: 에코시안_조영우 | W7: 모니터링보고서 및 검증보고서 내 비공개 필요 부분 정확히 명시 필요(모니터링보고서 증빙자료는 정보공개 대상 아님) | AE7: 업체정보보호(업무상 비밀)
A8: =D8&L8&M8 -> 카프로 N2O 저감 사업11차2021-01-01 | B8: 6 | C8: 단일감축사업 | D8: 카프로 N2O 저감 사업 | E8: 주식회사 카프로 | F8: 2011-06-09~2021-06-08 | G8: 11차 (2021-01-01~2021-01-01) | H8: =VLOOKUP(D8,'인증실적 비공개승인관리_국내'!$D:$K,6,FALSE) -> 2024-01-24 | I8: =VLOOKUP(D8,'인증실적 비공개승인관리_국내'!$D:$K,7,FALSE) -> 산업통상부 | J8: =VLOOKUP(D8,'인증실적 비공개승인관리_국내'!$D:$K,8,FALSE) -> 2024-06-17 | K8: =VLOOKUP(A8,'인증실적 비공개승인관리_국내'!$A:$N,8,FALSE) -> 반려 | L8: =LEFT(G8,FIND("차",G8)) -> 11차 | M8: =MID(G8,FINDB("(",G8),10) -> 2021-01-01 | N8: =LEFT(VLOOKUP(D8,'국내인증(ORS)'!O:BI,38,0),10) -> 2022-05-31 | O8: =IF(N8=#REF!,"O","X") -> #REF! | P8: X | Q8: 선택 | R8: 선택 | S8: 선택 | T8: 종결 | U8: 45769 | W8: 반려 완료, 외부사업이 평가/인증 단계에서 반려
A9: =D9&L9&M9 -> 에이스침대 여주공장의 B-C유에서 도시가스(LNG)로 연료전환을 통한 온실가스 배출 감축사업1차2010-11-22 | B9: 7 | C9: 단일감축사업 | D9: 에이스침대 여주공장의 B-C유에서 도시가스(LNG)로 연료전환을 통한 온실가스 배출 감축사업 | E9: (주)에이스침대중부공장 | F9: 2010-11-22~2020-11-21 | G9: 1차 (2010-11-22~2010-11-22) | H9: =VLOOKUP(D9,'인증실적 비공개승인관리_국내'!$D:$K,6,FALSE) -> 2022-11-30 | I9: =VLOOKUP(D9,'인증실적 비공개승인관리_국내'!$D:$K,7,FALSE) -> 산업통상부 | J9: =VLOOKUP(D9,'인증실적 비공개승인관리_국내'!$D:$K,8,FALSE) -> 2023-06-19 | K9: =VLOOKUP(A9,'인증실적 비공개승인관리_국내'!$A:$N,8,FALSE) -> 보완요청 | L9: =LEFT(G9,FIND("차",G9)) -> 1차 | M9: =MID(G9,FINDB("(",G9),10) -> 2010-11-22 | N9: =LEFT(VLOOKUP(D9,'국내인증(ORS)'!O:BI,38,0),10) -> 2022-11-30 | O9: =IF(N9=#REF!,"O","X") -> #REF! | P9: 검토필요 | Q9: 보완요청 | R9: 사업자 | S9: 보완요청 | T9: 사업자 | U9: 45096 | V9: 에코시안_조영우 | W9: 모니터링보고서 및 검증보고서 내 보안유지 필요부분 구체화 필요 | AE9: 업체정보보호(업무상 비밀)
A10: =D10&L10&M10 -> 에스오엠의 정제유에서 도시가스(LNG)로 연료전환을 통한 온실가스 배출 감축사업1차2011-01-22 | B10: 8 | C10: 단일감축사업 | D10: 에스오엠의 정제유에서 도시가스(LNG)로 연료전환을 통한 온실가스 배출 감축사업 | E10: 에스오엠 | F10: 2011-01-22~2021-01-21 | G10: 1차 (2011-01-22~2011-01-22) | H10: =VLOOKUP(D10,'인증실적 비공개승인관리_국내'!$D:$K,6,FALSE) -> 2022-11-25 | I10: =VLOOKUP(D10,'인증실적 비공개승인관리_국내'!$D:$K,7,FALSE) -> 산업통상부 | J10: =VLOOKUP(D10,'인증실적 비공개승인관리_국내'!$D:$K,8,FALSE) -> 2024-06-17 | K10: =VLOOKUP(A10,'인증실적 비공개승인관리_국내'!$A:$N,8,FALSE) -> 보완요청 | L10: =LEFT(G10,FIND("차",G10)) -> 1차 | M10: =MID(G10,FINDB("(",G10),10) -> 2011-01-22 | N10: =LEFT(VLOOKUP(D10,'국내인증(ORS)'!O:BI,38,0),10) -> 2022-10-20 | O10: =IF(N10=#REF!,"O","X") -> #REF! | P10: 검토필요 | Q10: 보완요청 | R10: 사업자 | S10: 보완요청 | T10: 사업자 | U10: 45457 | V10: 에코시안_조영우 | W10: 모니터링보고서 및 검증보고서 내 비공개 필요 부분 정확히 명시 필요(모니터링보고서 증빙자료는 정보공개 대상 아님) | AE10: 내부방침
A11: =D11&L11&M11 -> 삼일이노팩의 B-C유에서 LNG로 연료전환을 통한 온실가스 배출 감축사업2차2020-07-01 | B11: 9 | C11: 단일감축사업 | D11: 삼일이노팩의 B-C유에서 LNG로 연료전환을 통한 온실가스 배출 감축사업 | E11: 주식회사 삼일이노팩 | F11: 2012-10-04~2022-10-03 | G11: 2차 (2020-07-01~2020-07-01) | H11: =VLOOKUP(D11,'인증실적 비공개승인관리_국내'!$D:$K,6,FALSE) -> 2022-11-15 | I11: =VLOOKUP(D11,'인증실적 비공개승인관리_국내'!$D:$K,7,FALSE) -> 산업통상부 | J11: =VLOOKUP(D11,'인증실적 비공개승인관리_국내'!$D:$K,8,FALSE) -> 2024-06-17 | K11: =VLOOKUP(A11,'인증실적 비공개승인관리_국내'!$A:$N,8,FALSE) -> 보완요청 | L11: =LEFT(G11,FIND("차",G11)) -> 2차 | M11: =MID(G11,FINDB("(",G11),10) -> 2020-07-01 | N11: =LEFT(VLOOKUP(D11,'국내인증(ORS)'!O:BI,38,0),10) -> 2022-11-15 | O11: =IF(N11=#REF!,"O","X") -> #REF! | P11: 검토필요 | Q11: 보완요청 | R11: 사업자 | S11: 보완요청 | T11: 사업자 | U11: 45457 | V11: 에코시안_조영우 | W11: 모니터링보고서 및 검증보고서 내 비공개 필요 부분 정확히 명시 필요(모니터링보고서 증빙자료는 정보공개 대상 아님) | AE11: 업체정보보호(업무상 비밀)
A12: =D12&L12&M12 -> 남부산업의 이온정제유에서 LNG로 연료전환을 통한 온실가스 배출 감축사업1차2015-03-01 | B12: 10 | C12: 단일감축사업 | D12: 남부산업의 이온정제유에서 LNG로 연료전환을 통한 온실가스 배출 감축사업 | E12: 남부산업[주] | F12: 2013-01-29~2023-01-28 | G12: 1차 (2015-03-01~2015-03-01) | H12: =VLOOKUP(D12,'인증실적 비공개승인관리_국내'!$D:$K,6,FALSE) -> 2022-07-20 | I12: =VLOOKUP(D12,'인증실적 비공개승인관리_국내'!$D:$K,7,FALSE) -> 산업통상부 | J12: =VLOOKUP(D12,'인증실적 비공개승인관리_국내'!$D:$K,8,FALSE) -> 2022-10-19 | K12: =VLOOKUP(A12,'인증실적 비공개승인관리_국내'!$A:$N,8,FALSE) -> 보완요청 | L12: =LEFT(G12,FIND("차",G12)) -> 1차 | M12: =MID(G12,FINDB("(",G12),10) -> 2015-03-01 | N12: =LEFT(VLOOKUP(D12,'국내인증(ORS)'!O:BI,38,0),10) -> 2021-09-29 | O12: =IF(N12=#REF!,"O","X") -> #REF! | P12: 검토필요 | Q12: 보완요청 | R12: 사업자 | S12: 보완요청 | T12: 사업자 | U12: 10월 13일 | V12: 에코시안 | W12: 모니터링보고서 및 검증보고서 내 보안유지 필요부분 구체화 필요 | AE12: 내부방침
A13: =D13&L13&M13 -> 동신산업 평택공장의 B-C유에서 LNG로 연료전환을 통한 온실가스 배출 감축사업1차2010-05-21 | B13: 11 | C13: 단일감축사업 | D13: 동신산업 평택공장의 B-C유에서 LNG로 연료전환을 통한 온실가스 배출 감축사업 | E13: 동신산업(주) | F13: 2008-07-30~2018-07-29 | G13: 1차 (2010-05-21~2010-05-21) | H13: =VLOOKUP(D13,'인증실적 비공개승인관리_국내'!$D:$K,6,FALSE) -> 2022-07-20 | I13: =VLOOKUP(D13,'인증실적 비공개승인관리_국내'!$D:$K,7,FALSE) -> 산업통상부 | J13: =VLOOKUP(D13,'인증실적 비공개승인관리_국내'!$D:$K,8,FALSE) -> 2022-10-19 | K13: =VLOOKUP(A13,'인증실적 비공개승인관리_국내'!$A:$N,8,FALSE) -> 보완요청 | L13: =LEFT(G13,FIND("차",G13)) -> 1차 | M13: =MID(G13,FINDB("(",G13),10) -> 2010-05-21 | N13: =LEFT(VLOOKUP(D13,'국내인증(ORS)'!O:BI,38,0),10) -> 2021-09-28 | O13: =IF(N13=#REF!,"O","X") -> #REF! | P13: 검토필요 | Q13: 보완요청 | R13: 사업자 | S13: 보완요청 | T13: 사업자 | U13: 10월 13일 | V13: 에코시안 | W13: 모니터링보고서 및 검증보고서 내 보안유지 필요부분 구체화 필요 | AE13: 내부방침
A14: =D14&L14&M14 -> 부천수지의 B-C유에서 도시가스(LNG)로 연료전환을 통한 온실가스 배출 감축사업1차2011-08-08 | B14: 12 | C14: 단일감축사업 | D14: 부천수지의 B-C유에서 도시가스(LNG)로 연료전환을 통한 온실가스 배출 감축사업 | E14: (주)부천수지 | F14: 2011-08-08~2021-08-07 | G14: 1차 (2011-08-08~2011-08-08) | H14: =VLOOKUP(D14,'인증실적 비공개승인관리_국내'!$D:$K,6,FALSE) -> 2022-06-10 | I14: =VLOOKUP(D14,'인증실적 비공개승인관리_국내'!$D:$K,7,FALSE) -> 산업통상부 | J14: =VLOOKUP(D14,'인증실적 비공개승인관리_국내'!$D:$K,8,FALSE) -> 2023-04-25 | K14: =VLOOKUP(A14,'인증실적 비공개승인관리_국내'!$A:$N,8,FALSE) -> 보완요청 | L14: =LEFT(G14,FIND("차",G14)) -> 1차 | M14: =MID(G14,FINDB("(",G14),10) -> 2011-08-08 | N14: =LEFT(VLOOKUP(D14,'국내인증(ORS)'!O:BI,38,0),10) -> 2022-06-10 | O14: =IF(N14=#REF!,"O","X") -> #REF! | P14: 검토필요 | Q14: 보완요청 | R14: 사업자 | S14: 보완요청 | T14: 사업자 | U14: 45012 | V14: 에코시안_조영우 | W14: 모니터링보고서 내용 중 비공개 필요 부분 정확히 명시 필요(모니터링보고서 증빙자료는 정보공개 대상 아님) | AE14: 내부방침
A15: =D15&L15&M15 -> 태림포장의 B-C유에서 LNG로 연료전환을 통한 온실가스 배출 감축사업1차2010-05-02 | B15: 13 | C15: 단일감축사업 | D15: 태림포장의 B-C유에서 LNG로 연료전환을 통한 온실가스 배출 감축사업 | E15: 태림포장(주) | F15: 2008-07-14~2018-07-13 | G15: 1차 (2010-05-02~2010-05-02) | H15: =VLOOKUP(D15,'인증실적 비공개승인관리_국내'!$D:$K,6,FALSE) -> 2022-06-10 | I15: =VLOOKUP(D15,'인증실적 비공개승인관리_국내'!$D:$K,7,FALSE) -> 산업통상부 | J15: =VLOOKUP(D15,'인증실적 비공개승인관리_국내'!$D:$K,8,FALSE) -> 2023-04-25 | K15: =VLOOKUP(A15,'인증실적 비공개승인관리_국내'!$A:$N,8,FALSE) -> 보완요청 | L15: =LEFT(G15,FIND("차",G15)) -> 1차 | M15: =MID(G15,FINDB("(",G15),10) -> 2010-05-02 | N15: =LEFT(VLOOKUP(D15,'국내인증(ORS)'!O:BI,38,0),10) -> 2022-06-10 | O15: =IF(N15=#REF!,"O","X") -> #REF! | P15: 검토필요 | Q15: 보완요청 | R15: 사업자 | S15: 보완요청 | T15: 사업자 | U15: 45012 | V15: 에코시안_조영우 | W15: 모니터링보고서 내용 중 비공개 필요 부분 정확히 명시 필요(모니터링보고서 증빙자료는 정보공개 대상 아님) | AE15: 내부방침
A16: =D16&L16&M16 -> (주)덕산의 신재 및 재생 드라이어의 B-C유에서 도시가스(LNG)로 연료전환을 통한 온실가스 배출 감축사업1차2020-01-22 | B16: 14 | C16: 단일감축사업 | D16: (주)덕산의 신재 및 재생 드라이어의 B-C유에서 도시가스(LNG)로 연료전환을 통한 온실가스 배출 감축사업 | E16: (주) 덕 산 | F16: 2020-01-22~2030-01-21 | G16: 1차 (2020-01-22~2020-01-22) | H16: =VLOOKUP(D16,'인증실적 비공개승인관리_국내'!$D:$K,6,FALSE) -> 2022-05-30 | I16: =VLOOKUP(D16,'인증실적 비공개승인관리_국내'!$D:$K,7,FALSE) -> 산업통상부 | J16: =VLOOKUP(D16,'인증실적 비공개승인관리_국내'!$D:$K,8,FALSE) -> 2023-04-25 | K16: =VLOOKUP(A16,'인증실적 비공개승인관리_국내'!$A:$N,8,FALSE) -> 보완요청 | L16: =LEFT(G16,FIND("차",G16)) -> 1차 | M16: =MID(G16,FINDB("(",G16),10) -> 2020-01-22 | N16: =LEFT(VLOOKUP(D16,'국내인증(ORS)'!O:BI,38,0),10) -> 2022-05-30 | O16: =IF(N16=#REF!,"O","X") -> #REF! | P16: 검토필요 | Q16: 보완요청 | R16: 사업자 | S16: 보완요청 | T16: 사업자 | U16: 45012 | V16: 에코시안_조영우 | W16: 모니터링보고서 내용 중 비공개 필요 부분 정확히 명시 필요(모니터링보고서 증빙자료는 정보공개 대상 아님) | AE16: 내부방침
A17: =D17&L17&M17 -> 대평산업개발의 정제유 및 B-C유에서 도시가스(LNG)로의 연료전환을 통한 온실가스 배출 감축사업1차2019-02-01 | B17: 15 | C17: 단일감축사업 | D17: 대평산업개발의 정제유 및 B-C유에서 도시가스(LNG)로의 연료전환을 통한 온실가스 배출 감축사업 | E17: (주)대평산업개발 | F17: 2019-02-01~2026-01-31 | G17: 1차 (2019-02-01~2019-02-01) | H17: =VLOOKUP(D17,'인증실적 비공개승인관리_국내'!$D:$K,6,FALSE) -> 2022-05-16 | I17: =VLOOKUP(D17,'인증실적 비공개승인관리_국내'!$D:$K,7,FALSE) -> 산업통상부 | J17: =VLOOKUP(D17,'인증실적 비공개승인관리_국내'!$D:$K,8,FALSE) -> 2023-04-25 | K17: =VLOOKUP(A17,'인증실적 비공개승인관리_국내'!$A:$N,8,FALSE) -> 보완요청 | L17: =LEFT(G17,FIND("차",G17)) -> 1차 | M17: =MID(G17,FINDB("(",G17),10) -> 2019-02-01 | N17: =LEFT(VLOOKUP(D17,'국내인증(ORS)'!O:BI,38,0),10) -> 2022-05-16 | O17: =IF(N17=#REF!,"O","X") -> #REF! | P17: 검토필요 | Q17: 보완요청 | R17: 사업자 | S17: 보완요청 | T17: 사업자 | U17: 45012 | V17: 에코시안_조영우 | W17: 모니터링보고서 내용 중 비공개 필요 부분 정확히 명시 필요(모니터링보고서 증빙자료는 정보공개 대상 아님) | AE17: 내부방침
A18: =D18&L18&M18 -> 덕산지에스의 부생연료유 2호에서 도시가스(LNG)로의 연료전환을 통한 온실가스 배출 감축사업1차2018-12-17 | B18: 16 | C18: 단일감축사업 | D18: 덕산지에스의 부생연료유 2호에서 도시가스(LNG)로의 연료전환을 통한 온실가스 배출 감축사업 | E18: (주)덕산지에스 | F18: 2018-12-17~2028-12-16 | G18: 1차 (2018-12-17~2018-12-17) | H18: =VLOOKUP(D18,'인증실적 비공개승인관리_국내'!$D:$K,6,FALSE) -> 2022-05-16 | I18: =VLOOKUP(D18,'인증실적 비공개승인관리_국내'!$D:$K,7,FALSE) -> 산업통상부 | J18: =VLOOKUP(D18,'인증실적 비공개승인관리_국내'!$D:$K,8,FALSE) -> 2023-04-25 | K18: =VLOOKUP(A18,'인증실적 비공개승인관리_국내'!$A:$N,8,FALSE) -> 보완요청 | L18: =LEFT(G18,FIND("차",G18)) -> 1차 | M18: =MID(G18,FINDB("(",G18),10) -> 2018-12-17 | N18: =LEFT(VLOOKUP(D18,'국내인증(ORS)'!O:BI,38,0),10) -> 2022-05-16 | O18: =IF(N18=#REF!,"O","X") -> #REF! | P18: 검토필요 | Q18: 보완요청 | R18: 사업자 | S18: 보완요청 | T18: 사업자 | U18: 45012 | V18: 에코시안_조영우 | W18: 모니터링보고서 내용 중 비공개 필요 부분 정확히 명시 필요(모니터링보고서 증빙자료는 정보공개 대상 아님) | AE18: 내부방침
A19: =D19&L19&M19 -> 이연제약 진천공장의 B-C유에서 LNG로의 연료전환을 통한 온실가스 배출 감축사업1차2013-12-11 | B19: 17 | C19: 단일감축사업 | D19: 이연제약 진천공장의 B-C유에서 LNG로의 연료전환을 통한 온실가스 배출 감축사업 | E19: 이연제약(주) | F19: 2013-12-11~2023-12-10 | G19: 1차 (2013-12-11~2013-12-11) | H19: =VLOOKUP(D19,'인증실적 비공개승인관리_국내'!$D:$K,6,FALSE) -> 2022-02-15 | I19: =VLOOKUP(D19,'인증실적 비공개승인관리_국내'!$D:$K,7,FALSE) -> 산업통상부 | J19: =VLOOKUP(D19,'인증실적 비공개승인관리_국내'!$D:$K,8,FALSE) -> 2022-10-19 | K19: =VLOOKUP(A19,'인증실적 비공개승인관리_국내'!$A:$N,8,FALSE) -> 보완요청 | L19: =LEFT(G19,FIND("차",G19)) -> 1차 | M19: =MID(G19,FINDB("(",G19),10) -> 2013-12-11 | N19: =LEFT(VLOOKUP(D19,'국내인증(ORS)'!O:BI,38,0),10) -> 2024-09-06 | O19: =IF(N19=#REF!,"O","X") -> #REF! | P19: 검토필요 | Q19: 보완요청 | R19: 사업자 | S19: 보완요청 | T19: 사업자 | U19: 10월 13일 | V19: 에코시안 | W19: 모니터링보고서 및 검증보고서 내 보안유지 필요부분 구체화 필요 | AE19: 내부방침
A20: =D20&L20&M20 -> (주)선일로에스의 B-A유에서 LNG로 연료전환을 통한 온실가스 배출 감축사업1차2013-04-01 | B20: 18 | C20: 단일감축사업 | D20: (주)선일로에스의 B-A유에서 LNG로 연료전환을 통한 온실가스 배출 감축사업 | E20: (주)선일로에스 | F20: 2008-04-01~2018-03-31 | G20: 1차 (2013-04-01~2013-04-01) | H20: =VLOOKUP(D20,'인증실적 비공개승인관리_국내'!$D:$K,6,FALSE) -> 2022-01-04 | I20: =VLOOKUP(D20,'인증실적 비공개승인관리_국내'!$D:$K,7,FALSE) -> 산업통상부 | J20: =VLOOKUP(D20,'인증실적 비공개승인관리_국내'!$D:$K,8,FALSE) -> 2023-04-19 | K20: =VLOOKUP(A20,'인증실적 비공개승인관리_국내'!$A:$N,8,FALSE) -> 보완요청 | L20: =LEFT(G20,FIND("차",G20)) -> 1차 | M20: =MID(G20,FINDB("(",G20),10) -> 2013-04-01 | N20: =LEFT(VLOOKUP(D20,'국내인증(ORS)'!O:BI,38,0),10) -> 2022-01-04 | O20: =IF(N20=#REF!,"O","X") -> #REF! | P20: 검토필요 | Q20: 보완요청 | R20: 사업자 | S20: 보완요청 | T20: 사업자 | U20: 10월 13일 | V20: 에코시안 | W20: 모니터링보고서 및 검증보고서 내 보안유지 필요부분 구체화 필요 | AE20: 내부방침
A21: =D21&L21&M21 -> 금강 연료전환(B-C유->도시가스) 감축사업(C-002)1차2019-07-31 | B21: 19 | C21: 프로그램감축사업 | D21: 금강 연료전환(B-C유->도시가스) 감축사업(C-002) | E21: (주)삼천리 | F21: 2019-07-31~2026-07-30 | G21: 1차 (2019-07-31~2019-07-31) | H21: =VLOOKUP(D21,'인증실적 비공개승인관리_국내'!$D:$K,6,FALSE) -> 2021-12-22 | I21: =VLOOKUP(D21,'인증실적 비공개승인관리_국내'!$D:$K,7,FALSE) -> 산업통상부 | J21: =VLOOKUP(D21,'인증실적 비공개승인관리_국내'!$D:$K,8,FALSE) -> 2022-10-19 | K21: =VLOOKUP(A21,'인증실적 비공개승인관리_국내'!$A:$N,8,FALSE) -> 보완요청 | L21: =LEFT(G21,FIND("차",G21)) -> 1차 | M21: =MID(G21,FINDB("(",G21),10) -> 2019-07-31 | N21: =LEFT(VLOOKUP(D21,'국내인증(ORS)'!O:BI,38,0),10) -> 2021-12-17 | O21: =IF(N21=#REF!,"O","X") -> #REF! | P21: 검토필요 | Q21: 보완요청 | R21: 사업자 | S21: 보완요청 | T21: 사업자 | U21: 10월 13일 | V21: 에코시안 | W21: 모니터링보고서 및 검증보고서 내 보안유지 필요부분 구체화 필요(사유: 인증 실적 비공개) | AE21: 내부방침 | AF21: 사업명과 상이
A22: =D22&L22&M22 -> 부일레미콘의 B-C유에서 도시가스(LNG)로 연료전환을 통한 온실가스 배출 감축사업1차2018-01-25 | B22: 20 | C22: 단일감축사업 | D22: 부일레미콘의 B-C유에서 도시가스(LNG)로 연료전환을 통한 온실가스 배출 감축사업 | E22: (주)부일레미콘 | F22: 2018-01-25~2028-01-24 | G22: 1차 (2018-01-25~2018-01-25) | H22: =VLOOKUP(D22,'인증실적 비공개승인관리_국내'!$D:$K,6,FALSE) -> 2021-12-17 | I22: =VLOOKUP(D22,'인증실적 비공개승인관리_국내'!$D:$K,7,FALSE) -> 산업통상부 | J22: =VLOOKUP(D22,'인증실적 비공개승인관리_국내'!$D:$K,8,FALSE) -> 2022-10-19 | K22: =VLOOKUP(A22,'인증실적 비공개승인관리_국내'!$A:$N,8,FALSE) -> 보완요청 | L22: =LEFT(G22,FIND("차",G22)) -> 1차 | M22: =MID(G22,FINDB("(",G22),10) -> 2018-01-25 | N22: =LEFT(VLOOKUP(D22,'국내인증(ORS)'!O:BI,38,0),10) -> 2021-12-17 | O22: =IF(N22=#REF!,"O","X") -> #REF! | P22: 검토필요 | Q22: 보완요청 | R22: 사업자 | S22: 보완요청 | T22: 사업자 | U22: 10월 13일 | V22: 에코시안 | W22: 모니터링보고서 및 검증보고서 내 보안유지 필요부분 구체화 필요 | AE22: 내부방침
A23: =D23&L23&M23 -> 현대리바트의 부생연료 1호에서 LNG로 연료전환을 통한 온실가스 배출 감축사업1차2010-11-23 | B23: 21 | C23: 단일감축사업 | D23: 현대리바트의 부생연료 1호에서 LNG로 연료전환을 통한 온실가스 배출 감축사업 | E23: (주)현대리바트 | F23: 2010-11-23~2020-11-22 | G23: 1차 (2010-11-23~2010-11-23) | H23: =VLOOKUP(D23,'인증실적 비공개승인관리_국내'!$D:$K,6,FALSE) -> 2021-09-28 | I23: =VLOOKUP(D23,'인증실적 비공개승인관리_국내'!$D:$K,7,FALSE) -> 산업통상부 | J23: =VLOOKUP(D23,'인증실적 비공개승인관리_국내'!$D:$K,8,FALSE) -> 2022-10-19 | K23: =VLOOKUP(A23,'인증실적 비공개승인관리_국내'!$A:$N,8,FALSE) -> 보완요청 | L23: =LEFT(G23,FIND("차",G23)) -> 1차 | M23: =MID(G23,FINDB("(",G23),10) -> 2010-11-23 | N23: =LEFT(VLOOKUP(D23,'국내인증(ORS)'!O:BI,38,0),10) -> 2021-09-28 | O23: =IF(N23=#REF!,"O","X") -> #REF! | P23: 검토필요 | Q23: 보완요청 | R23: 사업자 | S23: 보완요청 | T23: 사업자 | U23: 10월 13일 | V23: 에코시안 | W23: 모니터링보고서 및 검증보고서 내 보안유지 필요부분 구체화 필요 | AE23: 내부방침
A24: =D24&L24&M24 -> 우성세라믹스공업의 LPG에서 LNG로 연료전환을 통한 온실가스 배출 감축사업1차2008-05-15 | B24: 22 | C24: 단일감축사업 | D24: 우성세라믹스공업의 LPG에서 LNG로 연료전환을 통한 온실가스 배출 감축사업 | E24: 우성세라믹스공업(주) | F24: 2008-05-15~2018-05-14 | G24: 1차 (2008-05-15~2008-05-15) | H24: =VLOOKUP(D24,'인증실적 비공개승인관리_국내'!$D:$K,6,FALSE) -> 2021-09-28 | I24: =VLOOKUP(D24,'인증실적 비공개승인관리_국내'!$D:$K,7,FALSE) -> 산업통상부 | J24: =VLOOKUP(D24,'인증실적 비공개승인관리_국내'!$D:$K,8,FALSE) -> 2022-06-03 | K24: =VLOOKUP(A24,'인증실적 비공개승인관리_국내'!$A:$N,8,FALSE) -> 보완요청 | L24: =LEFT(G24,FIND("차",G24)) -> 1차 | M24: =MID(G24,FINDB("(",G24),10) -> 2008-05-15 | N24: =LEFT(VLOOKUP(D24,'국내인증(ORS)'!O:BI,38,0),10) -> 2021-09-28 | O24: =IF(N24=#REF!,"O","X") -> #REF! | P24: 검토필요 | Q24: 보완요청 | R24: 사업자 | S24: 보완요청 | T24: 사업자 | U24: 5월 26일 | V24: 에코시안_조영우 | W24: 모니터링보고서 및 검증보고서 내 보안유지 필요부분 구체화 필요 | AE24: 내부방침
A25: =D25&L25&M25 -> 태형기업(주) 양주사업장의 B-C유에서 도시가스(LNG)로 연료전환을 통한 온실가스(CO2) 배출 감축사업1차2011-03-30 | B25: 23 | C25: 단일감축사업 | D25: 태형기업(주) 양주사업장의 B-C유에서 도시가스(LNG)로 연료전환을 통한 온실가스(CO2) 배출 감축사업 | E25: 태형기업(주) | F25: 2011-03-30~2021-03-29 | G25: 1차 (2011-03-30~2011-03-30) | H25: =VLOOKUP(D25,'인증실적 비공개승인관리_국내'!$D:$K,6,FALSE) -> 2021-04-22 | I25: =VLOOKUP(D25,'인증실적 비공개승인관리_국내'!$D:$K,7,FALSE) -> 산업통상부 | J25: =VLOOKUP(D25,'인증실적 비공개승인관리_국내'!$D:$K,8,FALSE) -> 2022-06-03 | K25: =VLOOKUP(A25,'인증실적 비공개승인관리_국내'!$A:$N,8,FALSE) -> 보완요청 | L25: =LEFT(G25,FIND("차",G25)) -> 1차 | M25: =MID(G25,FINDB("(",G25),10) -> 2011-03-30 | N25: =LEFT(VLOOKUP(D25,'국내인증(ORS)'!O:BI,38,0),10) -> 2021-04-22 | O25: =IF(N25=#REF!,"O","X") -> #REF! | P25: 검토필요 | Q25: 보완요청 | R25: 사업자 | S25: 보완요청 | T25: 사업자 | U25: 5월 26일 | V25: 에코시안_조영우 | W25: 모니터링보고서 및 검증보고서 내 보안유지 필요부분 구체화 필요 | AE25: 내부방침
A26: =D26&L26&M26 -> 덕성 인천사업장의 B-A유 및 B-C유에서 LNG로 연료전환을 통한 온실가스 배출 감축사업1차2012-12-19 | B26: 24 | C26: 단일감축사업 | D26: 덕성 인천사업장의 B-A유 및 B-C유에서 LNG로 연료전환을 통한 온실가스 배출 감축사업 | E26: (주)덕성 | F26: 2012-12-19~2022-12-18 | G26: 1차 (2012-12-19~2012-12-19) | H26: =VLOOKUP(D26,'인증실적 비공개승인관리_국내'!$D:$K,6,FALSE) -> 2023-11-24 | I26: =VLOOKUP(D26,'인증실적 비공개승인관리_국내'!$D:$K,7,FALSE) -> 산업통상부 | J26: =VLOOKUP(D26,'인증실적 비공개승인관리_국내'!$D:$K,8,FALSE) -> 2024-06-17 | K26: =VLOOKUP(A26,'인증실적 비공개승인관리_국내'!$A:$N,8,FALSE) -> 보완요청 | L26: =LEFT(G26,FIND("차",G26)) -> 1차 | M26: =MID(G26,FINDB("(",G26),10) -> 2012-12-19 | N26: =LEFT(VLOOKUP(D26,'국내인증(ORS)'!O:BI,38,0),10) -> 2023-09-25 | O26: =IF(N26=#REF!,"O","X") -> #REF! | P26: 검토필요 | Q26: 보완요청 | R26: 사업자 | S26: 보완요청 | T26: 사업자 | U26: 5월 26일 | V26: 에코시안_조영우 | W26: 모니터링보고서 및 검증보고서 내 보안유지 필요부분 구체화 필요 | AE26: 내부방침
A27: =D27&L27&M27 -> 삼일이노팩의 B-C유에서 LNG로 연료전환을 통한 온실가스 배출 감축사업1차2014-10-01 | B27: 25 | C27: 단일감축사업 | D27: 삼일이노팩의 B-C유에서 LNG로 연료전환을 통한 온실가스 배출 감축사업 | E27: 주식회사 삼일이노팩 | F27: 2012-10-04~2022-10-03 | G27: 1차 (2014-10-01~2014-10-01) | H27: =VLOOKUP(D27,'인증실적 비공개승인관리_국내'!$D:$K,6,FALSE) -> 2022-11-15 | I27: =VLOOKUP(D27,'인증실적 비공개승인관리_국내'!$D:$K,7,FALSE) -> 산업통상부 | J27: =VLOOKUP(D27,'인증실적 비공개승인관리_국내'!$D:$K,8,FALSE) -> 2024-06-17 | K27: =VLOOKUP(A27,'인증실적 비공개승인관리_국내'!$A:$N,8,FALSE) -> 보완요청 | L27: =LEFT(G27,FIND("차",G27)) -> 1차 | M27: =MID(G27,FINDB("(",G27),10) -> 2014-10-01 | N27: =LEFT(VLOOKUP(D27,'국내인증(ORS)'!O:BI,38,0),10) -> 2022-11-15 | O27: =IF(N27=#REF!,"O","X") -> #REF! | P27: 검토필요 | Q27: 보완요청 | R27: 사업자 | S27: 보완요청 | T27: 사업자 | U27: 5월 26일 | V27: 에코시안_조영우 | W27: 모니터링보고서 및 검증보고서 내 보안유지 필요부분 구체화 필요 | AE27: 내부방침
A28: =D28&L28&M28 -> 한미약품의 경유에서 LNG로 연료전환을 통한 온실가스 배출 감축사업1차2010-04-21 | B28: 26 | C28: 단일감축사업 | D28: 한미약품의 경유에서 LNG로 연료전환을 통한 온실가스 배출 감축사업 | E28: 한미약품(주) | F28: 2007-12-07~2017-12-06 | G28: 1차 (2010-04-21~2010-04-21) | H28: =VLOOKUP(D28,'인증실적 비공개승인관리_국내'!$D:$K,6,FALSE) -> 2021-02-09 | I28: =VLOOKUP(D28,'인증실적 비공개승인관리_국내'!$D:$K,7,FALSE) -> 산업통상부 | J28: =VLOOKUP(D28,'인증실적 비공개승인관리_국내'!$D:$K,8,FALSE) -> 2022-06-03 | K28: =VLOOKUP(A28,'인증실적 비공개승인관리_국내'!$A:$N,8,FALSE) -> 보완요청 | L28: =LEFT(G28,FIND("차",G28)) -> 1차 | M28: =MID(G28,FINDB("(",G28),10) -> 2010-04-21 | N28: =LEFT(VLOOKUP(D28,'국내인증(ORS)'!O:BI,38,0),10) -> 2021-02-09 | O28: =IF(N28=#REF!,"O","X") -> #REF! | P28: 검토필요 | Q28: 보완요청 | R28: 사업자 | S28: 보완요청 | T28: 사업자 | U28: 5월 26일 | V28: 에코시안_조영우 | W28: 모니터링보고서 및 검증보고서 내 보안유지 필요부분 구체화 필요 | AE28: 내부방침
A29: =D29&L29&M29 -> (주)대평의 연료전환 (B-B유 → LNG)에 의한 온실가스(CO2) 배출 감축사업1차2015-11-01 | B29: 27 | C29: 단일감축사업 | D29: (주)대평의 연료전환 (B-B유 → LNG)에 의한 온실가스(CO2) 배출 감축사업 | E29: (주)대평 | F29: 2013-11-01~2018-10-31 | G29: 1차 (2015-11-01~2015-11-01) | H29: =VLOOKUP(D29,'인증실적 비공개승인관리_국내'!$D:$K,6,FALSE) -> 2021-01-25 | I29: =VLOOKUP(D29,'인증실적 비공개승인관리_국내'!$D:$K,7,FALSE) -> 산업통상부 | J29: =VLOOKUP(D29,'인증실적 비공개승인관리_국내'!$D:$K,8,FALSE) -> 2022-06-03 | K29: =VLOOKUP(A29,'인증실적 비공개승인관리_국내'!$A:$N,8,FALSE) -> 보완요청 | L29: =LEFT(G29,FIND("차",G29)) -> 1차 | M29: =MID(G29,FINDB("(",G29),10) -> 2015-11-01 | N29: =LEFT(VLOOKUP(D29,'국내인증(ORS)'!O:BI,38,0),10) -> 2019-10-15 | O29: =IF(N29=#REF!,"O","X") -> #REF! | P29: 검토필요 | Q29: 보완요청 | R29: 사업자 | S29: 보완요청 | T29: 사업자 | U29: 5월 26일 | V29: 에코시안_조영우 | W29: 모니터링보고서 및 검증보고서 내 보안유지 필요부분 구체화 필요 | AE29: 내부방침
A30: =D30&L30&M30 -> 마니커 동두천지점의 B-C유에서 LNG로 연료전환을 통한 온실가스 배출 감축사업1차2008-08-18 | B30: 28 | C30: 단일감축사업 | D30: 마니커 동두천지점의 B-C유에서 LNG로 연료전환을 통한 온실가스 배출 감축사업 | E30: (주)마니커 동두천지점 | F30: 2008-08-18~2018-08-17 | G30: 1차 (2008-08-18~2008-08-18) | H30: =VLOOKUP(D30,'인증실적 비공개승인관리_국내'!$D:$K,6,FALSE) -> 2020-09-02 | I30: =VLOOKUP(D30,'인증실적 비공개승인관리_국내'!$D:$K,7,FALSE) -> 산업통상부 | J30: =VLOOKUP(D30,'인증실적 비공개승인관리_국내'!$D:$K,8,FALSE) -> 2022-06-03 | K30: =VLOOKUP(A30,'인증실적 비공개승인관리_국내'!$A:$N,8,FALSE) -> 보완요청 | L30: =LEFT(G30,FIND("차",G30)) -> 1차 | M30: =MID(G30,FINDB("(",G30),10) -> 2008-08-18 | N30: =LEFT(VLOOKUP(D30,'국내인증(ORS)'!O:BI,38,0),10) -> 2020-09-02 | O30: =IF(N30=#REF!,"O","X") -> #REF! | P30: 검토필요 | Q30: 보완요청 | R30: 사업자 | S30: 보완요청 | T30: 사업자 | U30: 5월 26일 | V30: 에코시안_조영우 | W30: 모니터링보고서 및 검증보고서 내 보안유지 필요부분 구체화 필요 | AE30: 내부방침
A31: =D31&L31&M31 -> (주)한화 울산소재 질산공장 N2O감축 프로젝트3차2017-09-01 | B31: 29 | C31: 단일감축사업 | D31: (주)한화 울산소재 질산공장 N2O감축 프로젝트 | E31: 주식회사 에코아이 | F31: 2014-06-27~2021-06-26 | G31: 3차 (2017-09-01~2017-09-01) | H31: =VLOOKUP(D31,'인증실적 비공개승인관리_국내'!$D:$K,6,FALSE) -> 2022-06-16 | I31: =VLOOKUP(D31,'인증실적 비공개승인관리_국내'!$D:$K,7,FALSE) -> 산업통상부 | J31: =VLOOKUP(D31,'인증실적 비공개승인관리_국내'!$D:$K,8,FALSE) -> 2022-09-28 | K31: =VLOOKUP(A31,'인증실적 비공개승인관리_국내'!$A:$N,8,FALSE) -> 반려 | L31: =LEFT(G31,FIND("차",G31)) -> 3차 | M31: =MID(G31,FINDB("(",G31),10) -> 2017-09-01 | N31: =LEFT(VLOOKUP(D31,'국내인증(ORS)'!O:BI,38,0),10) -> 2020-06-04 | O31: =IF(N31=#REF!,"O","X") -> #REF! | P31: 검토필요 | Q31: 반려 | R31: 종결 | S31: 반려완료 | T31: 종결 | U31: 5월 26일 | V31: 에코시안_조영우 | W31: 사업자 반려 요청 | AE31: 내부방침
A32: =D32&L32&M32 -> 부일화학의 B-C유에서 LNG로 연료전환을 통한 온실가스 배출 감축사업1차2013-06-26 | B32: 30 | C32: 단일감축사업 | D32: 부일화학의 B-C유에서 LNG로 연료전환을 통한 온실가스 배출 감축사업 | E32: 부일화학(주) | F32: 2013-06-26~2023-06-25 | G32: 1차 (2013-06-26~2013-06-26) | H32: =VLOOKUP(D32,'인증실적 비공개승인관리_국내'!$D:$K,6,FALSE) -> 2020-08-24 | I32: =VLOOKUP(D32,'인증실적 비공개승인관리_국내'!$D:$K,7,FALSE) -> 산업통상부 | J32: =VLOOKUP(D32,'인증실적 비공개승인관리_국내'!$D:$K,8,FALSE) -> 2022-06-03 | K32: =VLOOKUP(A32,'인증실적 비공개승인관리_국내'!$A:$N,8,FALSE) -> 보완요청 | L32: =LEFT(G32,FIND("차",G32)) -> 1차 | M32: =MID(G32,FINDB("(",G32),10) -> 2013-06-26 | N32: =LEFT(VLOOKUP(D32,'국내인증(ORS)'!O:BI,38,0),10) -> 2020-08-24 | O32: =IF(N32=#REF!,"O","X") -> #REF! | P32: 검토필요 | Q32: 보완요청 | R32: 사업자 | S32: 보완요청 | T32: 사업자 | U32: 5월 26일 | V32: 에코시안_조영우 | W32: 모니터링보고서 및 검증보고서 내 보안유지 필요부분 구체화 필요 | AE32: 내부방침
A33: =D33&L33&M33 -> 신성금속 용해로 버너교체에 따른 설비 성능개선 및 연료전환을 통한 온실가스 감축사업1차2016-07-01 | B33: 31 | C33: 단일감축사업 | D33: 신성금속 용해로 버너교체에 따른 설비 성능개선 및 연료전환을 통한 온실가스 감축사업 | E33: (주)신성금속산업 | F33: 2015-07-01~2020-06-30 | G33: 1차 (2016-07-01~2016-07-01) | H33: =VLOOKUP(D33,'인증실적 비공개승인관리_국내'!$D:$K,6,FALSE) -> 2020-07-14 | I33: =VLOOKUP(D33,'인증실적 비공개승인관리_국내'!$D:$K,7,FALSE) -> 산업통상부 | J33: =VLOOKUP(D33,'인증실적 비공개승인관리_국내'!$D:$K,8,FALSE) -> 2022-06-03 | K33: =VLOOKUP(A33,'인증실적 비공개승인관리_국내'!$A:$N,8,FALSE) -> 보완요청 | L33: =LEFT(G33,FIND("차",G33)) -> 1차 | M33: =MID(G33,FINDB("(",G33),10) -> 2016-07-01 | N33: =LEFT(VLOOKUP(D33,'국내인증(ORS)'!O:BI,38,0),10) -> 2019-08-13 | O33: =IF(N33=#REF!,"O","X") -> #REF! | P33: 검토필요 | Q33: 보완요청 | R33: 사업자 | S33: 보완요청 | T33: 사업자 | U33: 5월 26일 | V33: 에코시안_조영우 | W33: 모니터링보고서 및 검증보고서 내 보안유지 필요부분 구체화 필요 | AE33: 내부방침
... A40: =D40&L40&M40 -> 한청판지 보일러 버너의 연료전환 (B-C유 → LNG)을 통한 온실가스 감축사업1차2015-10-01 | B40: 38 | C40: 단일감축사업 | D40: 한청판지 보일러 버너의 연료전환 (B-C유 → LNG)을 통한 온실가스 감축사업 | E40: (주)한청판지 | F40: 2013-10-01~2018-09-30 | G40: 1차 (2015-10-01~2015-10-01) | H40: =VLOOKUP(D40,'인증실적 비공개승인관리_국내'!$D:$K,6,FALSE) -> 2019-11-18 | I40: =VLOOKUP(D40,'인증실적 비공개승인관리_국내'!$D:$K,7,FALSE) -> 산업통상부 | J40: =VLOOKUP(D40,'인증실적 비공개승인관리_국내'!$D:$K,8,FALSE) -> 2022-06-03 | K40: =VLOOKUP(A40,'인증실적 비공개승인관리_국내'!$A:$N,8,FALSE) -> 보완요청 | L40: =LEFT(G40,FIND("차",G40)) -> 1차 | M40: =MID(G40,FINDB("(",G40),10) -> 2015-10-01 | N40: =LEFT(VLOOKUP(D40,'국내인증(ORS)'!O:BI,38,0),10) -> 2019-11-18 | O40: =IF(N40=#REF!,"O","X") -> #REF! | P40: 검토필요 | Q40: 보완요청 | R40: 사업자 | S40: 보완요청 | T40: 사업자 | U40: 5월 26일 | V40: 에코시안_조영우 | W40: 모니터링보고서 및 검증보고서 내 보안유지 필요부분 구체화 필요 | AE40: 내부방침
A41: =D41&L41&M41 -> (주)한국요업 소성로 미활용에너지 회수를 통한 온실가스 감축사업1차2014-01-01 | B41: 39 | C41: 단일감축사업 | D41: (주)한국요업 소성로 미활용에너지 회수를 통한 온실가스 감축사업 | E41: 한국요업주식회사 | F41: 2014-01-01~2018-12-31 | G41: 1차 (2014-01-01~2014-01-01) | H41: =VLOOKUP(D41,'인증실적 비공개승인관리_국내'!$D:$K,6,FALSE) -> 2019-11-18 | I41: =VLOOKUP(D41,'인증실적 비공개승인관리_국내'!$D:$K,7,FALSE) -> 산업통상부 | J41: =VLOOKUP(D41,'인증실적 비공개승인관리_국내'!$D:$K,8,FALSE) -> 2025-01-09 | K41: =VLOOKUP(A41,'인증실적 비공개승인관리_국내'!$A:$N,8,FALSE) -> 보완요청 | L41: =LEFT(G41,FIND("차",G41)) -> 1차 | M41: =MID(G41,FINDB("(",G41),10) -> 2014-01-01 | N41: =LEFT(VLOOKUP(D41,'국내인증(ORS)'!O:BI,38,0),10) -> 2019-11-18 | O41: =IF(N41=#REF!,"O","X") -> #REF! | P41: 승인 전 | Q41: 선택 | R41: 선택 | S41: 보완요청 | T41: 사업자 | U41: 45672 | V41: 에코시안_조은지 | W41: 제출서류 미비로 보완 요청. 보완 요청 통보 문구 기재(공단 통보)
A42: =D42&L42&M42 -> 피피이씨의령 두부공장 목재펠릿 연료 전환을 통한 온실가스 감축사업1차2015-10-01 | B42: 40 | C42: 단일감축사업 | D42: 피피이씨의령 두부공장 목재펠릿 연료 전환을 통한 온실가스 감축사업 | E42: 주식회사 피피이씨의령 | F42: 2015-10-01~2020-09-30 | G42: 1차 (2015-10-01~2015-10-01) | H42: =VLOOKUP(D42,'인증실적 비공개승인관리_국내'!$D:$K,6,FALSE) -> 2019-11-17 | I42: =VLOOKUP(D42,'인증실적 비공개승인관리_국내'!$D:$K,7,FALSE) -> 산업통상부 | J42: =VLOOKUP(D42,'인증실적 비공개승인관리_국내'!$D:$K,8,FALSE) -> 2022-06-03 | K42: =VLOOKUP(A42,'인증실적 비공개승인관리_국내'!$A:$N,8,FALSE) -> 보완요청 | L42: =LEFT(G42,FIND("차",G42)) -> 1차 | M42: =MID(G42,FINDB("(",G42),10) -> 2015-10-01 | N42: =LEFT(VLOOKUP(D42,'국내인증(ORS)'!O:BI,38,0),10) -> 2019-11-17 | O42: =IF(N42=#REF!,"O","X") -> #REF! | P42: 검토필요 | Q42: 보완요청 | R42: 사업자 | S42: 보완요청 | T42: 사업자 | U42: 5월 26일 | V42: 에코시안_조영우 | W42: 모니터링보고서 및 검증보고서 내 보안유지 필요부분 구체화 필요 | AE42: 내부방침
A43: =D43&L43&M43 -> 풀무원 음성 두부공장 목재펠릿 연료 전환을 통한 온실가스 감축사업1차2015-09-01 | B43: 41 | C43: 단일감축사업 | D43: 풀무원 음성 두부공장 목재펠릿 연료 전환을 통한 온실가스 감축사업 | E43: 풀무원식품 주식회사 | F43: 2013-09-01~2018-08-31 | G43: 1차 (2015-09-01~2015-09-01) | H43: =VLOOKUP(D43,'인증실적 비공개승인관리_국내'!$D:$K,6,FALSE) -> 2019-11-17 | I43: =VLOOKUP(D43,'인증실적 비공개승인관리_국내'!$D:$K,7,FALSE) -> 산업통상부 | J43: =VLOOKUP(D43,'인증실적 비공개승인관리_국내'!$D:$K,8,FALSE) -> 2022-06-03 | K43: =VLOOKUP(A43,'인증실적 비공개승인관리_국내'!$A:$N,8,FALSE) -> 보완요청 | L43: =LEFT(G43,FIND("차",G43)) -> 1차 | M43: =MID(G43,FINDB("(",G43),10) -> 2015-09-01 | N43: =LEFT(VLOOKUP(D43,'국내인증(ORS)'!O:BI,38,0),10) -> 2019-11-17 | O43: =IF(N43=#REF!,"O","X") -> #REF! | P43: 검토필요 | Q43: 보완요청 | R43: 사업자 | S43: 보완요청 | T43: 사업자 | U43: 5월 26일 | V43: 에코시안_조영우 | W43: 모니터링보고서 및 검증보고서 내 보안유지 필요부분 구체화 필요 | AE43: 내부방침
A44: =D44&L44&M44 -> 영광아스콘(주) 버너연료를 B-C유 에서 LNG로 연료 전환 하는 온실가스 감축사업1차2016-06-01 | B44: 42 | C44: 단일감축사업 | D44: 영광아스콘(주) 버너연료를 B-C유 에서 LNG로 연료 전환 하는 온실가스 감축사업 | E44: 영광아스콘(주) | F44: 2012-06-01~2017-05-31 | G44: 1차 (2016-06-01~2016-06-01) | H44: =VLOOKUP(D44,'인증실적 비공개승인관리_국내'!$D:$K,6,FALSE) -> 2019-11-17 | I44: =VLOOKUP(D44,'인증실적 비공개승인관리_국내'!$D:$K,7,FALSE) -> 산업통상부 | J44: =VLOOKUP(D44,'인증실적 비공개승인관리_국내'!$D:$K,8,FALSE) -> 2022-06-03 | K44: =VLOOKUP(A44,'인증실적 비공개승인관리_국내'!$A:$N,8,FALSE) -> 보완요청 | L44: =LEFT(G44,FIND("차",G44)) -> 1차 | M44: =MID(G44,FINDB("(",G44),10) -> 2016-06-01 | N44: =LEFT(VLOOKUP(D44,'국내인증(ORS)'!O:BI,38,0),10) -> 2019-11-17 | O44: =IF(N44=#REF!,"O","X") -> #REF! | P44: 검토필요 | Q44: 보완요청 | R44: 사업자 | S44: 보완요청 | T44: 사업자 | U44: 5월 26일 | V44: 에코시안_조영우 | W44: 모니터링보고서 및 검증보고서 내 보안유지 필요부분 구체화 필요 | AE44: 내부방침
A45: =D45&L45&M45 -> 신일산업의 보일러 연료교체(LNG->목재펠릿)을 통한 온실가스 감축사업1차2016-05-01 | B45: 43 | C45: 단일감축사업 | D45: 신일산업의 보일러 연료교체(LNG->목재펠릿)을 통한 온실가스 감축사업 | E45: 신일산업(주) | F45: 2015-05-01~2020-04-30 | G45: 1차 (2016-05-01~2016-05-01) | H45: =VLOOKUP(D45,'인증실적 비공개승인관리_국내'!$D:$K,6,FALSE) -> 2019-11-17 | I45: =VLOOKUP(D45,'인증실적 비공개승인관리_국내'!$D:$K,7,FALSE) -> 산업통상부 | J45: =VLOOKUP(D45,'인증실적 비공개승인관리_국내'!$D:$K,8,FALSE) -> 2023-10-11 | K45: =VLOOKUP(A45,'인증실적 비공개승인관리_국내'!$A:$N,8,FALSE) -> 보완요청 | L45: =LEFT(G45,FIND("차",G45)) -> 1차 | M45: =MID(G45,FINDB("(",G45),10) -> 2016-05-01 | N45: =LEFT(VLOOKUP(D45,'국내인증(ORS)'!O:BI,38,0),10) -> 2019-11-17 | O45: =IF(N45=#REF!,"O","X") -> #REF! | P45: 검토필요 | Q45: 보완요청 | R45: 사업자 | S45: 보완요청 | T45: 사업자 | U45: 45188 | V45: 에코시안_조영우 | W45: 모니터링보고서 및 검증보고서 내 보안유지 필요부분 구체화 필요 | AE45: 내부방침
A46: =D46&L46&M46 -> 신원아이엔티 버너교체 연료전환(B-C유 → LPG)을 통한 온실가스 감축 사업1차2016-08-01 | B46: 44 | C46: 단일감축사업 | D46: 신원아이엔티 버너교체 연료전환(B-C유 → LPG)을 통한 온실가스 감축 사업 | E46: 신원아이엔티 | F46: 2016-08-01~2021-07-31 | G46: 1차 (2016-08-01~2016-08-01) | H46: =VLOOKUP(D46,'인증실적 비공개승인관리_국내'!$D:$K,6,FALSE) -> 2019-11-17 | I46: =VLOOKUP(D46,'인증실적 비공개승인관리_국내'!$D:$K,7,FALSE) -> 산업통상부 | J46: =VLOOKUP(D46,'인증실적 비공개승인관리_국내'!$D:$K,8,FALSE) -> 2022-06-02 | K46: =VLOOKUP(A46,'인증실적 비공개승인관리_국내'!$A:$N,8,FALSE) -> 보완요청 | L46: =LEFT(G46,FIND("차",G46)) -> 1차 | M46: =MID(G46,FINDB("(",G46),10) -> 2016-08-01 | N46: =LEFT(VLOOKUP(D46,'국내인증(ORS)'!O:BI,38,0),10) -> 2019-11-17 | O46: =IF(N46=#REF!,"O","X") -> #REF! | P46: 검토필요 | Q46: 보완요청 | R46: 사업자 | S46: 보완요청 | T46: 사업자 | U46: 5월 26일 | V46: 에코시안_조혜민 | W46: 모니터링보고서 및 검증보고서 내 보안유지 필요부분 구체화 필요 | AE46: 내부방침
A47: =D47&L47&M47 -> 신명염색 버너교체 연료전환(B-C유 → LPG)을 통한 온실가스 감축 사업1차2016-11-01 | B47: 45 | C47: 단일감축사업 | D47: 신명염색 버너교체 연료전환(B-C유 → LPG)을 통한 온실가스 감축 사업 | E47: 신명염색(주) | F47: 2016-11-01~2021-10-31 | G47: 1차 (2016-11-01~2016-11-01) | H47: =VLOOKUP(D47,'인증실적 비공개승인관리_국내'!$D:$K,6,FALSE) -> 2019-11-17 | I47: =VLOOKUP(D47,'인증실적 비공개승인관리_국내'!$D:$K,7,FALSE) -> 산업통상부 | J47: =VLOOKUP(D47,'인증실적 비공개승인관리_국내'!$D:$K,8,FALSE) -> 2022-06-02 | K47: =VLOOKUP(A47,'인증실적 비공개승인관리_국내'!$A:$N,8,FALSE) -> 보완요청 | L47: =LEFT(G47,FIND("차",G47)) -> 1차 | M47: =MID(G47,FINDB("(",G47),10) -> 2016-11-01 | N47: =LEFT(VLOOKUP(D47,'국내인증(ORS)'!O:BI,38,0),10) -> 2019-11-17 | O47: =IF(N47=#REF!,"O","X") -> #REF! | P47: 검토필요 | Q47: 보완요청 | R47: 사업자 | S47: 보완요청 | T47: 사업자 | U47: 5월 26일 | V47: 에코시안_조혜민 | W47: 모니터링보고서 및 검증보고서 내 보안유지 필요부분 구체화 필요 | AE47: 내부방침
A48: =D48&L48&M48 -> 세흥 목재펠릿 보일러 설치를 통한 온실가스 감축사업1차2015-10-01 | B48: 46 | C48: 단일감축사업 | D48: 세흥 목재펠릿 보일러 설치를 통한 온실가스 감축사업 | E48: (주)세흥 | F48: 2014-04-01~2019-03-31 | G48: 1차 (2015-10-01~2015-10-01) | H48: =VLOOKUP(D48,'인증실적 비공개승인관리_국내'!$D:$K,6,FALSE) -> 2019-11-17 | I48: =VLOOKUP(D48,'인증실적 비공개승인관리_국내'!$D:$K,7,FALSE) -> 산업통상부 | J48: =VLOOKUP(D48,'인증실적 비공개승인관리_국내'!$D:$K,8,FALSE) -> 2022-06-02 | K48: =VLOOKUP(A48,'인증실적 비공개승인관리_국내'!$A:$N,8,FALSE) -> 보완요청 | L48: =LEFT(G48,FIND("차",G48)) -> 1차 | M48: =MID(G48,FINDB("(",G48),10) -> 2015-10-01 | N48: =LEFT(VLOOKUP(D48,'국내인증(ORS)'!O:BI,38,0),10) -> 2019-11-17 | O48: =IF(N48=#REF!,"O","X") -> #REF! | P48: 검토필요 | Q48: 보완요청 | R48: 사업자 | S48: 보완요청 | T48: 사업자 | U48: 5월 26일 | V48: 에코시안_조혜민 | W48: 모니터링보고서 및 검증보고서 내 보안유지 필요부분 구체화 필요 | AE48: 내부방침
A49: =D49&L49&M49 -> 삼두염색(주) 보일러 연료전환(LNG → 목재펠릿)을 통한 온실가스(CO2) 감축사업1차2015-09-01 | B49: 47 | C49: 단일감축사업 | D49: 삼두염색(주) 보일러 연료전환(LNG → 목재펠릿)을 통한 온실가스(CO2) 감축사업 | E49: 삼두염색(주) | F49: 2014-03-01~2019-02-28 | G49: 1차 (2015-09-01~2015-09-01) | H49: =VLOOKUP(D49,'인증실적 비공개승인관리_국내'!$D:$K,6,FALSE) -> 2019-11-17 | I49: =VLOOKUP(D49,'인증실적 비공개승인관리_국내'!$D:$K,7,FALSE) -> 산업통상부 | J49: =VLOOKUP(D49,'인증실적 비공개승인관리_국내'!$D:$K,8,FALSE) -> 2022-06-02 | K49: =VLOOKUP(A49,'인증실적 비공개승인관리_국내'!$A:$N,8,FALSE) -> 보완요청 | L49: =LEFT(G49,FIND("차",G49)) -> 1차 | M49: =MID(G49,FINDB("(",G49),10) -> 2015-09-01 | N49: =LEFT(VLOOKUP(D49,'국내인증(ORS)'!O:BI,38,0),10) -> 2019-11-17 | O49: =IF(N49=#REF!,"O","X") -> #REF! | P49: 검토필요 | Q49: 보완요청 | R49: 사업자 | S49: 보완요청 | T49: 사업자 | U49: 5월 26일 | V49: 에코시안_조혜민 | W49: 모니터링보고서 및 검증보고서 내 보안유지 필요부분 구체화 필요 | AE49: 내부방침
A50: =D50&L50&M50 -> 삼광에프엔씨 목재펠릿 연료 전환을 통한 온실가스 감축사업1차2016-09-01 | B50: 48 | C50: 단일감축사업 | D50: 삼광에프엔씨 목재펠릿 연료 전환을 통한 온실가스 감축사업 | E50: (주)삼광에프엔씨 | F50: 2014-09-01~2019-08-31 | G50: 1차 (2016-09-01~2016-09-01) | H50: =VLOOKUP(D50,'인증실적 비공개승인관리_국내'!$D:$K,6,FALSE) -> 2019-11-17 | I50: =VLOOKUP(D50,'인증실적 비공개승인관리_국내'!$D:$K,7,FALSE) -> 산업통상부 | J50: =VLOOKUP(D50,'인증실적 비공개승인관리_국내'!$D:$K,8,FALSE) -> 2022-06-02 | K50: =VLOOKUP(A50,'인증실적 비공개승인관리_국내'!$A:$N,8,FALSE) -> 보완요청 | L50: =LEFT(G50,FIND("차",G50)) -> 1차 | M50: =MID(G50,FINDB("(",G50),10) -> 2016-09-01 | N50: =LEFT(VLOOKUP(D50,'국내인증(ORS)'!O:BI,38,0),10) -> 2019-11-17 | O50: =IF(N50=#REF!,"O","X") -> #REF! | P50: 검토필요 | Q50: 보완요청 | R50: 사업자 | S50: 보완요청 | T50: 사업자 | U50: 5월 26일 | V50: 에코시안_조혜민 | W50: 모니터링보고서 및 검증보고서 내 보안유지 필요부분 구체화 필요 | AE50: 내부방침
A51: =D51&L51&M51 -> 동양제지공업 보일러 연료 전환([B-C유+정제유]→LNG) 온실가스 감축사업1차2015-07-01 | B51: 49 | C51: 단일감축사업 | D51: 동양제지공업 보일러 연료 전환([B-C유+정제유]→LNG) 온실가스 감축사업 | E51: 동양제지공업(주) | F51: 2013-01-01~2017-12-31 | G51: 1차 (2015-07-01~2015-07-01) | H51: =VLOOKUP(D51,'인증실적 비공개승인관리_국내'!$D:$K,6,FALSE) -> 2019-11-17 | I51: =VLOOKUP(D51,'인증실적 비공개승인관리_국내'!$D:$K,7,FALSE) -> 산업통상부 | J51: =VLOOKUP(D51,'인증실적 비공개승인관리_국내'!$D:$K,8,FALSE) -> 2022-06-02 | K51: =VLOOKUP(A51,'인증실적 비공개승인관리_국내'!$A:$N,8,FALSE) -> 보완요청 | L51: =LEFT(G51,FIND("차",G51)) -> 1차 | M51: =MID(G51,FINDB("(",G51),10) -> 2015-07-01 | N51: =LEFT(VLOOKUP(D51,'국내인증(ORS)'!O:BI,38,0),10) -> 2019-11-17 | O51: =IF(N51=#REF!,"O","X") -> #REF! | P51: 검토필요 | Q51: 보완요청 | R51: 사업자 | S51: 보완요청 | T51: 사업자 | U51: 5월 26일 | V51: 에코시안_조혜민 | W51: 모니터링보고서 및 검증보고서 내 보안유지 필요부분 구체화 필요 | AE51: 내부방침
A52: =D52&L52&M52 -> 동보피엔티 목재펠릿 연료 전환을 통한 온실가스 감축사업1차2016-02-01 | B52: 50 | C52: 단일감축사업 | D52: 동보피엔티 목재펠릿 연료 전환을 통한 온실가스 감축사업 | E52: [주]동보피엔티 | F52: 2014-02-01~2019-01-31 | G52: 1차 (2016-02-01~2016-02-01) | H52: =VLOOKUP(D52,'인증실적 비공개승인관리_국내'!$D:$K,6,FALSE) -> 2019-11-17 | I52: =VLOOKUP(D52,'인증실적 비공개승인관리_국내'!$D:$K,7,FALSE) -> 산업통상부 | J52: =VLOOKUP(D52,'인증실적 비공개승인관리_국내'!$D:$K,8,FALSE) -> 2022-06-02 | K52: =VLOOKUP(A52,'인증실적 비공개승인관리_국내'!$A:$N,8,FALSE) -> 보완요청 | L52: =LEFT(G52,FIND("차",G52)) -> 1차 | M52: =MID(G52,FINDB("(",G52),10) -> 2016-02-01 | N52: =LEFT(VLOOKUP(D52,'국내인증(ORS)'!O:BI,38,0),10) -> 2019-11-17 | O52: =IF(N52=#REF!,"O","X") -> #REF! | P52: 검토필요 | Q52: 보완요청 | R52: 사업자 | S52: 보완요청 | T52: 사업자 | U52: 5월 26일 | V52: 에코시안_조혜민 | W52: 모니터링보고서 및 검증보고서 내 보안유지 필요부분 구체화 필요 | AE52: 내부방침
A53: =D53&L53&M53 -> 경림산업(주) 제주사업장 B-B유에서 목재펠릿으로 연료 전환을 통한 온실가스 감축사업1차2016-05-01 | B53: 51 | C53: 단일감축사업 | D53: 경림산업(주) 제주사업장 B-B유에서 목재펠릿으로 연료 전환을 통한 온실가스 감축사업 | E53: 경림산업(주) | F53: 2015-05-01~2020-04-30 | G53: 1차 (2016-05-01~2016-05-01) | H53: =VLOOKUP(D53,'인증실적 비공개승인관리_국내'!$D:$K,6,FALSE) -> 2019-11-17 | I53: =VLOOKUP(D53,'인증실적 비공개승인관리_국내'!$D:$K,7,FALSE) -> 산업통상부 | J53: =VLOOKUP(D53,'인증실적 비공개승인관리_국내'!$D:$K,8,FALSE) -> 2022-06-02 | K53: =VLOOKUP(A53,'인증실적 비공개승인관리_국내'!$A:$N,8,FALSE) -> 보완요청 | L53: =LEFT(G53,FIND("차",G53)) -> 1차 | M53: =MID(G53,FINDB("(",G53),10) -> 2016-05-01 | N53: =LEFT(VLOOKUP(D53,'국내인증(ORS)'!O:BI,38,0),10) -> 2019-11-17 | O53: =IF(N53=#REF!,"O","X") -> #REF! | P53: 검토필요 | Q53: 보완요청 | R53: 사업자 | S53: 보완요청 | T53: 사업자 | U53: 5월 26일 | V53: 에코시안_조혜민 | W53: 모니터링보고서 및 검증보고서 내 보안유지 필요부분 구체화 필요 | AE53: 내부방침
A54: =D54&L54&M54 -> (주)우리섬유 버너교체 연료전환(경유, B-C유 → LPG)을 통한 온실가스 감축 사업1차2016-10-01 | B54: 52 | C54: 단일감축사업 | D54: (주)우리섬유 버너교체 연료전환(경유, B-C유 → LPG)을 통한 온실가스 감축 사업 | E54: 우리섬유 | F54: 2016-10-01~2021-09-30 | G54: 1차 (2016-10-01~2016-10-01) | H54: =VLOOKUP(D54,'인증실적 비공개승인관리_국내'!$D:$K,6,FALSE) -> 2019-11-17 | I54: =VLOOKUP(D54,'인증실적 비공개승인관리_국내'!$D:$K,7,FALSE) -> 산업통상부 | J54: =VLOOKUP(D54,'인증실적 비공개승인관리_국내'!$D:$K,8,FALSE) -> 2022-06-02 | K54: =VLOOKUP(A54,'인증실적 비공개승인관리_국내'!$A:$N,8,FALSE) -> 보완요청 | L54: =LEFT(G54,FIND("차",G54)) -> 1차 | M54: =MID(G54,FINDB("(",G54),10) -> 2016-10-01 | N54: =LEFT(VLOOKUP(D54,'국내인증(ORS)'!O:BI,38,0),10) -> 2019-11-17 | O54: =IF(N54=#REF!,"O","X") -> #REF! | P54: 검토필요 | Q54: 보완요청 | R54: 사업자 | S54: 보완요청 | T54: 사업자 | U54: 5월 26일 | V54: 에코시안_조혜민 | W54: 모니터링보고서 및 검증보고서 내 보안유지 필요부분 구체화 필요 | AE54: 내부방침
A55: =D55&L55&M55 -> (주)와이엠 프로폴의 보일러 연료전환 (B-C유 → LNG)에 의한 온실가스(CO2) 배출 감축사업1차2013-07-01 | B55: 53 | C55: 단일감축사업 | D55: (주)와이엠 프로폴의 보일러 연료전환 (B-C유 → LNG)에 의한 온실가스(CO2) 배출 감축사업 | E55: (주)와이엠프로폴 | F55: 2013-07-01~2018-06-30 | G55: 1차 (2013-07-01~2013-07-01) | H55: =VLOOKUP(D55,'인증실적 비공개승인관리_국내'!$D:$K,6,FALSE) -> 2019-11-17 | I55: =VLOOKUP(D55,'인증실적 비공개승인관리_국내'!$D:$K,7,FALSE) -> 산업통상부 | J55: =VLOOKUP(D55,'인증실적 비공개승인관리_국내'!$D:$K,8,FALSE) -> 2022-06-02 | K55: =VLOOKUP(A55,'인증실적 비공개승인관리_국내'!$A:$N,8,FALSE) -> 보완요청 | L55: =LEFT(G55,FIND("차",G55)) -> 1차 | M55: =MID(G55,FINDB("(",G55),10) -> 2013-07-01 | N55: =LEFT(VLOOKUP(D55,'국내인증(ORS)'!O:BI,38,0),10) -> 2019-11-17 | O55: =IF(N55=#REF!,"O","X") -> #REF! | P55: 검토필요 | Q55: 보완요청 | R55: 사업자 | S55: 보완요청 | T55: 사업자 | U55: 5월 26일 | V55: 에코시안_조혜민 | W55: 모니터링보고서 및 검증보고서 내 보안유지 필요부분 구체화 필요 | AE55: 내부방침
A56: =D56&L56&M56 -> (주)에이치에스아쿠아피드 밀양사업장 B-C유에서 목재펠릿으로 연료전환을 통한 온실가스 감축사업1차2016-06-01 | B56: 54 | C56: 단일감축사업 | D56: (주)에이치에스아쿠아피드 밀양사업장 B-C유에서 목재펠릿으로 연료전환을 통한 온실가스 감축사업 | E56: (주)에이치에스아쿠아피드 | F56: 2014-06-01~2019-05-31 | G56: 1차 (2016-06-01~2016-06-01) | H56: =VLOOKUP(D56,'인증실적 비공개승인관리_국내'!$D:$K,6,FALSE) -> 2019-11-17 | I56: =VLOOKUP(D56,'인증실적 비공개승인관리_국내'!$D:$K,7,FALSE) -> 산업통상부 | J56: =VLOOKUP(D56,'인증실적 비공개승인관리_국내'!$D:$K,8,FALSE) -> 2022-06-02 | K56: =VLOOKUP(A56,'인증실적 비공개승인관리_국내'!$A:$N,8,FALSE) -> 보완요청 | L56: =LEFT(G56,FIND("차",G56)) -> 1차 | M56: =MID(G56,FINDB("(",G56),10) -> 2016-06-01 | N56: =LEFT(VLOOKUP(D56,'국내인증(ORS)'!O:BI,38,0),10) -> 2019-11-17 | O56: =IF(N56=#REF!,"O","X") -> #REF! | P56: 검토필요 | Q56: 보완요청 | R56: 사업자 | S56: 보완요청 | T56: 사업자 | U56: 5월 26일 | V56: 에코시안_조혜민 | W56: 모니터링보고서 및 검증보고서 내 보안유지 필요부분 구체화 필요 | AE56: 내부방침
A57: =D57&L57&M57 -> 성창 버너 연료전환을 통한 온실가스 (CO2) 감축사업1차2015-07-01 | B57: 55 | C57: 단일감축사업 | D57: 성창 버너 연료전환을 통한 온실가스 (CO2) 감축사업 | E57: (주)성창 | F57: 2013-07-01~2018-06-30 | G57: 1차 (2015-07-01~2015-07-01) | H57: =VLOOKUP(D57,'인증실적 비공개승인관리_국내'!$D:$K,6,FALSE) -> 2019-11-17 | I57: =VLOOKUP(D57,'인증실적 비공개승인관리_국내'!$D:$K,7,FALSE) -> 산업통상부 | J57: =VLOOKUP(D57,'인증실적 비공개승인관리_국내'!$D:$K,8,FALSE) -> 2022-06-02 | K57: =VLOOKUP(A57,'인증실적 비공개승인관리_국내'!$A:$N,8,FALSE) -> 보완요청 | L57: =LEFT(G57,FIND("차",G57)) -> 1차 | M57: =MID(G57,FINDB("(",G57),10) -> 2015-07-01 | N57: =LEFT(VLOOKUP(D57,'국내인증(ORS)'!O:BI,38,0),10) -> 2019-11-17 | O57: =IF(N57=#REF!,"O","X") -> #REF! | P57: 검토필요 | Q57: 보완요청 | R57: 사업자 | S57: 보완요청 | T57: 사업자 | U57: 5월 26일 | V57: 에코시안_조혜민 | W57: 모니터링보고서 및 검증보고서 내 보안유지 필요부분 구체화 필요 | AE57: 내부방침
... A63: =D63&L63&M63 -> ㈜태형기업 화성 공장 아스콘 생산 시 연료 B-C유에서 LNG로의 연료전환을 통한 온실가스 감축사업1차2016-04-01 | B63: 61 | C63: 단일감축사업 | D63: ㈜태형기업 화성 공장 아스콘 생산 시 연료 B-C유에서 LNG로의 연료전환을 통한 온실가스 감축사업 | E63: 태형기업(주) 본점 | F63: 2012-04-01~2017-03-31 | G63: 1차 (2016-04-01~2016-04-01) | H63: =VLOOKUP(D63,'인증실적 비공개승인관리_국내'!$D:$K,6,FALSE) -> 2019-11-14 | I63: =VLOOKUP(D63,'인증실적 비공개승인관리_국내'!$D:$K,7,FALSE) -> 산업통상부 | J63: =VLOOKUP(D63,'인증실적 비공개승인관리_국내'!$D:$K,8,FALSE) -> 2022-06-02 | K63: =VLOOKUP(A63,'인증실적 비공개승인관리_국내'!$A:$N,8,FALSE) -> 보완요청 | L63: =LEFT(G63,FIND("차",G63)) -> 1차 | M63: =MID(G63,FINDB("(",G63),10) -> 2016-04-01 | N63: =LEFT(VLOOKUP(D63,'국내인증(ORS)'!O:BI,38,0),10) -> 2019-11-14 | O63: =IF(N63=#REF!,"O","X") -> #REF! | P63: 검토필요 | Q63: 보완요청 | R63: 사업자 | S63: 보완요청 | T63: 사업자 | U63: 5월 26일 | V63: 에코시안_조혜민 | W63: 모니터링보고서 및 검증보고서 내 보안유지 필요부분 구체화 필요 | AE63: 내부방침
A64: =D64&L64&M64 -> 케이비에프 보일러의 연료전환(부생연료2호->LPG)을 통한 온실가스 감축 사업1차2016-06-10 | B64: 62 | C64: 단일감축사업 | D64: 케이비에프 보일러의 연료전환(부생연료2호->LPG)을 통한 온실가스 감축 사업 | E64: 케이비에프(주) | F64: 2013-12-10~2018-12-09 | G64: 1차 (2016-06-10~2016-06-10) | H64: =VLOOKUP(D64,'인증실적 비공개승인관리_국내'!$D:$K,6,FALSE) -> 2019-11-14 | I64: =VLOOKUP(D64,'인증실적 비공개승인관리_국내'!$D:$K,7,FALSE) -> 산업통상부 | J64: =VLOOKUP(D64,'인증실적 비공개승인관리_국내'!$D:$K,8,FALSE) -> 2023-06-19 | K64: =VLOOKUP(A64,'인증실적 비공개승인관리_국내'!$A:$N,8,FALSE) -> 보완요청 | L64: =LEFT(G64,FIND("차",G64)) -> 1차 | M64: =MID(G64,FINDB("(",G64),10) -> 2016-06-10 | N64: =LEFT(VLOOKUP(D64,'국내인증(ORS)'!O:BI,38,0),10) -> 2019-11-14 | O64: =IF(N64=#REF!,"O","X") -> #REF! | P64: 검토필요 | Q64: 보완요청 | R64: 사업자 | S64: 보완요청 | T64: 사업자 | U64: 45096 | V64: 에코시안_조영우 | W64: 모니터링보고서 및 검증보고서 내 보안유지 필요부분 구체화 필요 | AE64: 내부방침
A65: =D65&L65&M65 -> 우일산업 청양공장 목재펠릿 연료 전환(부생연료 2호-> 목재펠릿)을 통한 온실가스 감축사업1차2016-07-01 | B65: 63 | C65: 단일감축사업 | D65: 우일산업 청양공장 목재펠릿 연료 전환(부생연료 2호-> 목재펠릿)을 통한 온실가스 감축사업 | E65: 우일산업(주) | F65: 2014-07-01~2019-06-30 | G65: 1차 (2016-07-01~2016-07-01) | H65: =VLOOKUP(D65,'인증실적 비공개승인관리_국내'!$D:$K,6,FALSE) -> 2019-11-14 | I65: =VLOOKUP(D65,'인증실적 비공개승인관리_국내'!$D:$K,7,FALSE) -> 산업통상부 | J65: =VLOOKUP(D65,'인증실적 비공개승인관리_국내'!$D:$K,8,FALSE) -> 2022-06-02 | K65: =VLOOKUP(A65,'인증실적 비공개승인관리_국내'!$A:$N,8,FALSE) -> 보완요청 | L65: =LEFT(G65,FIND("차",G65)) -> 1차 | M65: =MID(G65,FINDB("(",G65),10) -> 2016-07-01 | N65: =LEFT(VLOOKUP(D65,'국내인증(ORS)'!O:BI,38,0),10) -> 2019-11-14 | O65: =IF(N65=#REF!,"O","X") -> #REF! | P65: 검토필요 | Q65: 보완요청 | R65: 사업자 | S65: 보완요청 | T65: 사업자 | U65: 5월 26일 | V65: 에코시안_조혜민 | W65: 모니터링보고서 및 검증보고서 내 보안유지 필요부분 구체화 필요 | AE65: 내부방침
A66: =D66&L66&M66 -> 신화콘크리트의 목재펠릿 연료전환(B-C유->목재펠릿)을 통한 온실가스 감축사업1차2015-11-01 | B66: 64 | C66: 단일감축사업 | D66: 신화콘크리트의 목재펠릿 연료전환(B-C유->목재펠릿)을 통한 온실가스 감축사업 | E66: (주)신화콘크리트 | F66: 2014-11-01~2019-10-31 | G66: 1차 (2015-11-01~2015-11-01) | H66: =VLOOKUP(D66,'인증실적 비공개승인관리_국내'!$D:$K,6,FALSE) -> 2019-11-14 | I66: =VLOOKUP(D66,'인증실적 비공개승인관리_국내'!$D:$K,7,FALSE) -> 산업통상부 | J66: =VLOOKUP(D66,'인증실적 비공개승인관리_국내'!$D:$K,8,FALSE) -> 2022-06-02 | K66: =VLOOKUP(A66,'인증실적 비공개승인관리_국내'!$A:$N,8,FALSE) -> 보완요청 | L66: =LEFT(G66,FIND("차",G66)) -> 1차 | M66: =MID(G66,FINDB("(",G66),10) -> 2015-11-01 | N66: =LEFT(VLOOKUP(D66,'국내인증(ORS)'!O:BI,38,0),10) -> 2019-11-14 | O66: =IF(N66=#REF!,"O","X") -> #REF! | P66: 검토필요 | Q66: 보완요청 | R66: 사업자 | S66: 보완요청 | T66: 사업자 | U66: 5월 26일 | V66: 에코시안_조혜민 | W66: 모니터링보고서 및 검증보고서 내 보안유지 필요부분 구체화 필요 | AE66: 내부방침
A67: =D67&L67&M67 -> 승민섬유 보일러 버너의 연료전환(B-C → LNG)을 통한 온실가스 감축사업1차2016-08-01 | B67: 65 | C67: 단일감축사업 | D67: 승민섬유 보일러 버너의 연료전환(B-C → LNG)을 통한 온실가스 감축사업 | E67: 승민섬유 | F67: 2014-08-01~2019-07-31 | G67: 1차 (2016-08-01~2016-08-01) | H67: =VLOOKUP(D67,'인증실적 비공개승인관리_국내'!$D:$K,6,FALSE) -> 2019-11-14 | I67: =VLOOKUP(D67,'인증실적 비공개승인관리_국내'!$D:$K,7,FALSE) -> 산업통상부 | J67: =VLOOKUP(D67,'인증실적 비공개승인관리_국내'!$D:$K,8,FALSE) -> 2022-06-07 | K67: =VLOOKUP(A67,'인증실적 비공개승인관리_국내'!$A:$N,8,FALSE) -> 보완요청 | L67: =LEFT(G67,FIND("차",G67)) -> 1차 | M67: =MID(G67,FINDB("(",G67),10) -> 2016-08-01 | N67: =LEFT(VLOOKUP(D67,'국내인증(ORS)'!O:BI,38,0),10) -> 2019-11-14 | O67: =IF(N67=#REF!,"O","X") -> #REF! | P67: 검토필요 | Q67: 보완요청 | R67: 사업자 | S67: 보완요청 | T67: 사업자 | U67: 5월 26일 | V67: 에코시안_기샛별 | W67: 모니터링보고서 및 검증보고서 내 보안유지 필요부분 구체화 필요 | AE67: 내부방침
A68: =D68&L68&M68 -> 세창이피에스 김포공장 목재펠릿 연료 전환(LNG→목재펠릿)을 통한 온실가스 감축사업1차2016-01-01 | B68: 66 | C68: 단일감축사업 | D68: 세창이피에스 김포공장 목재펠릿 연료 전환(LNG→목재펠릿)을 통한 온실가스 감축사업 | E68: 세창이피에스[주] | F68: 2014-01-01~2018-12-31 | G68: 1차 (2016-01-01~2016-01-01) | H68: =VLOOKUP(D68,'인증실적 비공개승인관리_국내'!$D:$K,6,FALSE) -> 2019-11-14 | I68: =VLOOKUP(D68,'인증실적 비공개승인관리_국내'!$D:$K,7,FALSE) -> 산업통상부 | J68: =VLOOKUP(D68,'인증실적 비공개승인관리_국내'!$D:$K,8,FALSE) -> 2023-06-19 | K68: =VLOOKUP(A68,'인증실적 비공개승인관리_국내'!$A:$N,8,FALSE) -> 보완요청 | L68: =LEFT(G68,FIND("차",G68)) -> 1차 | M68: =MID(G68,FINDB("(",G68),10) -> 2016-01-01 | N68: =LEFT(VLOOKUP(D68,'국내인증(ORS)'!O:BI,38,0),10) -> 2019-11-14 | O68: =IF(N68=#REF!,"O","X") -> #REF! | P68: 검토필요 | Q68: 보완요청 | R68: 사업자 | S68: 보완요청 | T68: 사업자 | U68: 45096 | V68: 에코시안_조영우 | W68: 모니터링보고서 및 검증보고서 내 보안유지 필요부분 구체화 필요 | AE68: 내부방침
A69: =D69&L69&M69 -> (주)세광케미칼김포사업장 정제유 및 벙커C유에서 목재펠릿 연료전환을 통한 온실가스 감축사업1차2014-10-01 | B69: 67 | C69: 단일감축사업 | D69: (주)세광케미칼김포사업장 정제유 및 벙커C유에서 목재펠릿 연료전환을 통한 온실가스 감축사업 | E69: [주]세광케미칼 | F69: 2014-10-01~2019-09-30 | G69: 1차 (2014-10-01~2014-10-01) | H69: =VLOOKUP(D69,'인증실적 비공개승인관리_국내'!$D:$K,6,FALSE) -> 2019-11-14 | I69: =VLOOKUP(D69,'인증실적 비공개승인관리_국내'!$D:$K,7,FALSE) -> 산업통상부 | J69: =VLOOKUP(D69,'인증실적 비공개승인관리_국내'!$D:$K,8,FALSE) -> 2022-06-07 | K69: =VLOOKUP(A69,'인증실적 비공개승인관리_국내'!$A:$N,8,FALSE) -> 보완요청 | L69: =LEFT(G69,FIND("차",G69)) -> 1차 | M69: =MID(G69,FINDB("(",G69),10) -> 2014-10-01 | N69: =LEFT(VLOOKUP(D69,'국내인증(ORS)'!O:BI,38,0),10) -> 2019-11-14 | O69: =IF(N69=#REF!,"O","X") -> #REF! | P69: 검토필요 | Q69: 보완요청 | R69: 사업자 | S69: 보완요청 | T69: 사업자 | U69: 5월 26일 | V69: 에코시안_기샛별 | W69: 모니터링보고서 및 검증보고서 내 보안유지 필요부분 구체화 필요 | AE69: 내부방침
A70: =D70&L70&M70 -> 성원산업사 열매체보일러 버너교체를 통한 연료전환(B-C유 → LNG) 온실가스 배출 감축 사업 1차2015-03-01 | B70: 68 | C70: 단일감축사업 | D70: 성원산업사 열매체보일러 버너교체를 통한 연료전환(B-C유 → LNG) 온실가스 배출 감축 사업 | E70: 성원산업사 | F70: 2013-03-19~2018-03-18 | G70: 1차 (2015-03-01~2015-03-01) | H70: =VLOOKUP(D70,'인증실적 비공개승인관리_국내'!$D:$K,6,FALSE) -> 2019-11-14 | I70: =VLOOKUP(D70,'인증실적 비공개승인관리_국내'!$D:$K,7,FALSE) -> 산업통상부 | J70: =VLOOKUP(D70,'인증실적 비공개승인관리_국내'!$D:$K,8,FALSE) -> 2022-06-07 | K70: =VLOOKUP(A70,'인증실적 비공개승인관리_국내'!$A:$N,8,FALSE) -> 보완요청 | L70: =LEFT(G70,FIND("차",G70)) -> 1차 | M70: =MID(G70,FINDB("(",G70),10) -> 2015-03-01 | N70: =LEFT(VLOOKUP(D70,'국내인증(ORS)'!O:BI,38,0),10) -> 2019-11-14 | O70: =IF(N70=#REF!,"O","X") -> #REF! | P70: 검토필요 | Q70: 보완요청 | R70: 사업자 | S70: 보완요청 | T70: 사업자 | U70: 5월 26일 | V70: 에코시안_기샛별 | W70: 모니터링보고서 및 검증보고서 내 보안유지 필요부분 구체화 필요 | AE70: 내부방침
A71: =D71&L71&M71 -> 폐열스팀으로 기존의 LNG 및 B-C유 사용 생산스팀을 대체하여 온실가스 배출을 감축하는 사업1차2016-04-01 | B71: 69 | C71: 단일감축사업 | D71: 폐열스팀으로 기존의 LNG 및 B-C유 사용 생산스팀을 대체하여 온실가스 배출을 감축하는 사업 | E71: 서진섬유(주) | F71: 2012-04-01~2017-03-31 | G71: 1차 (2016-04-01~2016-04-01) | H71: =VLOOKUP(D71,'인증실적 비공개승인관리_국내'!$D:$K,6,FALSE) -> 2019-11-14 | I71: =VLOOKUP(D71,'인증실적 비공개승인관리_국내'!$D:$K,7,FALSE) -> 산업통상부 | J71: =VLOOKUP(D71,'인증실적 비공개승인관리_국내'!$D:$K,8,FALSE) -> 2022-06-07 | K71: =VLOOKUP(A71,'인증실적 비공개승인관리_국내'!$A:$N,8,FALSE) -> 보완요청 | L71: =LEFT(G71,FIND("차",G71)) -> 1차 | M71: =MID(G71,FINDB("(",G71),10) -> 2016-04-01 | N71: =LEFT(VLOOKUP(D71,'국내인증(ORS)'!O:BI,38,0),10) -> 2019-11-14 | O71: =IF(N71=#REF!,"O","X") -> #REF! | P71: 검토필요 | Q71: 보완요청 | R71: 사업자 | S71: 보완요청 | T71: 사업자 | U71: 5월 26일 | V71: 에코시안_기샛별 | W71: 모니터링보고서 및 검증보고서 내 보안유지 필요부분 구체화 필요 | AE71: 내부방침
A72: =D72&L72&M72 -> 한탈L&C의 보일러 연료 교체(LPG->목재펠릿)을 통한 온실가스 감축사업1차2016-02-01 | B72: 70 | C72: 단일감축사업 | D72: 한탈L&C의 보일러 연료 교체(LPG->목재펠릿)을 통한 온실가스 감축사업 | E72: (주)한탈L&C | F72: 2014-08-01~2019-07-31 | G72: 1차 (2016-02-01~2016-02-01) | H72: =VLOOKUP(D72,'인증실적 비공개승인관리_국내'!$D:$K,6,FALSE) -> 2019-11-14 | I72: =VLOOKUP(D72,'인증실적 비공개승인관리_국내'!$D:$K,7,FALSE) -> 산업통상부 | J72: =VLOOKUP(D72,'인증실적 비공개승인관리_국내'!$D:$K,8,FALSE) -> 2022-10-19 | K72: =VLOOKUP(A72,'인증실적 비공개승인관리_국내'!$A:$N,8,FALSE) -> 보완요청 | L72: =LEFT(G72,FIND("차",G72)) -> 1차 | M72: =MID(G72,FINDB("(",G72),10) -> 2016-02-01 | N72: =LEFT(VLOOKUP(D72,'국내인증(ORS)'!O:BI,38,0),10) -> 2019-11-14 | O72: =IF(N72=#REF!,"O","X") -> #REF! | P72: 검토필요 | Q72: 보완요청 | R72: 사업자 | S72: 보완요청 | T72: 사업자 | U72: 10월 13일 | V72: 에코시안 | W72: 모니터링보고서 및 검증보고서 내 보안유지 필요부분 구체화 필요 | AE72: 내부방침
A73: =D73&L73&M73 -> 폐열스팀으로 LNG 스팀보일러 생산스팀을 대체하여 CO2를 감축하는 사업1차2016-05-01 | B73: 71 | C73: 단일감축사업 | D73: 폐열스팀으로 LNG 스팀보일러 생산스팀을 대체하여 CO2를 감축하는 사업 | E73: 명신섬유공업(주) | F73: 2012-05-01~2017-04-30 | G73: 1차 (2016-05-01~2016-05-01) | H73: =VLOOKUP(D73,'인증실적 비공개승인관리_국내'!$D:$K,6,FALSE) -> 2019-11-14 | I73: =VLOOKUP(D73,'인증실적 비공개승인관리_국내'!$D:$K,7,FALSE) -> 산업통상부 | J73: =VLOOKUP(D73,'인증실적 비공개승인관리_국내'!$D:$K,8,FALSE) -> 2022-06-07 | K73: =VLOOKUP(A73,'인증실적 비공개승인관리_국내'!$A:$N,8,FALSE) -> 보완요청 | L73: =LEFT(G73,FIND("차",G73)) -> 1차 | M73: =MID(G73,FINDB("(",G73),10) -> 2016-05-01 | N73: =LEFT(VLOOKUP(D73,'국내인증(ORS)'!O:BI,38,0),10) -> 2019-11-14 | O73: =IF(N73=#REF!,"O","X") -> #REF! | P73: 검토필요 | Q73: 보완요청 | R73: 사업자 | S73: 보완요청 | T73: 사업자 | U73: 5월 26일 | V73: 에코시안_기샛별 | W73: 모니터링보고서 및 검증보고서 내 보안유지 필요부분 구체화 필요 | AE73: 내부방침
A74: =D74&L74&M74 -> 동호칼슘(주)의 보일러 연료전환(벙커C유->LNG)을 통한 온실가스 배출 감축사업1차2015-11-01 | B74: 72 | C74: 단일감축사업 | D74: 동호칼슘(주)의 보일러 연료전환(벙커C유->LNG)을 통한 온실가스 배출 감축사업 | E74: 동호칼슘(주) | F74: 2011-11-01~2016-10-31 | G74: 1차 (2015-11-01~2015-11-01) | H74: =VLOOKUP(D74,'인증실적 비공개승인관리_국내'!$D:$K,6,FALSE) -> 2019-11-14 | I74: =VLOOKUP(D74,'인증실적 비공개승인관리_국내'!$D:$K,7,FALSE) -> 산업통상부 | J74: =VLOOKUP(D74,'인증실적 비공개승인관리_국내'!$D:$K,8,FALSE) -> 2022-06-07 | K74: =VLOOKUP(A74,'인증실적 비공개승인관리_국내'!$A:$N,8,FALSE) -> 보완요청 | L74: =LEFT(G74,FIND("차",G74)) -> 1차 | M74: =MID(G74,FINDB("(",G74),10) -> 2015-11-01 | N74: =LEFT(VLOOKUP(D74,'국내인증(ORS)'!O:BI,38,0),10) -> 2019-11-14 | O74: =IF(N74=#REF!,"O","X") -> #REF! | P74: 검토필요 | Q74: 보완요청 | R74: 사업자 | S74: 보완요청 | T74: 사업자 | U74: 5월 26일 | V74: 에코시안_기샛별 | W74: 모니터링보고서 및 검증보고서 내 보안유지 필요부분 구체화 필요 | AE74: 내부방침
A75: =D75&L75&M75 -> 동원유지 목재펠릿 연료 전환을 통한 온실가스 감축사업1차2016-09-01 | B75: 73 | C75: 단일감축사업 | D75: 동원유지 목재펠릿 연료 전환을 통한 온실가스 감축사업 | E75: 동원유지 | F75: 2014-09-01~2019-08-31 | G75: 1차 (2016-09-01~2016-09-01) | H75: =VLOOKUP(D75,'인증실적 비공개승인관리_국내'!$D:$K,6,FALSE) -> 2019-11-14 | I75: =VLOOKUP(D75,'인증실적 비공개승인관리_국내'!$D:$K,7,FALSE) -> 산업통상부 | J75: =VLOOKUP(D75,'인증실적 비공개승인관리_국내'!$D:$K,8,FALSE) -> 2025-01-09 | K75: =VLOOKUP(A75,'인증실적 비공개승인관리_국내'!$A:$N,8,FALSE) -> 보완요청 | L75: =LEFT(G75,FIND("차",G75)) -> 1차 | M75: =MID(G75,FINDB("(",G75),10) -> 2016-09-01 | N75: =LEFT(VLOOKUP(D75,'국내인증(ORS)'!O:BI,38,0),10) -> 2019-11-14 | O75: =IF(N75=#REF!,"O","X") -> #REF! | P75: 승인 전 | Q75: 선택 | R75: 선택 | S75: 보완요청 | T75: 사업자 | U75: 45672 | V75: 에코시안_조영우 | W75: 제출서류 미비로 보완 요청. 보완 요청 통보 문구 기재(공단 통보)
A76: =D76&L76&M76 -> 도형아스콘 버너 연료전환을 통한 온실가스 감축사업1차2015-09-01 | B76: 74 | C76: 단일감축사업 | D76: 도형아스콘 버너 연료전환을 통한 온실가스 감축사업 | E76: 유한회사 도형 | F76: 2013-09-01~2018-08-31 | G76: 1차 (2015-09-01~2015-09-01) | H76: =VLOOKUP(D76,'인증실적 비공개승인관리_국내'!$D:$K,6,FALSE) -> 2019-11-14 | I76: =VLOOKUP(D76,'인증실적 비공개승인관리_국내'!$D:$K,7,FALSE) -> 산업통상부 | J76: =VLOOKUP(D76,'인증실적 비공개승인관리_국내'!$D:$K,8,FALSE) -> 2022-06-07 | K76: =VLOOKUP(A76,'인증실적 비공개승인관리_국내'!$A:$N,8,FALSE) -> 보완요청 | L76: =LEFT(G76,FIND("차",G76)) -> 1차 | M76: =MID(G76,FINDB("(",G76),10) -> 2015-09-01 | N76: =LEFT(VLOOKUP(D76,'국내인증(ORS)'!O:BI,38,0),10) -> 2019-11-14 | O76: =IF(N76=#REF!,"O","X") -> #REF! | P76: 검토필요 | Q76: 보완요청 | R76: 사업자 | S76: 보완요청 | T76: 사업자 | U76: 5월 26일 | V76: 에코시안_기샛별 | W76: 모니터링보고서 및 검증보고서 내 보안유지 필요부분 구체화 필요 | AE76: 내부방침
A77: =D77&L77&M77 -> 대흥산업 열매체 보일러의 연료교체(B-C유→LNG)를 통한 온실가스(CO2) 배출 감축사업1차2016-08-01 | B77: 75 | C77: 단일감축사업 | D77: 대흥산업 열매체 보일러의 연료교체(B-C유→LNG)를 통한 온실가스(CO2) 배출 감축사업 | E77: 대흥산업 | F77: 2012-02-01~2017-01-31 | G77: 1차 (2016-08-01~2016-08-01) | H77: =VLOOKUP(D77,'인증실적 비공개승인관리_국내'!$D:$K,6,FALSE) -> 2019-11-14 | I77: =VLOOKUP(D77,'인증실적 비공개승인관리_국내'!$D:$K,7,FALSE) -> 산업통상부 | J77: =VLOOKUP(D77,'인증실적 비공개승인관리_국내'!$D:$K,8,FALSE) -> 2022-06-07 | K77: =VLOOKUP(A77,'인증실적 비공개승인관리_국내'!$A:$N,8,FALSE) -> 보완요청 | L77: =LEFT(G77,FIND("차",G77)) -> 1차 | M77: =MID(G77,FINDB("(",G77),10) -> 2016-08-01 | N77: =LEFT(VLOOKUP(D77,'국내인증(ORS)'!O:BI,38,0),10) -> 2019-11-14 | O77: =IF(N77=#REF!,"O","X") -> #REF! | P77: 검토필요 | Q77: 보완요청 | R77: 사업자 | S77: 보완요청 | T77: 사업자 | U77: 5월 26일 | V77: 에코시안_기샛별 | W77: 모니터링보고서 및 검증보고서 내 보안유지 필요부분 구체화 필요 | AE77: 내부방침
A78: =D78&L78&M78 -> 대동EPS의 보일러 교체(B-C유 -> 목재펠릿보일러)를 통한 온실가스 감축사업1차2016-01-01 | B78: 76 | C78: 단일감축사업 | D78: 대동EPS의 보일러 교체(B-C유 -> 목재펠릿보일러)를 통한 온실가스 감축사업 | E78: 대동EPS | F78: 2014-07-01~2019-06-30 | G78: 1차 (2016-01-01~2016-01-01) | H78: =VLOOKUP(D78,'인증실적 비공개승인관리_국내'!$D:$K,6,FALSE) -> 2019-11-14 | I78: =VLOOKUP(D78,'인증실적 비공개승인관리_국내'!$D:$K,7,FALSE) -> 산업통상부 | J78: =VLOOKUP(D78,'인증실적 비공개승인관리_국내'!$D:$K,8,FALSE) -> 2022-06-07 | K78: =VLOOKUP(A78,'인증실적 비공개승인관리_국내'!$A:$N,8,FALSE) -> 보완요청 | L78: =LEFT(G78,FIND("차",G78)) -> 1차 | M78: =MID(G78,FINDB("(",G78),10) -> 2016-01-01 | N78: =LEFT(VLOOKUP(D78,'국내인증(ORS)'!O:BI,38,0),10) -> 2019-11-14 | O78: =IF(N78=#REF!,"O","X") -> #REF! | P78: 검토필요 | Q78: 보완요청 | R78: 사업자 | S78: 보완요청 | T78: 사업자 | U78: 5월 26일 | V78: 에코시안_기샛별 | W78: 모니터링보고서 및 검증보고서 내 보안유지 필요부분 구체화 필요 | AE78: 내부방침
A79: =D79&L79&M79 -> 대경화학 증기재압축장치 등(B-C유를 LNG로 연료전환) 설치를 통한 온실가스 감축사업1차2016-07-01 | B79: 77 | C79: 단일감축사업 | D79: 대경화학 증기재압축장치 등(B-C유를 LNG로 연료전환) 설치를 통한 온실가스 감축사업 | E79: (주)대경화학 | F79: 2014-07-01~2019-06-30 | G79: 1차 (2016-07-01~2016-07-01) | H79: =VLOOKUP(D79,'인증실적 비공개승인관리_국내'!$D:$K,6,FALSE) -> 2019-11-14 | I79: =VLOOKUP(D79,'인증실적 비공개승인관리_국내'!$D:$K,7,FALSE) -> 산업통상부 | J79: =VLOOKUP(D79,'인증실적 비공개승인관리_국내'!$D:$K,8,FALSE) -> 2022-06-07 | K79: =VLOOKUP(A79,'인증실적 비공개승인관리_국내'!$A:$N,8,FALSE) -> 보완요청 | L79: =LEFT(G79,FIND("차",G79)) -> 1차 | M79: =MID(G79,FINDB("(",G79),10) -> 2016-07-01 | N79: =LEFT(VLOOKUP(D79,'국내인증(ORS)'!O:BI,38,0),10) -> 2019-11-14 | O79: =IF(N79=#REF!,"O","X") -> #REF! | P79: 검토필요 | Q79: 보완요청 | R79: 사업자 | S79: 보완요청 | T79: 사업자 | U79: 5월 26일 | V79: 에코시안_기샛별 | W79: 모니터링보고서 및 검증보고서 내 보안유지 필요부분 구체화 필요 | AE79: 내부방침
A80: =D80&L80&M80 -> ㈜태호화학 논산사업장 B-C유에서 LPG로 연료 전환을 통한 온실가스 감축사업1차2016-05-01 | B80: 78 | C80: 단일감축사업 | D80: ㈜태호화학 논산사업장 B-C유에서 LPG로 연료 전환을 통한 온실가스 감축사업 | E80: (주)태호화학 | F80: 2014-11-01~2019-10-31 | G80: 1차 (2016-05-01~2016-05-01) | H80: =VLOOKUP(D80,'인증실적 비공개승인관리_국내'!$D:$K,6,FALSE) -> 2019-11-14 | I80: =VLOOKUP(D80,'인증실적 비공개승인관리_국내'!$D:$K,7,FALSE) -> 산업통상부 | J80: =VLOOKUP(D80,'인증실적 비공개승인관리_국내'!$D:$K,8,FALSE) -> 2022-06-02 | K80: =VLOOKUP(A80,'인증실적 비공개승인관리_국내'!$A:$N,8,FALSE) -> 보완요청 | L80: =LEFT(G80,FIND("차",G80)) -> 1차 | M80: =MID(G80,FINDB("(",G80),10) -> 2016-05-01 | N80: =LEFT(VLOOKUP(D80,'국내인증(ORS)'!O:BI,38,0),10) -> 2019-11-14 | O80: =IF(N80=#REF!,"O","X") -> #REF! | P80: 검토필요 | Q80: 보완요청 | R80: 사업자 | S80: 보완요청 | T80: 사업자 | U80: 5월 26일 | V80: KECM_이태준 | W80: 모니터링보고서 및 검증보고서 내 보안유지 필요부분 구체화 필요 | X80: X | Y80: X | Z80: X | AA80: O | AB80: O | AC80: X | AD80: X | AE80: 내부방침
A81: =D81&L81&M81 -> 크린멤버스의 목재펠릿 연료전환(LPG->목재펠릿)을 통한 온실가스 감축사업1차2016-01-01 | B81: 79 | C81: 단일감축사업 | D81: 크린멤버스의 목재펠릿 연료전환(LPG->목재펠릿)을 통한 온실가스 감축사업 | E81: (주)크린멤버스 | F81: 2015-01-01~2019-12-31 | G81: 1차 (2016-01-01~2016-01-01) | H81: =VLOOKUP(D81,'인증실적 비공개승인관리_국내'!$D:$K,6,FALSE) -> 2019-11-14 | I81: =VLOOKUP(D81,'인증실적 비공개승인관리_국내'!$D:$K,7,FALSE) -> 산업통상부 | J81: =VLOOKUP(D81,'인증실적 비공개승인관리_국내'!$D:$K,8,FALSE) -> 2022-10-19 | K81: =VLOOKUP(A81,'인증실적 비공개승인관리_국내'!$A:$N,8,FALSE) -> 보완요청 | L81: =LEFT(G81,FIND("차",G81)) -> 1차 | M81: =MID(G81,FINDB("(",G81),10) -> 2016-01-01 | N81: =LEFT(VLOOKUP(D81,'국내인증(ORS)'!O:BI,38,0),10) -> 2019-11-14 | O81: =IF(N81=#REF!,"O","X") -> #REF! | P81: 검토필요 | Q81: 보완요청 | R81: 사업자 | S81: 보완요청 | T81: 사업자 | U81: 10월 13일 | V81: 에코시안 | W81: 모니터링보고서 및 검증보고서 내 보안유지 필요부분 구체화 필요 | AE81: 내부방침
A82: =D82&L82&M82 -> 케이티세라믹 당진사업장 소성로 및 드라이어의 연료교체(LPG->LNG)를 통한 온실가스 배출 감축사업1차2015-06-01 | B82: 80 | C82: 단일감축사업 | D82: 케이티세라믹 당진사업장 소성로 및 드라이어의 연료교체(LPG->LNG)를 통한 온실가스 배출 감축사업 | E82: 경남모직(주)케이티세라믹사업부 당진지점 | F82: 2014-06-01~2019-05-31 | G82: 1차 (2015-06-01~2015-06-01) | H82: =VLOOKUP(D82,'인증실적 비공개승인관리_국내'!$D:$K,6,FALSE) -> 2019-11-14 | I82: =VLOOKUP(D82,'인증실적 비공개승인관리_국내'!$D:$K,7,FALSE) -> 산업통상부 | J82: =VLOOKUP(D82,'인증실적 비공개승인관리_국내'!$D:$K,8,FALSE) -> 2022-10-19 | K82: =VLOOKUP(A82,'인증실적 비공개승인관리_국내'!$A:$N,8,FALSE) -> 보완요청 | L82: =LEFT(G82,FIND("차",G82)) -> 1차 | M82: =MID(G82,FINDB("(",G82),10) -> 2015-06-01 | N82: =LEFT(VLOOKUP(D82,'국내인증(ORS)'!O:BI,38,0),10) -> 2019-11-14 | O82: =IF(N82=#REF!,"O","X") -> #REF! | P82: 검토필요 | Q82: 보완요청 | R82: 사업자 | S82: 보완요청 | T82: 사업자 | U82: 10월 13일 | V82: 에코시안 | W82: 모니터링보고서 및 검증보고서 내 보안유지 필요부분 구체화 필요 | AE82: 내부방침
A83: =D83&L83&M83 -> (주)산하의 아스콘 제조 사업장의 버너연료를 B-C유에서 LNG로 연료 전환하는 온실가스 감축사업1차2015-10-01 | B83: 81 | C83: 단일감축사업 | D83: (주)산하의 아스콘 제조 사업장의 버너연료를 B-C유에서 LNG로 연료 전환하는 온실가스 감축사업 | E83: (주)산하 | F83: 2012-10-01~2017-09-30 | G83: 1차 (2015-10-01~2015-10-01) | H83: =VLOOKUP(D83,'인증실적 비공개승인관리_국내'!$D:$K,6,FALSE) -> 2019-11-14 | I83: =VLOOKUP(D83,'인증실적 비공개승인관리_국내'!$D:$K,7,FALSE) -> 산업통상부 | J83: =VLOOKUP(D83,'인증실적 비공개승인관리_국내'!$D:$K,8,FALSE) -> 2022-06-02 | K83: =VLOOKUP(A83,'인증실적 비공개승인관리_국내'!$A:$N,8,FALSE) -> 보완요청 | L83: =LEFT(G83,FIND("차",G83)) -> 1차 | M83: =MID(G83,FINDB("(",G83),10) -> 2015-10-01 | N83: =LEFT(VLOOKUP(D83,'국내인증(ORS)'!O:BI,38,0),10) -> 2019-11-14 | O83: =IF(N83=#REF!,"O","X") -> #REF! | P83: 검토필요 | Q83: 보완요청 | R83: 사업자 | S83: 보완요청 | T83: 사업자 | U83: 5월 26일 | V83: KECM_이태준 | W83: 모니터링보고서 및 검증보고서 내 보안유지 필요부분 구체화 필요 | X83: X | Y83: X | Z83: X | AA83: O | AB83: O | AC83: X | AD83: X | AE83: 내부방침
A84: =D84&L84&M84 -> 케이티세라믹 예산사업장 소성로 및 드라이어의 연료교체(LPG-LNG)을 통한 온실가스 배출 감축사업1차2016-04-01 | B84: 82 | C84: 단일감축사업 | D84: 케이티세라믹 예산사업장 소성로 및 드라이어의 연료교체(LPG-LNG)을 통한 온실가스 배출 감축사업 | E84: 경남모직(주)케이티세라믹사업부 예산지점 | F84: 2013-04-01~2018-03-31 | G84: 1차 (2016-04-01~2016-04-01) | H84: =VLOOKUP(D84,'인증실적 비공개승인관리_국내'!$D:$K,6,FALSE) -> 2019-11-14 | I84: =VLOOKUP(D84,'인증실적 비공개승인관리_국내'!$D:$K,7,FALSE) -> 산업통상부 | J84: =VLOOKUP(D84,'인증실적 비공개승인관리_국내'!$D:$K,8,FALSE) -> 2022-10-19 | K84: =VLOOKUP(A84,'인증실적 비공개승인관리_국내'!$A:$N,8,FALSE) -> 보완요청 | L84: =LEFT(G84,FIND("차",G84)) -> 1차 | M84: =MID(G84,FINDB("(",G84),10) -> 2016-04-01 | N84: =LEFT(VLOOKUP(D84,'국내인증(ORS)'!O:BI,38,0),10) -> 2019-11-18 | O84: =IF(N84=#REF!,"O","X") -> #REF! | P84: 검토필요 | Q84: 보완요청 | R84: 사업자 | S84: 보완요청 | T84: 사업자 | U84: 10월 13일 | V84: 에코시안 | W84: 모니터링보고서 및 검증보고서 내 보안유지 필요부분 구체화 필요 | AE84: 내부방침
A85: =D85&L85&M85 -> 미활용열을 회수하는 사업1차2015-08-01 | B85: 83 | C85: 단일감축사업 | D85: 미활용열을 회수하는 사업 | E85: (주)세왕섬유 | F85: 2015-08-01~2020-07-31 | G85: 1차 (2015-08-01~2015-08-01) | H85: =VLOOKUP(D85,'인증실적 비공개승인관리_국내'!$D:$K,6,FALSE) -> 2019-11-14 | I85: =VLOOKUP(D85,'인증실적 비공개승인관리_국내'!$D:$K,7,FALSE) -> 산업통상부 | J85: =VLOOKUP(D85,'인증실적 비공개승인관리_국내'!$D:$K,8,FALSE) -> 2022-06-02 | K85: =VLOOKUP(A85,'인증실적 비공개승인관리_국내'!$A:$N,8,FALSE) -> 보완요청 | L85: =LEFT(G85,FIND("차",G85)) -> 1차 | M85: =MID(G85,FINDB("(",G85),10) -> 2015-08-01 | N85: =LEFT(VLOOKUP(D85,'국내인증(ORS)'!O:BI,38,0),10) -> 2021-08-18 | O85: =IF(N85=#REF!,"O","X") -> #REF! | P85: 검토필요 | Q85: 보완요청 | R85: 사업자 | S85: 보완요청 | T85: 사업자 | U85: 5월 26일 | V85: KECM_이태준 | W85: 모니터링보고서 및 검증보고서 내 보안유지 필요부분 구체화 필요 | X85: X | Y85: X | Z85: X | AA85: O | AB85: O | AC85: X | AD85: X | AE85: 내부방침
A86: =D86&L86&M86 -> ㈜ 상산쎄라믹 버너 연료전환(B-C유-LNG)를 통한 온실가스 감축사업1차2016-04-01 | B86: 84 | C86: 단일감축사업 | D86: ㈜ 상산쎄라믹 버너 연료전환(B-C유-LNG)를 통한 온실가스 감축사업 | E86: (주)상산쎄라믹 | F86: 2012-04-01~2017-03-31 | G86: 1차 (2016-04-01~2016-04-01) | H86: =VLOOKUP(D86,'인증실적 비공개승인관리_국내'!$D:$K,6,FALSE) -> 2019-11-14 | I86: =VLOOKUP(D86,'인증실적 비공개승인관리_국내'!$D:$K,7,FALSE) -> 산업통상부 | J86: =VLOOKUP(D86,'인증실적 비공개승인관리_국내'!$D:$K,8,FALSE) -> 2022-06-02 | K86: =VLOOKUP(A86,'인증실적 비공개승인관리_국내'!$A:$N,8,FALSE) -> 보완요청 | L86: =LEFT(G86,FIND("차",G86)) -> 1차 | M86: =MID(G86,FINDB("(",G86),10) -> 2016-04-01 | N86: =LEFT(VLOOKUP(D86,'국내인증(ORS)'!O:BI,38,0),10) -> 2019-11-14 | O86: =IF(N86=#REF!,"O","X") -> #REF! | P86: 검토필요 | Q86: 보완요청 | R86: 사업자 | S86: 보완요청 | T86: 사업자 | U86: 5월 26일 | V86: KECM_이태준 | W86: 모니터링보고서 및 검증보고서 내 보안유지 필요부분 구체화 필요 | X86: X | Y86: X | Z86: X | AA86: O | AB86: X | AC86: X | AD86: X | AE86: 내부방침
A87: =D87&L87&M87 -> 동원유지 보일러 연료 전환(B-C유→목재펠릿)을 통한 온실가스 감축사업1차2016-07-01 | B87: 85 | C87: 단일감축사업 | D87: 동원유지 보일러 연료 전환(B-C유→목재펠릿)을 통한 온실가스 감축사업 | E87: [자]동원유지 | F87: 2014-07-01~2019-06-30 | G87: 1차 (2016-07-01~2016-07-01) | H87: =VLOOKUP(D87,'인증실적 비공개승인관리_국내'!$D:$K,6,FALSE) -> 2019-11-14 | I87: =VLOOKUP(D87,'인증실적 비공개승인관리_국내'!$D:$K,7,FALSE) -> 산업통상부 | J87: =VLOOKUP(D87,'인증실적 비공개승인관리_국내'!$D:$K,8,FALSE) -> 2022-06-02 | K87: =VLOOKUP(A87,'인증실적 비공개승인관리_국내'!$A:$N,8,FALSE) -> 보완요청 | L87: =LEFT(G87,FIND("차",G87)) -> 1차 | M87: =MID(G87,FINDB("(",G87),10) -> 2016-07-01 | N87: =LEFT(VLOOKUP(D87,'국내인증(ORS)'!O:BI,38,0),10) -> 2019-11-14 | O87: =IF(N87=#REF!,"O","X") -> #REF! | P87: 검토필요 | Q87: 보완요청 | R87: 사업자 | S87: 보완요청 | T87: 사업자 | U87: 5월 26일 | V87: KECM_이태준 | W87: 모니터링보고서 및 검증보고서 내 보안유지 필요부분 구체화 필요 | X87: X | Y87: X | Z87: X | AA87: O | AB87: O | AC87: X | AD87: X | AE87: 내부방침
A88: =D88&L88&M88 -> 금산공영(합) 아스콘 드라이어 버너 연료전환(B-C유 → LPG)을 통한 온실가스(CO2) 감축사업1차2016-05-01 | B88: 86 | C88: 단일감축사업 | D88: 금산공영(합) 아스콘 드라이어 버너 연료전환(B-C유 → LPG)을 통한 온실가스(CO2) 감축사업 | E88: 금산공영(합) | F88: 2015-05-01~2020-04-30 | G88: 1차 (2016-05-01~2016-05-01) | H88: =VLOOKUP(D88,'인증실적 비공개승인관리_국내'!$D:$K,6,FALSE) -> 2019-11-14 | I88: =VLOOKUP(D88,'인증실적 비공개승인관리_국내'!$D:$K,7,FALSE) -> 산업통상부 | J88: =VLOOKUP(D88,'인증실적 비공개승인관리_국내'!$D:$K,8,FALSE) -> 2022-06-02 | K88: =VLOOKUP(A88,'인증실적 비공개승인관리_국내'!$A:$N,8,FALSE) -> 보완요청 | L88: =LEFT(G88,FIND("차",G88)) -> 1차 | M88: =MID(G88,FINDB("(",G88),10) -> 2016-05-01 | N88: =LEFT(VLOOKUP(D88,'국내인증(ORS)'!O:BI,38,0),10) -> 2019-11-14 | O88: =IF(N88=#REF!,"O","X") -> #REF! | P88: 검토필요 | Q88: 보완요청 | R88: 사업자 | S88: 보완요청 | T88: 사업자 | U88: 5월 26일 | V88: KECM_이태준 | W88: 모니터링보고서 및 검증보고서 내 보안유지 필요부분 구체화 필요 | X88: X | Y88: X | Z88: X | AA88: O | AB88: O | AC88: X | AD88: X | AE88: 내부방침
A89: =D89&L89&M89 -> 한화제약(주) 스팀보일러 버너 연료전환(부생연료유 1호 → LPG)을 통한 온실가스(CO2) 감축사업1차2016-11-01 | B89: 87 | C89: 단일감축사업 | D89: 한화제약(주) 스팀보일러 버너 연료전환(부생연료유 1호 → LPG)을 통한 온실가스(CO2) 감축사업 | E89: 한화제약(주) | F89: 2014-11-01~2019-10-31 | G89: 1차 (2016-11-01~2016-11-01) | H89: =VLOOKUP(D89,'인증실적 비공개승인관리_국내'!$D:$K,6,FALSE) -> 2019-11-14 | I89: =VLOOKUP(D89,'인증실적 비공개승인관리_국내'!$D:$K,7,FALSE) -> 산업통상부 | J89: =VLOOKUP(D89,'인증실적 비공개승인관리_국내'!$D:$K,8,FALSE) -> 2022-06-02 | K89: =VLOOKUP(A89,'인증실적 비공개승인관리_국내'!$A:$N,8,FALSE) -> 보완요청 | L89: =LEFT(G89,FIND("차",G89)) -> 1차 | M89: =MID(G89,FINDB("(",G89),10) -> 2016-11-01 | N89: =LEFT(VLOOKUP(D89,'국내인증(ORS)'!O:BI,38,0),10) -> 2019-11-14 | O89: =IF(N89=#REF!,"O","X") -> #REF! | P89: 검토필요 | Q89: 보완요청 | R89: 사업자 | S89: 보완요청 | T89: 사업자 | U89: 5월 26일 | V89: KECM_이태준 | W89: 모니터링보고서 및 검증보고서 내 보안유지 필요부분 구체화 필요 | X89: X | Y89: X | Z89: X | AA89: O | AB89: O | AC89: X | AD89: X | AE89: 내부방침
A90: =D90&L90&M90 -> 보일러 연료전환(벙커C유 및 보일러 등유 -> LNG)을 통한 온실가스(CO2) 배출 감축 사업1차2014-06-01 | B90: 88 | C90: 단일감축사업 | D90: 보일러 연료전환(벙커C유 및 보일러 등유 -> LNG)을 통한 온실가스(CO2) 배출 감축 사업 | E90: (주)진유원 | F90: 2011-06-01~2016-05-31 | G90: 1차 (2014-06-01~2014-06-01) | H90: =VLOOKUP(D90,'인증실적 비공개승인관리_국내'!$D:$K,6,FALSE) -> 2019-11-13 | I90: =VLOOKUP(D90,'인증실적 비공개승인관리_국내'!$D:$K,7,FALSE) -> 산업통상부 | J90: =VLOOKUP(D90,'인증실적 비공개승인관리_국내'!$D:$K,8,FALSE) -> 2022-06-02 | K90: =VLOOKUP(A90,'인증실적 비공개승인관리_국내'!$A:$N,8,FALSE) -> 보완요청 | L90: =LEFT(G90,FIND("차",G90)) -> 1차 | M90: =MID(G90,FINDB("(",G90),10) -> 2014-06-01 | N90: =LEFT(VLOOKUP(D90,'국내인증(ORS)'!O:BI,38,0),10) -> 2019-11-13 | O90: =IF(N90=#REF!,"O","X") -> #REF! | P90: 검토필요 | Q90: 보완요청 | R90: 사업자 | S90: 보완요청 | T90: 사업자 | U90: 5월 26일 | V90: KECM_이태준 | W90: 모니터링보고서 및 검증보고서 내 보안유지 필요부분 구체화 필요 | X90: X | Y90: X | Z90: O | AA90: O | AB90: O | AC90: X | AD90: X | AE90: 내부방침
A91: =D91&L91&M91 -> 휴켐스 질산공장 N2O 감축사업(휴켐스 주식회사의 질산 공장 세곡에서 tail gas에 포한된 아산화질소를 촉매를 사용하여 제거하는 프로젝트)14차2019-02-17 | B91: 89 | C91: 단일감축사업 | D91: 휴켐스 질산공장 N2O 감축사업(휴켐스 주식회사의 질산 공장 세곡에서 tail gas에 포한된 아산화질소를 촉매를 사용하여 제거하는 프로젝트) | E91: 주식회사 에코아이 | F91: 2014-01-22~2021-01-21 | G91: 14차 (2019-02-17~2019-02-17) | H91: =VLOOKUP(D91,'인증실적 비공개승인관리_국내'!$D:$K,6,FALSE) -> 2022-06-16 | I91: =VLOOKUP(D91,'인증실적 비공개승인관리_국내'!$D:$K,7,FALSE) -> 산업통상부 | J91: =VLOOKUP(D91,'인증실적 비공개승인관리_국내'!$D:$K,8,FALSE) -> 2022-09-28 | K91: =VLOOKUP(A91,'인증실적 비공개승인관리_국내'!$A:$N,8,FALSE) -> 반려 | L91: =LEFT(G91,FIND("차",G91)) -> 14차 | M91: =MID(G91,FINDB("(",G91),10) -> 2019-02-17 | N91: =LEFT(VLOOKUP(D91,'국내인증(ORS)'!O:BI,38,0),10) -> 2020-11-11 | O91: =IF(N91=#REF!,"O","X") -> #REF! | P91: 검토필요 | Q91: 반려 | R91: 종결 | S91: 반려완료 | T91: 종결 | U91: 5월 26일 | V91: KECM_이태준 | W91: 사업자 반려 요청 | X91: X | Y91: O | Z91: X | AA91: O | AB91: O | AC91: X | AD91: X | AE91: 내부방침
A92: =D92&L92&M92 -> 산청토기와 버너교체 연료전환(c9+,LPG → LNG)를 통한 온실가스(CO2) 감축사업1차2015-10-01 | B92: 90 | C92: 단일감축사업 | D92: 산청토기와 버너교체 연료전환(c9+,LPG → LNG)를 통한 온실가스(CO2) 감축사업 | E92: (주)산청토기와 | F92: 2012-10-01~2017-09-30 | G92: 1차 (2015-10-01~2015-10-01) | H92: =VLOOKUP(D92,'인증실적 비공개승인관리_국내'!$D:$K,6,FALSE) -> 2019-09-29 | I92: =VLOOKUP(D92,'인증실적 비공개승인관리_국내'!$D:$K,7,FALSE) -> 산업통상부 | J92: =VLOOKUP(D92,'인증실적 비공개승인관리_국내'!$D:$K,8,FALSE) -> 2022-06-02 | K92: =VLOOKUP(A92,'인증실적 비공개승인관리_국내'!$A:$N,8,FALSE) -> 보완요청 | L92: =LEFT(G92,FIND("차",G92)) -> 1차 | M92: =MID(G92,FINDB("(",G92),10) -> 2015-10-01 | N92: =LEFT(VLOOKUP(D92,'국내인증(ORS)'!O:BI,38,0),10) -> 2019-09-29 | O92: =IF(N92=#REF!,"O","X") -> #REF! | P92: 검토필요 | Q92: 보완요청 | R92: 사업자 | S92: 보완요청 | T92: 사업자 | U92: 5월 26일 | V92: KECM_이태준 | W92: 모니터링보고서 및 검증보고서 내 보안유지 필요부분 구체화 필요 | X92: X | Y92: X | Z92: X | AA92: O | AB92: X | AC92: X | AD92: X | AE92: 내부방침
A93: =D93&L93&M93 -> 정암산업 버너 교체를 통한 연료전환 사업 (콘크리트 파일 생산)1차2015-11-01 | B93: 91 | C93: 단일감축사업 | D93: 정암산업 버너 교체를 통한 연료전환 사업 (콘크리트 파일 생산) | E93: 정암산업(주) | F93: 2011-11-01~2016-10-31 | G93: 1차 (2015-11-01~2015-11-01) | H93: =VLOOKUP(D93,'인증실적 비공개승인관리_국내'!$D:$K,6,FALSE) -> 2019-09-22 | I93: =VLOOKUP(D93,'인증실적 비공개승인관리_국내'!$D:$K,7,FALSE) -> 산업통상부 | J93: =VLOOKUP(D93,'인증실적 비공개승인관리_국내'!$D:$K,8,FALSE) -> 2022-06-02 | K93: =VLOOKUP(A93,'인증실적 비공개승인관리_국내'!$A:$N,8,FALSE) -> 보완요청 | L93: =LEFT(G93,FIND("차",G93)) -> 1차 | M93: =MID(G93,FINDB("(",G93),10) -> 2015-11-01 | N93: =LEFT(VLOOKUP(D93,'국내인증(ORS)'!O:BI,38,0),10) -> 2019-09-22 | O93: =IF(N93=#REF!,"O","X") -> #REF! | P93: 검토필요 | Q93: 보완요청 | R93: 사업자 | S93: 보완요청 | T93: 사업자 | U93: 5월 26일 | V93: KECM_이태준 | W93: 모니터링보고서 및 검증보고서 내 보안유지 필요부분 구체화 필요 | X93: X | Y93: X | Z93: X | AA93: O | AB93: O | AC93: X | AD93: X | AE93: 내부방침
A94: =D94&L94&M94 -> 정암산업 버너 교체를 통한 연료전환 사업 (아스콘 생산)1차2015-11-01 | B94: 92 | C94: 단일감축사업 | D94: 정암산업 버너 교체를 통한 연료전환 사업 (아스콘 생산) | E94: 정암산업(주) | F94: 2012-06-01~2017-05-31 | G94: 1차 (2015-11-01~2015-11-01) | H94: =VLOOKUP(D94,'인증실적 비공개승인관리_국내'!$D:$K,6,FALSE) -> 2019-09-22 | I94: =VLOOKUP(D94,'인증실적 비공개승인관리_국내'!$D:$K,7,FALSE) -> 산업통상부 | J94: =VLOOKUP(D94,'인증실적 비공개승인관리_국내'!$D:$K,8,FALSE) -> 2022-06-02 | K94: =VLOOKUP(A94,'인증실적 비공개승인관리_국내'!$A:$N,8,FALSE) -> 보완요청 | L94: =LEFT(G94,FIND("차",G94)) -> 1차 | M94: =MID(G94,FINDB("(",G94),10) -> 2015-11-01 | N94: =LEFT(VLOOKUP(D94,'국내인증(ORS)'!O:BI,38,0),10) -> 2019-09-22 | O94: =IF(N94=#REF!,"O","X") -> #REF! | P94: 검토필요 | Q94: 보완요청 | R94: 사업자 | S94: 보완요청 | T94: 사업자 | U94: 5월 26일 | V94: KECM_이태준 | W94: 모니터링보고서 및 검증보고서 내 보안유지 필요부분 구체화 필요 | X94: X | Y94: X | Z94: X | AA94: O | AB94: O | AC94: X | AD94: X | AE94: 내부방침
A95: =D95&L95&M95 -> 카프로 N2O 저감 사업7차2017-11-01 | B95: 93 | C95: 단일감축사업 | D95: 카프로 N2O 저감 사업 | E95: 주식회사 에코아이 | F95: 2011-06-09~2021-06-08 | G95: 7차 (2017-11-01~2017-11-01) | H95: =VLOOKUP(D95,'인증실적 비공개승인관리_국내'!$D:$K,6,FALSE) -> 2024-01-24 | I95: =VLOOKUP(D95,'인증실적 비공개승인관리_국내'!$D:$K,7,FALSE) -> 산업통상부 | J95: =VLOOKUP(D95,'인증실적 비공개승인관리_국내'!$D:$K,8,FALSE) -> 2024-06-17 | K95: =VLOOKUP(A95,'인증실적 비공개승인관리_국내'!$A:$N,8,FALSE) -> 반려 | L95: =LEFT(G95,FIND("차",G95)) -> 7차 | M95: =MID(G95,FINDB("(",G95),10) -> 2017-11-01 | N95: =LEFT(VLOOKUP(D95,'국내인증(ORS)'!O:BI,38,0),10) -> 2022-05-31 | O95: =IF(N95=#REF!,"O","X") -> #REF! | P95: 검토필요 | Q95: 반려 | R95: 종결 | S95: 반려완료 | T95: 종결 | U95: 5월 26일 | V95: KECM_이태준 | W95: 반려 완료 | X95: X | Y95: X | Z95: X | AA95: O | AB95: X | AC95: X | AD95: X | AE95: 내부방침
A96: =D96&L96&M96 -> 한국유에스지보랄 소성공정 연료전환(B-C유에서 LNG)을 통한 온실가스 감축사업1차2016-01-01 | B96: 94 | C96: 단일감축사업 | D96: 한국유에스지보랄 소성공정 연료전환(B-C유에서 LNG)을 통한 온실가스 감축사업 | E96: 크나우프석고보드 주식회사 | F96: 2012-09-01~2017-08-31 | G96: 1차 (2016-01-01~2016-01-01) | H96: =VLOOKUP(D96,'인증실적 비공개승인관리_국내'!$D:$K,6,FALSE) -> 2019-08-06 | I96: =VLOOKUP(D96,'인증실적 비공개승인관리_국내'!$D:$K,7,FALSE) -> 산업통상부 | J96: =VLOOKUP(D96,'인증실적 비공개승인관리_국내'!$D:$K,8,FALSE) -> 2022-06-02 | K96: =VLOOKUP(A96,'인증실적 비공개승인관리_국내'!$A:$N,8,FALSE) -> 보완요청 | L96: =LEFT(G96,FIND("차",G96)) -> 1차 | M96: =MID(G96,FINDB("(",G96),10) -> 2016-01-01 | N96: =LEFT(VLOOKUP(D96,'국내인증(ORS)'!O:BI,38,0),10) -> 2019-08-06 | O96: =IF(N96=#REF!,"O","X") -> #REF! | P96: 검토필요 | Q96: 보완요청 | R96: 사업자 | S96: 보완요청 | T96: 사업자 | U96: 5월 26일 | V96: KECM_이태준 | W96: 모니터링보고서 및 검증보고서 내 보안유지 필요부분 구체화 필요 | X96: X | Y96: X | Z96: X | AA96: O | AB96: O | AC96: X | AD96: X | AE96: 내부방침
... A107: =D107&L107&M107 -> 팜스코 중부공장 연료전환 (B-C유 >도시가스) 감축사업1차2008-12-17 | B107: 105 | C107: 단일감축사업 | D107: 팜스코 중부공장 연료전환 (B-C유 >도시가스) 감축사업 | E107: (주)팜스코 | F107: 2008-12-17~2018-12-16 | G107: 1차 (2008-12-17~2008-12-17) | H107: =VLOOKUP(D107,'인증실적 비공개승인관리_국내'!$D:$K,6,FALSE) -> 2019-01-21 | I107: =VLOOKUP(D107,'인증실적 비공개승인관리_국내'!$D:$K,7,FALSE) -> 산업통상부 | J107: =VLOOKUP(D107,'인증실적 비공개승인관리_국내'!$D:$K,8,FALSE) -> 2022-06-02 | K107: =VLOOKUP(A107,'인증실적 비공개승인관리_국내'!$A:$N,8,FALSE) -> 보완요청 | L107: =LEFT(G107,FIND("차",G107)) -> 1차 | M107: =MID(G107,FINDB("(",G107),10) -> 2008-12-17 | N107: =LEFT(VLOOKUP(D107,'국내인증(ORS)'!O:BI,38,0),10) -> 2019-01-21 | O107: =IF(N107=#REF!,"O","X") -> #REF! | P107: 검토필요 | Q107: 보완요청 | R107: 사업자 | S107: 보완요청 | T107: 사업자 | U107: 5월 26일 | V107: KECM_임하진 | W107: 보완 요청 필요(사유: 사업자 개인정보로 인해 비공개 신청) | X107: X | Y107: X | Z107: X | AA107: O | AB107: X | AC107: X | AD107: X | AE107: 개인정보보호
A108: =D108&L108&M108 -> 홍익콘크리트산업 연료전환(B-C유->도시가스) 감축사업(C-001)1차2011-08-17 | B108: 106 | C108: 프로그램감축사업 | D108: 홍익콘크리트산업 연료전환(B-C유->도시가스) 감축사업(C-001) | E108: (주)삼천리 | F108: 2011-08-17~2021-08-16 | G108: 1차 (2011-08-17~2011-08-17) | H108: =VLOOKUP(D108,'인증실적 비공개승인관리_국내'!$D:$K,6,FALSE) -> 2019-01-21 | I108: =VLOOKUP(D108,'인증실적 비공개승인관리_국내'!$D:$K,7,FALSE) -> 산업통상부 | J108: =VLOOKUP(D108,'인증실적 비공개승인관리_국내'!$D:$K,8,FALSE) -> 2022-10-19 | K108: =VLOOKUP(A108,'인증실적 비공개승인관리_국내'!$A:$N,8,FALSE) -> 보완요청 | L108: =LEFT(G108,FIND("차",G108)) -> 1차 | M108: =MID(G108,FINDB("(",G108),10) -> 2011-08-17 | N108: =LEFT(VLOOKUP(D108,'국내인증(ORS)'!O:BI,38,0),10) -> 2021-12-17 | O108: =IF(N108=#REF!,"O","X") -> #REF! | P108: 검토필요 | Q108: 보완요청 | R108: 사업자 | S108: 보완요청 | T108: 사업자 | U108: 10월 13일 | V108: 에코시안 | W108: 모니터링보고서 및 검증보고서 내 보안유지 필요부분 구체화 필요(사유: 사업자 개인정보로 인해 비공개 신청) | X108: X | Y108: X | Z108: X | AA108: X | AB108: X | AC108: X | AD108: X | AE108: 개인정보보호 | AF108: 사업명과 상이
A109: =D109&L109&M109 -> 삼화페인트공업 주식회사 연료전환 (B-C유 → 도시가스) 감축사업1차2008-12-04 | B109: 107 | C109: 단일감축사업 | D109: 삼화페인트공업 주식회사 연료전환 (B-C유 → 도시가스) 감축사업 | E109: 삼화페인트공업(주) | F109: 2008-12-04~2018-12-03 | G109: 1차 (2008-12-04~2008-12-04) | H109: =VLOOKUP(D109,'인증실적 비공개승인관리_국내'!$D:$K,6,FALSE) -> 2019-01-15 | I109: =VLOOKUP(D109,'인증실적 비공개승인관리_국내'!$D:$K,7,FALSE) -> 산업통상부 | J109: =VLOOKUP(D109,'인증실적 비공개승인관리_국내'!$D:$K,8,FALSE) -> 2022-06-02 | K109: =VLOOKUP(A109,'인증실적 비공개승인관리_국내'!$A:$N,8,FALSE) -> 보완요청 | L109: =LEFT(G109,FIND("차",G109)) -> 1차 | M109: =MID(G109,FINDB("(",G109),10) -> 2008-12-04 | N109: =LEFT(VLOOKUP(D109,'국내인증(ORS)'!O:BI,38,0),10) -> 2019-01-15 | O109: =IF(N109=#REF!,"O","X") -> #REF! | P109: 검토필요 | Q109: 보완요청 | R109: 사업자 | S109: 보완요청 | T109: 사업자 | U109: 5월 26일 | V109: KECM_임하진 | W109: 보완 요청 필요(사유: 사업자 개인정보로 인해 비공개 신청) | X109: X | Y109: X | Z109: X | AA109: O | AB109: X | AC109: X | AD109: X | AE109: 개인정보보호
A110: =D110&L110&M110 -> 선호피엔에스 연료전환 (B-B유 -> 도시가스) 감축사업1차2007-02-13 | B110: 108 | C110: 단일감축사업 | D110: 선호피엔에스 연료전환 (B-B유 -> 도시가스) 감축사업 | E110: 선호피엔에스 | F110: 2007-02-13~2017-02-12 | G110: 1차 (2007-02-13~2007-02-13) | H110: =VLOOKUP(D110,'인증실적 비공개승인관리_국내'!$D:$K,6,FALSE) -> 2019-01-15 | I110: =VLOOKUP(D110,'인증실적 비공개승인관리_국내'!$D:$K,7,FALSE) -> 산업통상부 | J110: =VLOOKUP(D110,'인증실적 비공개승인관리_국내'!$D:$K,8,FALSE) -> 2022-06-02 | K110: =VLOOKUP(A110,'인증실적 비공개승인관리_국내'!$A:$N,8,FALSE) -> 보완요청 | L110: =LEFT(G110,FIND("차",G110)) -> 1차 | M110: =MID(G110,FINDB("(",G110),10) -> 2007-02-13 | N110: =LEFT(VLOOKUP(D110,'국내인증(ORS)'!O:BI,38,0),10) -> 2019-01-15 | O110: =IF(N110=#REF!,"O","X") -> #REF! | P110: 검토필요 | Q110: 보완요청 | R110: 사업자 | S110: 보완요청 | T110: 사업자 | U110: 5월 26일 | V110: KECM_임하진 | W110: 보완 요청 필요(사유: 사업자 개인정보로 인해 비공개 신청) | X110: X | Y110: X | Z110: O | AA110: O | AB110: X | AC110: X | AD110: X | AE110: 개인정보보호
A111: =D111&L111&M111 -> 동인신철공업 주식회사 연료전환 (B-C유 -> 도시가스) 감축사업1차2008-03-20 | B111: 109 | C111: 단일감축사업 | D111: 동인신철공업 주식회사 연료전환 (B-C유 -> 도시가스) 감축사업 | E111: 동인신철공업(주) | F111: 2008-03-20~2018-03-19 | G111: 1차 (2008-03-20~2008-03-20) | H111: =VLOOKUP(D111,'인증실적 비공개승인관리_국내'!$D:$K,6,FALSE) -> 2019-01-15 | I111: =VLOOKUP(D111,'인증실적 비공개승인관리_국내'!$D:$K,7,FALSE) -> 산업통상부 | J111: =VLOOKUP(D111,'인증실적 비공개승인관리_국내'!$D:$K,8,FALSE) -> 2022-06-02 | K111: =VLOOKUP(A111,'인증실적 비공개승인관리_국내'!$A:$N,8,FALSE) -> 보완요청 | L111: =LEFT(G111,FIND("차",G111)) -> 1차 | M111: =MID(G111,FINDB("(",G111),10) -> 2008-03-20 | N111: =LEFT(VLOOKUP(D111,'국내인증(ORS)'!O:BI,38,0),10) -> 2019-01-15 | O111: =IF(N111=#REF!,"O","X") -> #REF! | P111: 검토필요 | Q111: 보완요청 | R111: 사업자 | S111: 보완요청 | T111: 사업자 | U111: 5월 26일 | V111: KECM_임하진 | W111: 보완 요청 필요(사유: 사업자 개인정보로 인해 비공개 신청) | X111: X | Y111: X | Z111: X | AA111: O | AB111: X | AC111: X | AD111: X | AE111: 개인정보보호
A112: =D112&L112&M112 -> 영덕물산 연료전환(B-C유-> 도시가스) 감축사업1차2007-09-10 | B112: 110 | C112: 단일감축사업 | D112: 영덕물산 연료전환(B-C유-> 도시가스) 감축사업 | E112: 영덕산업(주) | F112: 2007-09-10~2014-12-24 | G112: 1차 (2007-09-10~2007-09-10) | H112: =VLOOKUP(D112,'인증실적 비공개승인관리_국내'!$D:$K,6,FALSE) -> 2019-01-15 | I112: =VLOOKUP(D112,'인증실적 비공개승인관리_국내'!$D:$K,7,FALSE) -> 산업통상부 | J112: =VLOOKUP(D112,'인증실적 비공개승인관리_국내'!$D:$K,8,FALSE) -> 2022-06-02 | K112: =VLOOKUP(A112,'인증실적 비공개승인관리_국내'!$A:$N,8,FALSE) -> 보완요청 | L112: =LEFT(G112,FIND("차",G112)) -> 1차 | M112: =MID(G112,FINDB("(",G112),10) -> 2007-09-10 | N112: =LEFT(VLOOKUP(D112,'국내인증(ORS)'!O:BI,38,0),10) -> 2019-01-15 | O112: =IF(N112=#REF!,"O","X") -> #REF! | P112: 검토필요 | Q112: 보완요청 | R112: 사업자 | S112: 보완요청 | T112: 사업자 | U112: 5월 26일 | V112: KECM_임하진 | W112: 보완 요청 필요(사유: 사업자 개인정보로 인해 비공개 신청) | X112: X | Y112: X | Z112: O | AA112: O | AB112: X | AC112: X | AD112: X | AE112: 개인정보보호
A113: =D113&L113&M113 -> 제천 장락 주공 1단지 아파트 연료전환을 통한 온실가스 감축사업 1차2010-05-01 | B113: 111 | C113: 단일감축사업 | D113: 제천 장락 주공 1단지 아파트 연료전환을 통한 온실가스 감축사업 | E113: 한국토지주택공사 | F113: 2008-12-23~2018-12-22 | G113: 1차 (2010-05-01~2010-05-01) | H113: =VLOOKUP(D113,'인증실적 비공개승인관리_국내'!$D:$K,6,FALSE) -> 2025-08-06 | I113: =VLOOKUP(D113,'인증실적 비공개승인관리_국내'!$D:$K,7,FALSE) -> 산업통상부 | J113: =VLOOKUP(D113,'인증실적 비공개승인관리_국내'!$D:$K,8,FALSE) -> 2025-08-06 | K113: =VLOOKUP(A113,'인증실적 비공개승인관리_국내'!$A:$N,8,FALSE) -> 보완완료 | L113: =LEFT(G113,FIND("차",G113)) -> 1차 | M113: =MID(G113,FINDB("(",G113),10) -> 2010-05-01 | N113: =LEFT(VLOOKUP(D113,'국내인증(ORS)'!O:BI,38,0),10) -> 2025-04-15 | O113: =IF(N113=#REF!,"O","X") -> #REF! | P113: 검토필요 | Q113: 보완요청 | R113: 사업자 | S113: 반려요청 | T113: 검토반 | U113: 45877 | V113: 에코시안_남혜원 | W113: 모니터링보고서 및 검증보고서에 대한 정보 비공개 신청을 철회합니다. | X113: X | Y113: X | Z113: X | AA113: O | AB113: X | AC113: X | AD113: X | AE113: 내부방침
A114: =D114&L114&M114 -> 서울 월계 주공1단지 아파트 연료전환을 통한 온실가스 감축사업1차2010-05-01 | B114: 112 | C114: 단일감축사업 | D114: 서울 월계 주공1단지 아파트 연료전환을 통한 온실가스 감축사업 | E114: 한국토지주택공사 | F114: 2008-03-01~2018-02-28 | G114: 1차 (2010-05-01~2010-05-01) | H114: =VLOOKUP(D114,'인증실적 비공개승인관리_국내'!$D:$K,6,FALSE) -> 2025-10-15 | I114: =VLOOKUP(D114,'인증실적 비공개승인관리_국내'!$D:$K,7,FALSE) -> 산업통상부 | J114: =VLOOKUP(D114,'인증실적 비공개승인관리_국내'!$D:$K,8,FALSE) -> 2025-10-14 | K114: =VLOOKUP(A114,'인증실적 비공개승인관리_국내'!$A:$N,8,FALSE) -> 보완완료 | L114: =LEFT(G114,FIND("차",G114)) -> 1차 | M114: =MID(G114,FINDB("(",G114),10) -> 2010-05-01 | N114: =LEFT(VLOOKUP(D114,'국내인증(ORS)'!O:BI,38,0),10) -> 2018-12-03 | O114: =IF(N114=#REF!,"O","X") -> #REF! | P114: 검토필요 | Q114: 보완요청 | R114: 사업자 | S114: 반려요청 | T114: 검토반 | U114: 45946 | V114: KECM | W114: 모니터링보고서 및 검증보고서에 대한 정보 비공개 신청을 철회합니다. | X114: X | Y114: X | Z114: X | AA114: O | AB114: X | AC114: X | AD114: X | AE114: 내부방침
A115: =D115&L115&M115 -> 서울 우면아파트 연료전환을 통한 온실가스 감축사업1차2010-05-01 | B115: 113 | C115: 단일감축사업 | D115: 서울 우면아파트 연료전환을 통한 온실가스 감축사업 | E115: 한국토지주택공사 | F115: 2007-09-11~2017-09-10 | G115: 1차 (2010-05-01~2010-05-01) | H115: =VLOOKUP(D115,'인증실적 비공개승인관리_국내'!$D:$K,6,FALSE) -> 2025-10-15 | I115: =VLOOKUP(D115,'인증실적 비공개승인관리_국내'!$D:$K,7,FALSE) -> 산업통상부 | J115: =VLOOKUP(D115,'인증실적 비공개승인관리_국내'!$D:$K,8,FALSE) -> 2025-10-14 | K115: =VLOOKUP(A115,'인증실적 비공개승인관리_국내'!$A:$N,8,FALSE) -> 보완완료 | L115: =LEFT(G115,FIND("차",G115)) -> 1차 | M115: =MID(G115,FINDB("(",G115),10) -> 2010-05-01 | N115: =LEFT(VLOOKUP(D115,'국내인증(ORS)'!O:BI,38,0),10) -> 2018-12-03 | O115: =IF(N115=#REF!,"O","X") -> #REF! | P115: 검토필요 | Q115: 보완요청 | R115: 사업자 | S115: 반려요청 | T115: 검토반 | U115: 45946 | V115: KECM_임하진 | W115: 모니터링보고서 및 검증보고서에 대한 정보 비공개 신청을 철회합니다. | X115: X | Y115: X | Z115: O | AA115: O | AB115: X | AC115: X | AD115: X | AE115: 내부방침
A116: =D116&L116&M116 -> 서울 번동 주공 5단지 아파트 연료전환을 통한 온실가스 감축사업1차2010-05-01 | B116: 114 | C116: 단일감축사업 | D116: 서울 번동 주공 5단지 아파트 연료전환을 통한 온실가스 감축사업 | E116: 한국토지주택공사 | F116: 2008-02-29~2018-02-28 | G116: 1차 (2010-05-01~2010-05-01) | H116: =VLOOKUP(D116,'인증실적 비공개승인관리_국내'!$D:$K,6,FALSE) -> 2025-10-15 | I116: =VLOOKUP(D116,'인증실적 비공개승인관리_국내'!$D:$K,7,FALSE) -> 산업통상부 | J116: =VLOOKUP(D116,'인증실적 비공개승인관리_국내'!$D:$K,8,FALSE) -> 2025-10-14 | K116: =VLOOKUP(A116,'인증실적 비공개승인관리_국내'!$A:$N,8,FALSE) -> 보완완료 | L116: =LEFT(G116,FIND("차",G116)) -> 1차 | M116: =MID(G116,FINDB("(",G116),10) -> 2010-05-01 | N116: =LEFT(VLOOKUP(D116,'국내인증(ORS)'!O:BI,38,0),10) -> 2018-12-03 | O116: =IF(N116=#REF!,"O","X") -> #REF! | P116: 검토필요 | Q116: 보완요청 | R116: 사업자 | S116: 반려요청 | T116: 검토반 | U116: 45946 | V116: KECM_임하진 | W116: 모니터링보고서 및 검증보고서에 대한 정보 비공개 신청을 철회합니다. | X116: X | Y116: X | Z116: O | AA116: O | AB116: X | AC116: X | AD116: X | AE116: 내부방침
A117: =D117&L117&M117 -> 서울 번동 주공3단지 아파트연료전환을 통한 온실가스 감축사업1차2010-05-01 | B117: 115 | C117: 단일감축사업 | D117: 서울 번동 주공3단지 아파트연료전환을 통한 온실가스 감축사업 | E117: 한국토지주택공사 | F117: 2008-03-01~2018-02-28 | G117: 1차 (2010-05-01~2010-05-01) | H117: =VLOOKUP(D117,'인증실적 비공개승인관리_국내'!$D:$K,6,FALSE) -> 2025-10-15 | I117: =VLOOKUP(D117,'인증실적 비공개승인관리_국내'!$D:$K,7,FALSE) -> 산업통상부 | J117: =VLOOKUP(D117,'인증실적 비공개승인관리_국내'!$D:$K,8,FALSE) -> 2025-10-14 | K117: =VLOOKUP(A117,'인증실적 비공개승인관리_국내'!$A:$N,8,FALSE) -> 보완완료 | L117: =LEFT(G117,FIND("차",G117)) -> 1차 | M117: =MID(G117,FINDB("(",G117),10) -> 2010-05-01 | N117: =LEFT(VLOOKUP(D117,'국내인증(ORS)'!O:BI,38,0),10) -> 2018-12-03 | O117: =IF(N117=#REF!,"O","X") -> #REF! | P117: 검토필요 | Q117: 보완요청 | R117: 사업자 | S117: 반려요청 | T117: 검토반 | U117: 45946 | V117: KECM_임하진 | W117: 모니터링보고서 및 검증보고서에 대한 정보 비공개 신청을 철회합니다. | X117: X | Y117: X | Z117: O | AA117: O | AB117: X | AC117: X | AD117: X | AE117: 내부방침
A118: =D118&L118&M118 -> 서울 번동 주공2단지 아파트 연료전환을 통한 온실가스 감축사업1차2010-05-01 | B118: 116 | C118: 단일감축사업 | D118: 서울 번동 주공2단지 아파트 연료전환을 통한 온실가스 감축사업 | E118: 한국토지주택공사 | F118: 2008-03-03~2018-03-02 | G118: 1차 (2010-05-01~2010-05-01) | H118: =VLOOKUP(D118,'인증실적 비공개승인관리_국내'!$D:$K,6,FALSE) -> 2025-10-15 | I118: =VLOOKUP(D118,'인증실적 비공개승인관리_국내'!$D:$K,7,FALSE) -> 산업통상부 | J118: =VLOOKUP(D118,'인증실적 비공개승인관리_국내'!$D:$K,8,FALSE) -> 2025-10-14 | K118: =VLOOKUP(A118,'인증실적 비공개승인관리_국내'!$A:$N,8,FALSE) -> 보완완료 | L118: =LEFT(G118,FIND("차",G118)) -> 1차 | M118: =MID(G118,FINDB("(",G118),10) -> 2010-05-01 | N118: =LEFT(VLOOKUP(D118,'국내인증(ORS)'!O:BI,38,0),10) -> 2018-12-03 | O118: =IF(N118=#REF!,"O","X") -> #REF! | P118: 검토필요 | Q118: 보완요청 | R118: 사업자 | S118: 반려요청 | T118: 검토반 | U118: 45946 | V118: KECM_임하진 | W118: 모니터링보고서 및 검증보고서에 대한 정보 비공개 신청을 철회합니다. | X118: X | Y118: X | Z118: O | AA118: O | AB118: X | AC118: X | AD118: X | AE118: 내부방침
A119: =D119&L119&M119 -> 부천 춘의단지 아파트 연료전환을 통한 온실가스 감축사업 1차2010-05-01 | B119: 117 | C119: 단일감축사업 | D119: 부천 춘의단지 아파트 연료전환을 통한 온실가스 감축사업 | E119: 한국토지주택공사 | F119: 2009-09-30~2019-09-29 | G119: 1차 (2010-05-01~2010-05-01) | H119: =VLOOKUP(D119,'인증실적 비공개승인관리_국내'!$D:$K,6,FALSE) -> 2025-10-15 | I119: =VLOOKUP(D119,'인증실적 비공개승인관리_국내'!$D:$K,7,FALSE) -> 산업통상부 | J119: =VLOOKUP(D119,'인증실적 비공개승인관리_국내'!$D:$K,8,FALSE) -> 2025-10-14 | K119: =VLOOKUP(A119,'인증실적 비공개승인관리_국내'!$A:$N,8,FALSE) -> 보완완료 | L119: =LEFT(G119,FIND("차",G119)) -> 1차 | M119: =MID(G119,FINDB("(",G119),10) -> 2010-05-01 | N119: =LEFT(VLOOKUP(D119,'국내인증(ORS)'!O:BI,38,0),10) -> 2025-06-19 | O119: =IF(N119=#REF!,"O","X") -> #REF! | P119: 검토필요 | Q119: 보완요청 | R119: 사업자 | S119: 반려요청 | T119: 검토반 | U119: 45946 | V119: KECM_임하진 | W119: 모니터링보고서 및 검증보고서에 대한 정보 비공개 신청을 철회합니다. | X119: X | Y119: X | Z119: O | AA119: O | AB119: X | AC119: X | AD119: X | AE119: 내부방침
A120: =D120&L120&M120 -> 광주 하남 주공 1차 아파트 연료전환을 통한 온실가스 감축사업1차2011-09-02 | B120: 118 | C120: 단일감축사업 | D120: 광주 하남 주공 1차 아파트 연료전환을 통한 온실가스 감축사업 | E120: 한국토지주택공사 | F120: 2011-09-02~2018-09-01 | G120: 1차 (2011-09-02~2011-09-02) | H120: =VLOOKUP(D120,'인증실적 비공개승인관리_국내'!$D:$K,6,FALSE) -> 2025-10-15 | I120: =VLOOKUP(D120,'인증실적 비공개승인관리_국내'!$D:$K,7,FALSE) -> 산업통상부 | J120: =VLOOKUP(D120,'인증실적 비공개승인관리_국내'!$D:$K,8,FALSE) -> 2025-10-14 | K120: =VLOOKUP(A120,'인증실적 비공개승인관리_국내'!$A:$N,8,FALSE) -> 보완완료 | L120: =LEFT(G120,FIND("차",G120)) -> 1차 | M120: =MID(G120,FINDB("(",G120),10) -> 2011-09-02 | N120: =LEFT(VLOOKUP(D120,'국내인증(ORS)'!O:BI,38,0),10) -> 2025-07-03 | O120: =IF(N120=#REF!,"O","X") -> #REF! | P120: 검토필요 | Q120: 보완요청 | R120: 사업자 | S120: 반려요청 | T120: 검토반 | U120: 45946 | V120: KECM_임하진 | W120: 모니터링보고서 및 검증보고서에 대한 정보 비공개 신청을 철회합니다. | X120: X | Y120: X | Z120: O | AA120: O | AB120: X | AC120: X | AD120: X | AE120: 내부방침
A121: =D121&L121&M121 -> 광주 우산 주공 3단지 아파트 연료전환을 통한 온실가스 감축사업1차2011-09-01 | B121: 119 | C121: 단일감축사업 | D121: 광주 우산 주공 3단지 아파트 연료전환을 통한 온실가스 감축사업 | E121: 한국토지주택공사 | F121: 2011-09-01~2018-08-31 | G121: 1차 (2011-09-01~2011-09-01) | H121: =VLOOKUP(D121,'인증실적 비공개승인관리_국내'!$D:$K,6,FALSE) -> 2025-10-15 | I121: =VLOOKUP(D121,'인증실적 비공개승인관리_국내'!$D:$K,7,FALSE) -> 산업통상부 | J121: =VLOOKUP(D121,'인증실적 비공개승인관리_국내'!$D:$K,8,FALSE) -> 2025-10-14 | K121: =VLOOKUP(A121,'인증실적 비공개승인관리_국내'!$A:$N,8,FALSE) -> 보완완료 | L121: =LEFT(G121,FIND("차",G121)) -> 1차 | M121: =MID(G121,FINDB("(",G121),10) -> 2011-09-01 | N121: =LEFT(VLOOKUP(D121,'국내인증(ORS)'!O:BI,38,0),10) -> 2018-05-24 | O121: =IF(N121=#REF!,"O","X") -> #REF! | P121: 검토필요 | Q121: 보완요청 | R121: 사업자 | S121: 반려요청 | T121: 검토반 | U121: 45946 | V121: KECM_임하진 | W121: 모니터링보고서 및 검증보고서에 대한 정보 비공개 신청을 철회합니다. | X121: X | Y121: X | Z121: O | AA121: O | AB121: X | AC121: X | AD121: X | AE121: 내부방침
...

Sheet (비공개)국외평가
A1: 번호 | B1: 사업유형 | C1: 사업명 | D1: 업체명 | E1: 진행상태 | F1: 정보비공개 신청일 | G1: 사업 신청일 | H1: 평가 가능 여부 | I1: 관장기관 | J1: 처리일 | K1: 처리상태 | L1: 현재 상태 | M1: 검토대상 | N1: 진행상태 | O1: 현 위치 | P1: 검토대상 | Q1: 진행상태 | R1: 현 위치 | S1: 업데이트 | T1: 담당자 | U1: 비고 | V1: 권리 | W1: 대외비 자료 | X1: 계약서류 | Y1: 연료 사용량 | Z1: 공정 도식도 | AA1: 영업비밀 | AB1: 내규방침 제출여부 | AC1: 비공개 신청사유 | AD1: 특이사항
A2: 1 | B2: 단일감축사업 | C2: 아프리카 고효율 쿡스토브 보급 PoA 사업 : CPA0010(케냐) | D2: 씨이알피디(주) | E2: 반려 | F2: 2022-08-16 | G2: =LEFT(VLOOKUP(C2,'국외평가(ORS)'!A:AX,34,0),10) -> 2020-08-07 | H2: =IF(G2=F2,"O","X") -> X | I2: 산업통상자원부 | J2: 2022-09-05 | K2: =VLOOKUP(C2,'국외평가(ORS)'!P:AE, 16, 0) -> [보완1차]착수신고 2021-10-20 | L2: =VLOOKUP(C2, '국외평가(ORS)'!A:AX, 2, 0) -> 승인 | M2: 검토필요 | N2: 반려 | O2: 종결 | P2: =IF(AND(E2<>"반려", L2<>"반려"),"검토가능","") | Q2: 반려완료 | R2: 종결 | S2: 10월 13일 | T2: 에코시안_기샛별 | U2: 사업자 반려 요청 | AC2: 내부방침
A3: 2 | B3: 단일감축사업 | C3: 아프리카 고효율 쿡스토브 보급 PoA 사업 : CPA0009(케냐) | D3: 씨이알피디(주) | E3: 반려 | F3: 2022-09-06 | G3: =LEFT(VLOOKUP(C3,'국외평가(ORS)'!A:AX,34,0),10) -> 2020-08-07 | H3: =IF(G3=F3,"O","X") -> X | I3: 산업통상자원부 | J3: 2022-09-14 | K3: =VLOOKUP(C3,'국외평가(ORS)'!P:AE, 16, 0) -> [보완1차]착수신고 2021-10-20 | L3: =VLOOKUP(C3, '국외평가(ORS)'!A:AX, 2, 0) -> 승인 | M3: 검토필요 | N3: 반려 | O3: 종결 | P3: =IF(AND(E3<>"반려", L3<>"반려"),"검토가능","") | Q3: 반려완료 | R3: 종결 | S3: 10월 13일 | T3: 에코시안_기샛별 | U3: 사업자 반려 요청 | AC3: 내부방침
A4: 3 | B4: 단일감축사업 | C4: 아프리카 고효율 쿡스토브 보급 PoA 사업 : CPA0008(케냐) | D4: 씨이알피디(주) | E4: 반려 | F4: 2022-09-06 | G4: =LEFT(VLOOKUP(C4,'국외평가(ORS)'!A:AX,34,0),10) -> 2020-08-07 | H4: =IF(G4=F4,"O","X") -> X | I4: 산업통상자원부 | J4: 2022-09-14 | K4: =VLOOKUP(C4,'국외평가(ORS)'!P:AE, 16, 0) -> [보완1차]착수신고 2021-10-20 | L4: =VLOOKUP(C4, '국외평가(ORS)'!A:AX, 2, 0) -> 승인 | M4: 검토필요 | N4: 반려 | O4: 종결 | P4: =IF(AND(E4<>"반려", L4<>"반려"),"검토가능","") | Q4: 반려완료 | R4: 종결 | S4: 10월 13일 | T4: 에코시안_기샛별 | U4: 사업자 반려 요청 | AC4: 내부방침
A5: 4 | B5: 단일감축사업 | C5: 아프리카 고효율 쿡스토브 보급 PoA 사업 : CPA 00012(나이지리아)(한국 지원) | D5: 씨이알피디(주) | E5: 반려 | F5: 2022-09-06 | G5: =LEFT(VLOOKUP(C5,'국외평가(ORS)'!A:AX,34,0),10) -> 2020-04-28 | H5: =IF(G5=F5,"O","X") -> X | I5: 산업통상자원부 | J5: 2022-09-14 | K5: =VLOOKUP(C5,'국외평가(ORS)'!P:AE, 16, 0) -> [보완1차]착수신고 2021-10-20 | L5: =VLOOKUP(C5, '국외평가(ORS)'!A:AX, 2, 0) -> 승인 | M5: 검토필요 | N5: 반려 | O5: 종결 | P5: =IF(AND(E5<>"반려", L5<>"반려"),"검토가능","") | Q5: 반려완료 | R5: 종결 | S5: 10월 13일 | T5: 에코시안_기샛별 | U5: 사업자 반려 요청 | AC5: 내부방침
A6: 5 | B6: 단일감축사업 | C6: 아프리카 고효율 쿡스토브 보급 PoA 사업 : CPA 00011(나이지리아)(한국 지원) | D6: 씨이알피디(주) | E6: 반려 | F6: 2022-09-06 | G6: =LEFT(VLOOKUP(C6,'국외평가(ORS)'!A:AX,34,0),10) -> 2020-04-28 | H6: =IF(G6=F6,"O","X") -> X | I6: 산업통상자원부 | J6: 2022-09-14 | K6: =VLOOKUP(C6,'국외평가(ORS)'!P:AE, 16, 0) -> [보완1차]착수신고 2021-10-20 | L6: =VLOOKUP(C6, '국외평가(ORS)'!A:AX, 2, 0) -> 승인 | M6: 검토필요 | N6: 반려 | O6: 종결 | P6: =IF(AND(E6<>"반려", L6<>"반려"),"검토가능","") | Q6: 반려완료 | R6: 종결 | S6: 10월 13일 | T6: 에코시안_기샛별 | U6: 사업자 반려 요청 | AC6: 내부방침
A7: 6 | B7: 단일감축사업 | C7: 아프리카 고효율 쿡스토브 보급 PoA 사업 : CPA 00010(나이지리아)(한국 지원) | D7: 씨이알피디(주) | E7: 반려 | F7: 2022-09-06 | G7: =LEFT(VLOOKUP(C7,'국외평가(ORS)'!A:AX,34,0),10) -> 2020-04-28 | H7: =IF(G7=F7,"O","X") -> X | I7: 산업통상자원부 | J7: 2022-09-14 | K7: =VLOOKUP(C7,'국외평가(ORS)'!P:AE, 16, 0) -> [보완1차]착수신고 2021-10-20 | L7: =VLOOKUP(C7, '국외평가(ORS)'!A:AX, 2, 0) -> 승인 | M7: 검토필요 | N7: 반려 | O7: 종결 | P7: =IF(AND(E7<>"반려", L7<>"반려"),"검토가능","") | Q7: 반려완료 | R7: 종결 | S7: 10월 13일 | T7: 에코시안_기샛별 | U7: 사업자 반려 요청 | AC7: 내부방침
A8: 7 | B8: 단일감축사업 | C8: 아프리카 고효율 쿡스토브 보급 PoA 사업 : CPA 00009(가나)(한국 지원) | D8: 씨이알피디(주) | E8: 반려 | F8: 2022-09-06 | G8: =LEFT(VLOOKUP(C8,'국외평가(ORS)'!A:AX,34,0),10) -> 2020-03-09 | H8: =IF(G8=F8,"O","X") -> X | I8: 산업통상자원부 | J8: 2022-09-14 | K8: =VLOOKUP(C8,'국외평가(ORS)'!P:AE, 16, 0) -> [보완1차]착수신고 2021-10-20 | L8: =VLOOKUP(C8, '국외평가(ORS)'!A:AX, 2, 0) -> 승인 | M8: 검토필요 | N8: 반려 | O8: 종결 | P8: =IF(AND(E8<>"반려", L8<>"반려"),"검토가능","") | Q8: 반려완료 | R8: 종결 | S8: 10월 13일 | T8: 에코시안_기샛별 | U8: 사업자 반려 요청 | AC8: 내부방침
A9: 8 | B9: 단일감축사업 | C9: 아프리카 고효율 쿡스토브 보급 PoA 사업 : CPA 00008(가나)(한국 지원) | D9: 씨이알피디(주) | E9: 반려 | F9: 2022-09-06 | G9: =LEFT(VLOOKUP(C9,'국외평가(ORS)'!A:AX,34,0),10) -> 2020-03-09 | H9: =IF(G9=F9,"O","X") -> X | I9: 산업통상자원부 | J9: 2022-09-14 | K9: =VLOOKUP(C9,'국외평가(ORS)'!P:AE, 16, 0) -> [보완1차]착수신고 2021-10-20 | L9: =VLOOKUP(C9, '국외평가(ORS)'!A:AX, 2, 0) -> 승인 | M9: 검토필요 | N9: 반려 | O9: 종결 | P9: =IF(AND(E9<>"반려", L9<>"반려"),"검토가능","") | Q9: 반려완료 | R9: 종결 | S9: 10월 13일 | T9: 에코시안_기샛별 | U9: 사업자 반려 요청 | AC9: 내부방침
A10: 9 | B10: 단일감축사업 | C10: 아프리카 고효율 쿡스토브 보급 PoA 사업 : CPA 00007(가나)(한국 지원) | D10: 씨이알피디(주) | E10: 반려 | F10: 2022-09-06 | G10: =LEFT(VLOOKUP(C10,'국외평가(ORS)'!A:AX,34,0),10) -> 2020-03-09 | H10: =IF(G10=F10,"O","X") -> X | I10: 산업통상자원부 | J10: 2022-09-14 | K10: =VLOOKUP(C10,'국외평가(ORS)'!P:AE, 16, 0) -> [보완1차]착수신고 2021-10-20 | L10: =VLOOKUP(C10, '국외평가(ORS)'!A:AX, 2, 0) -> 승인 | M10: 검토필요 | N10: 반려 | O10: 종결 | P10: =IF(AND(E10<>"반려", L10<>"반려"),"검토가능","") | Q10: 반려완료 | R10: 종결 | S10: 10월 13일 | T10: 에코시안_기샛별 | U10: 사업자 반려 요청 | AC10: 내부방침
A11: 10 | B11: 단일감축사업 | C11: 인도 청정에너지 기기 보급 사업 (PoA 9181-CPA 22) | D11: 클리어스카이파트너스 | E11: 보완요청 | F11: 2020-12-10 | G11: =LEFT(VLOOKUP(C11,'국외평가(ORS)'!A:AX,34,0),10) -> 2020-04-07 | H11: =IF(G11=F11,"O","X") -> X | I11: 산업통상자원부 | J11: 2022-10-19 | K11: =VLOOKUP(C11,'국외평가(ORS)'!P:AE, 16, 0) -> [보완2차]착수신고 2022-10-16 | L11: =VLOOKUP(C11, '국외평가(ORS)'!A:AX, 2, 0) -> 승인 | M11: 검토필요 | N11: 보완요청 | O11: 사업자 | P11: =IF(AND(E11<>"반려", L11<>"반려"),"검토가능","") -> 검토가능 | Q11: 보완요청 | R11: 사업자 | S11: 10월 13일 | T11: 에코시안 | U11: 보완 요청 필요(사유: CPA 30번 사유와 동일) (CSP 보완3차) 최종사용자 소유 운영 입증 서류 (Verification)에는 개인정보가 포함되어 있으므로 비공개 부탁드립니다. (CSP) PoA 9181 CPA19-30 사업계획서_2020.12에는 영업기밀사항등이 포함되어 있으므로 비공개 부탁드립니다. * 승인가능하나, 신청서 오류로 보완요청 필요 | AC11: 업체정보보호(업무상 비밀)
A12: 11 | B12: 단일감축사업 | C12: 인도 청정에너지 기기 보급 사업 (PoA 9181-CPA 20) | D12: 클리어스카이파트너스 | E12: 보완요청 | F12: 2020-12-10 | G12: =LEFT(VLOOKUP(C12,'국외평가(ORS)'!A:AX,34,0),10) -> 2020-04-07 | H12: =IF(G12=F12,"O","X") -> X | I12: 산업통상자원부 | J12: 2022-10-19 | K12: =VLOOKUP(C12,'국외평가(ORS)'!P:AE, 16, 0) -> [보완1차]착수신고 2022-10-16 | L12: =VLOOKUP(C12, '국외평가(ORS)'!A:AX, 2, 0) -> 승인 | M12: 검토필요 | N12: 보완요청 | O12: 사업자 | P12: =IF(AND(E12<>"반려", L12<>"반려"),"검토가능","") -> 검토가능 | Q12: 보완요청 | R12: 사업자 | S12: 10월 13일 | T12: 에코시안 | U12: 보완 요청 필요(CPA 22번 사유와 동일) | AC12: 업체정보보호(업무상 비밀)
A13: 12 | B13: 단일감축사업 | C13: 인도 청정에너지 기기 보급 사업 (PoA 9181-CPA 19) | D13: 클리어스카이파트너스 | E13: 보완요청 | F13: 2020-12-10 | G13: =LEFT(VLOOKUP(C13,'국외평가(ORS)'!A:AX,34,0),10) -> 2020-04-07 | H13: =IF(G13=F13,"O","X") -> X | I13: 산업통상자원부 | J13: 2022-10-19 | K13: =VLOOKUP(C13,'국외평가(ORS)'!P:AE, 16, 0) -> [보완1차]착수신고 2022-10-16 | L13: =VLOOKUP(C13, '국외평가(ORS)'!A:AX, 2, 0) -> 승인 | M13: 검토필요 | N13: 보완요청 | O13: 사업자 | P13: =IF(AND(E13<>"반려", L13<>"반려"),"검토가능","") -> 검토가능 | Q13: 보완요청 | R13: 사업자 | S13: 10월 13일 | T13: 에코시안 | U13: 보완 요청 필요(CPA 22번 사유와 동일) | AC13: 업체정보보호(업무상 비밀)
... A21: 20 | B21: 단일감축사업 | C21: 인도 청정에너지 기기 보급 사업 (PoA 9181-CPA 29) | D21: 클리어스카이파트너스 | E21: 보완요청 | F21: 2020-12-10 | G21: =LEFT(VLOOKUP(C21,'국외평가(ORS)'!A:AX,34,0),10) -> 2020-12-10 | H21: =IF(G21=F21,"O","X") -> O | I21: 산업통상자원부 | J21: 2022-10-19 | K21: =VLOOKUP(C21,'국외평가(ORS)'!P:AE, 16, 0) -> 착수신고 2022-08-03 | L21: =VLOOKUP(C21, '국외평가(ORS)'!A:AX, 2, 0) -> 승인 | M21: 검토필요 | N21: 보완요청 | O21: 사업자 | P21: =IF(AND(E21<>"반려", L21<>"반려"),"검토가능","") -> 검토가능 | Q21: 보완요청 | R21: 사업자 | S21: 10월 13일 | T21: 에코시안 | U21: 보완 요청 필요(CPA 30번 사유와 동일) | AC21: 업체정보보호(업무상 비밀)
A22: 21 | B22: 단일감축사업 | C22: 인도 청정에너지 기기 보급 사업 (PoA 9181-CPA 30) | D22: 클리어스카이파트너스 | E22: 보완요청 | F22: 2020-12-10 | G22: =LEFT(VLOOKUP(C22,'국외평가(ORS)'!A:AX,34,0),10) -> 2020-12-10 | H22: =IF(G22=F22,"O","X") -> O | I22: 산업통상자원부 | J22: 2022-06-03 | K22: =VLOOKUP(C22,'국외평가(ORS)'!P:AE, 16, 0) -> 착수신고 2022-05-22 | L22: =VLOOKUP(C22, '국외평가(ORS)'!A:AX, 2, 0) -> 승인 | M22: 검토필요 | N22: 보완요청 | O22: 사업자 | P22: =IF(AND(E22<>"반려", L22<>"반려"),"검토가능","") -> 검토가능 | Q22: 보완요청 | R22: 사업자 | S22: 5월 26일 | T22: 에코시안_기샛별 | U22: 최종사용자 개인정보 및 사업계획서 상 영업기밀사항 등의 사유로 비공개 신청 (CSP) CPA 24-30_Verification Documents_MP10에는 개인정보가 포함되어 있으므로 비공개 부탁드립니다. > 태양광 사용자, 사업참여자 소속, 이름(p.12~15/검증을 위한 인터뷰 대상자) (CSP) PoA 9181 CPA19-30 사업계획서_2020.12에는 영업기밀사항등이 포함되어 있으므로 비공개 부탁드립니다. > 사업비용 조달 방법(p.7 사업비 확보는 회사 자본금 및 대출이며 향후 필요 시 추가 증자 및 대출 예정 등/20.12.10 최초 신청 후 6번째 보완 시까지 사업계획서 첨부자료로 해당 파일이 업로드 되어 있었으며 이후부터 CPA30 DD로 업로드됨) * 승인가능하나, 신청서 오류로 보완요청 필요 | AC22: 업체정보보호(업무상 비밀) | AF22: 클리어스카이파트너스 통보 문구 | AG22: 비공개 신청사유를 하기와 같이 보완 요청 드립니다. - 사업계획서 내용 중 보안유지 필요부분 및 사유 구체화(사업계획서 증빙자료는 정보공개 대상 아님) - 외부사업 정보 비공개 신청서 상 내용 기재 후 재제출
A23: 22 | B23: 단일감축사업 | C23: 중국 파랍기여덕 풍력발전 프로젝트 감축사업 | D23: 한국전력공사 | E23: 보완요청 | F23: 2023-01-12 | G23: =LEFT(VLOOKUP(C23,'국외평가(ORS)'!A:AX,34,0),10) -> 2019-10-15 | H23: =IF(G23=F23,"O","X") -> X | I23: 산업통상자원부 | J23: 2023-04-25 | K23: =VLOOKUP(C23,'국외평가(ORS)'!P:AE, 16, 0) -> [보완1차]착수신고 2020-02-26 | L23: =VLOOKUP(C23, '국외평가(ORS)'!A:AX, 2, 0) -> 승인 | M23: 검토필요 | N23: 보완요청 | O23: 사업자 | P23: =IF(AND(E23<>"반려", L23<>"반려"),"검토가능","") -> 검토가능 | Q23: 보완요청 | R23: 사업자 | S23: 23년3월27일 | T23: 에코시안_조영우 | U23: 사업계획서 내용 중 비공개 필요 부분 정확히 명시 필요(사업계획서 증빙자료는 정보공개 대상 아님)) | AC23: 업체정보보호(업무상 비밀)
A24: 23 | B24: 단일감축사업 | C24: 중국 북표소탑자 풍력발전 프로젝트 감축사업 | D24: 한국전력공사 | E24: 보완요청 | F24: 2023-01-12 | G24: =LEFT(VLOOKUP(C24,'국외평가(ORS)'!A:AX,34,0),10) -> 2019-10-15 | H24: =IF(G24=F24,"O","X") -> X | I24: 산업통상자원부 | J24: 2023-04-25 | K24: =VLOOKUP(C24,'국외평가(ORS)'!P:AE, 16, 0) -> [보완1차]착수신고 2020-02-26 | L24: =VLOOKUP(C24, '국외평가(ORS)'!A:AX, 2, 0) -> 승인 | M24: 검토필요 | N24: 보완요청 | O24: 사업자 | P24: =IF(AND(E24<>"반려", L24<>"반려"),"검토가능","") -> 검토가능 | Q24: 보완요청 | R24: 사업자 | S24: 23년3월27일 | T24: 에코시안_조영우 | U24: 사업계획서 내용 중 비공개 필요 부분 정확히 명시 필요(사업계획서 증빙자료는 정보공개 대상 아님)) | AC24: 업체정보보호(업무상 비밀)
A25: 24 | B25: 단일감축사업 | C25: 중국 객좌쌍묘 풍력발전 프로젝트 감축사업 | D25: 한국전력공사 | E25: 보완요청 | F25: 2023-01-12 | G25: =LEFT(VLOOKUP(C25,'국외평가(ORS)'!A:AX,34,0),10) -> 2019-10-15 | H25: =IF(G25=F25,"O","X") -> X | I25: 산업통상자원부 | J25: 2023-04-25 | K25: =VLOOKUP(C25,'국외평가(ORS)'!P:AE, 16, 0) -> [보완1차]착수신고 2020-02-26 | L25: =VLOOKUP(C25, '국외평가(ORS)'!A:AX, 2, 0) -> 승인 | M25: 검토필요 | N25: 보완요청 | O25: 사업자 | P25: =IF(AND(E25<>"반려", L25<>"반려"),"검토가능","") -> 검토가능 | Q25: 보완요청 | R25: 사업자 | S25: 23년3월27일 | T25: 에코시안_조영우 | U25: 사업계획서 내용 중 비공개 필요 부분 정확히 명시 필요(사업계획서 증빙자료는 정보공개 대상 아님)) | AC25: 업체정보보호(업무상 비밀)

Sheet (비공개)국외인증
A1: 검증 | B1: 번호 | C1: 사업유형 | D1: 사업명 | E1: 업체명 | F1: 유효기간 | G1: 모니터링차수 | H1: 차수 | I1: 모니터링 기간 시작일 | J1: 진행상태 | K1: 정보비공개 신청일 | L1: 사업 신청일 | M1: 평가 가능 여부 | N1: 관장기관 | O1: 처리일 | P1: 처리상태 | Q1: 검토대상 | R1: 진행상태 | S1: 현 위치 | T1: 검토대상 | U1: 진행상태 | V1: 현 위치 | W1: 업데이트 | X1: 담당자 | Y1: 비고 | Z1: 권리 | AA1: 대외비 자료 | AB1: 계약서류 | AC1: 연료 사용량 | AD1: 공정 도식도 | AE1: 영업비밀 | AF1: 내규방침 제출여부 | AG1: 비공개 신청사유 | AH1: 특이사항
A2: =D2&H2 -> 아프리카 고효율 쿡스토브 보급 PoA 사업 : CPA 00008(가나)(한국 지원)2차 | B2: 1 | C2: 단일감축사업 | D2: 아프리카 고효율 쿡스토브 보급 PoA 사업 : CPA 00008(가나)(한국 지원) | E2: 씨이알피디(주) | F2: 2019-04-12~2029-04-11 | G2: 2차 (2019-07-01~2019-07-01) | H2: =LEFT(G2,FIND("차",G2)) -> 2차 | I2: =MID(G2,FINDB("(",G2),10) -> 2019-07-01 | J2: 반려 | K2: 2022-09-06 | L2: =LEFT(VLOOKUP(D2,'국외인증(ORS)'!L:BA,33,0),10) -> 2022-04-22 | M2: =IF(L2=K2,"O","X") -> X | N2: 산업통상자원부 | O2: 2022-09-14 | P2: =VLOOKUP(A2,'국외인증(ORS)'!A:AQ, 43, 0) -> 심의승인 | Q2: 검토필요 | R2: 반려 | S2: 종결 | T2: =IF(AND(J2<>"반려",P2<>"검토반려"),"검토가능","") | U2: 반려완료 | V2: 종결 | W2: 10월 13일 | X2: 에코시안_기샛별 | Y2: 모니터링보고서 및 검증보고서 내 보안유지 필요부분 구체화 필요(회사 내규) | AG2: 내부방침
A3: =D3&H3 -> 아프리카 고효율 쿡스토브 보급 PoA 사업 : CPA 00009(가나)(한국 지원)2차 | B3: 2 | C3: 단일감축사업 | D3: 아프리카 고효율 쿡스토브 보급 PoA 사업 : CPA 00009(가나)(한국 지원) | E3: 씨이알피디(주) | F3: 2019-04-12~2029-04-11 | G3: 2차 (2019-07-01~2019-07-01) | H3: =LEFT(G3,FIND("차",G3)) -> 2차 | I3: =MID(G3,FINDB("(",G3),10) -> 2019-07-01 | J3: 반려 | K3: 2022-09-06 | L3: =LEFT(VLOOKUP(D3,'국외인증(ORS)'!L:BA,33,0),10) -> 2022-04-22 | M3: =IF(L3=K3,"O","X") -> X | N3: 산업통상자원부 | O3: 2022-09-14 | P3: =VLOOKUP(A3,'국외인증(ORS)'!A:AQ, 43, 0) -> 심의승인 | Q3: 검토필요 | R3: 반려 | S3: 종결 | T3: =IF(AND(J3<>"반려",P3<>"검토반려"),"검토가능","") | U3: 반려완료 | V3: 종결 | W3: 10월 13일 | X3: 에코시안_기샛별 | Y3: 모니터링보고서 및 검증보고서 내 보안유지 필요부분 구체화 필요 | AG3: 내부방침
A4: =D4&H4 -> 아프리카 고효율 쿡스토브 보급 PoA 사업 : CPA 00010(나이지리아)(한국 지원)2차 | B4: 3 | C4: 단일감축사업 | D4: 아프리카 고효율 쿡스토브 보급 PoA 사업 : CPA 00010(나이지리아)(한국 지원) | E4: 씨이알피디(주) | F4: 2019-04-05~2029-04-04 | G4: 2차 (2019-07-01~2019-07-01) | H4: =LEFT(G4,FIND("차",G4)) -> 2차 | I4: =MID(G4,FINDB("(",G4),10) -> 2019-07-01 | J4: 반려 | K4: 2022-09-06 | L4: =LEFT(VLOOKUP(D4,'국외인증(ORS)'!L:BA,33,0),10) -> 2022-04-21 | M4: =IF(L4=K4,"O","X") -> X | N4: 산업통상자원부 | O4: 2022-09-14 | P4: =VLOOKUP(A4,'국외인증(ORS)'!A:AQ, 43, 0) -> 심의승인 | Q4: 검토필요 | R4: 반려 | S4: 종결 | T4: =IF(AND(J4<>"반려",P4<>"검토반려"),"검토가능","") | U4: 반려완료 | V4: 종결 | W4: 10월 13일 | X4: 에코시안_기샛별 | Y4: 모니터링보고서 및 검증보고서 내 보안유지 필요부분 구체화 필요 | AG4: 내부방침
A5: =D5&H5 -> 아프리카 고효율 쿡스토브 보급 PoA 사업 : CPA 00011(나이지리아)(한국 지원)2차 | B5: 4 | C5: 단일감축사업 | D5: 아프리카 고효율 쿡스토브 보급 PoA 사업 : CPA 00011(나이지리아)(한국 지원) | E5: 씨이알피디(주) | F5: 2019-04-05~2029-04-04 | G5: 2차 (2019-07-01~2019-07-01) | H5: =LEFT(G5,FIND("차",G5)) -> 2차 | I5: =MID(G5,FINDB("(",G5),10) -> 2019-07-01 | J5: 반려 | K5: 2022-09-06 | L5: =LEFT(VLOOKUP(D5,'국외인증(ORS)'!L:BA,33,0),10) -> 2022-04-21 | M5: =IF(L5=K5,"O","X") -> X | N5: 산업통상자원부 | O5: 2022-09-14 | P5: =VLOOKUP(A5,'국외인증(ORS)'!A:AQ, 43, 0) -> 심의승인 | Q5: 검토필요 | R5: 반려 | S5: 종결 | T5: =IF(AND(J5<>"반려",P5<>"검토반려"),"검토가능","") | U5: 반려완료 | V5: 종결 | W5: 10월 13일 | X5: 에코시안_기샛별 | Y5: 모니터링보고서 및 검증보고서 내 보안유지 필요부분 구체화 필요 | AG5: 내부방침
A6: =D6&H6 -> 아프리카 고효율 쿡스토브 보급 PoA 사업 : CPA 00012(나이지리아)(한국 지원)2차 | B6: 5 | C6: 단일감축사업 | D6: 아프리카 고효율 쿡스토브 보급 PoA 사업 : CPA 00012(나이지리아)(한국 지원) | E6: 씨이알피디(주) | F6: 2019-04-05~2029-04-04 | G6: 2차 (2019-07-01~2019-07-01) | H6: =LEFT(G6,FIND("차",G6)) -> 2차 | I6: =MID(G6,FINDB("(",G6),10) -> 2019-07-01 | J6: 반려 | K6: 2022-09-06 | L6: =LEFT(VLOOKUP(D6,'국외인증(ORS)'!L:BA,33,0),10) -> 2022-04-21 | M6: =IF(L6=K6,"O","X") -> X | N6: 산업통상자원부 | O6: 2022-09-14 | P6: =VLOOKUP(A6,'국외인증(ORS)'!A:AQ, 43, 0) -> 심의승인 | Q6: 검토필요 | R6: 반려 | S6: 종결 | T6: =IF(AND(J6<>"반려",P6<>"검토반려"),"검토가능","") | U6: 반려완료 | V6: 종결 | W6: 10월 13일 | X6: 에코시안_기샛별 | Y6: 모니터링보고서 및 검증보고서 내 보안유지 필요부분 구체화 필요 | AG6: 내부방침
A7: =D7&H7 -> 아프리카 고효율 쿡스토브 보급 PoA 사업 : CPA0008(케냐)2차 | B7: 6 | C7: 단일감축사업 | D7: 아프리카 고효율 쿡스토브 보급 PoA 사업 : CPA0008(케냐) | E7: 씨이알피디(주) | F7: 2019-03-22~2029-03-21 | G7: 2차 (2019-07-01~2019-07-01) | H7: =LEFT(G7,FIND("차",G7)) -> 2차 | I7: =MID(G7,FINDB("(",G7),10) -> 2019-07-01 | J7: 반려 | K7: 2022-09-06 | L7: =LEFT(VLOOKUP(D7,'국외인증(ORS)'!L:BA,33,0),10) -> 2022-04-21 | M7: =IF(L7=K7,"O","X") -> X | N7: 산업통상자원부 | O7: 2022-09-14 | P7: =VLOOKUP(A7,'국외인증(ORS)'!A:AQ, 43, 0) -> 심의승인 | Q7: 검토필요 | R7: 반려 | S7: 종결 | T7: =IF(AND(J7<>"반려",P7<>"검토반려"),"검토가능","") | U7: 반려완료 | V7: 종결 | W7: 10월 13일 | X7: 에코시안_기샛별 | Y7: 모니터링보고서 및 검증보고서 내 보안유지 필요부분 구체화 필요 | AG7: 내부방침
A8: =D8&H8 -> 아프리카 고효율 쿡스토브 보급 PoA 사업 : CPA0009(케냐)2차 | B8: 7 | C8: 단일감축사업 | D8: 아프리카 고효율 쿡스토브 보급 PoA 사업 : CPA0009(케냐) | E8: 씨이알피디(주) | F8: 2019-03-22~2029-03-21 | G8: 2차 (2019-07-01~2019-07-01) | H8: =LEFT(G8,FIND("차",G8)) -> 2차 | I8: =MID(G8,FINDB("(",G8),10) -> 2019-07-01 | J8: 반려 | K8: 2022-09-06 | L8: =LEFT(VLOOKUP(D8,'국외인증(ORS)'!L:BA,33,0),10) -> 2022-04-21 | M8: =IF(L8=K8,"O","X") -> X | N8: 산업통상자원부 | O8: 2022-09-14 | P8: =VLOOKUP(A8,'국외인증(ORS)'!A:AQ, 43, 0) -> 심의승인 | Q8: 검토필요 | R8: 반려 | S8: 종결 | T8: =IF(AND(J8<>"반려",P8<>"검토반려"),"검토가능","") | U8: 반려완료 | V8: 종결 | W8: 10월 13일 | X8: 에코시안_기샛별 | Y8: 모니터링보고서 및 검증보고서 내 보안유지 필요부분 구체화 필요 | AG8: 내부방침
A9: =D9&H9 -> 아프리카 고효율 쿡스토브 보급 PoA 사업 : CPA0010(케냐)2차 | B9: 8 | C9: 단일감축사업 | D9: 아프리카 고효율 쿡스토브 보급 PoA 사업 : CPA0010(케냐) | E9: 씨이알피디(주) | F9: 2019-03-22~2029-03-21 | G9: 2차 (2019-07-01~2019-07-01) | H9: =LEFT(G9,FIND("차",G9)) -> 2차 | I9: =MID(G9,FINDB("(",G9),10) -> 2019-07-01 | J9: 반려 | K9: 2022-09-06 | L9: =LEFT(VLOOKUP(D9,'국외인증(ORS)'!L:BA,33,0),10) -> 2022-04-21 | M9: =IF(L9=K9,"O","X") -> X | N9: 산업통상자원부 | O9: 2022-09-14 | P9: =VLOOKUP(A9,'국외인증(ORS)'!A:AQ, 43, 0) -> 심의승인 | Q9: 검토필요 | R9: 반려 | S9: 종결 | T9: =IF(AND(J9<>"반려",P9<>"검토반려"),"검토가능","") | U9: 반려완료 | V9: 종결 | W9: 10월 13일 | X9: 에코시안_기샛별 | Y9: 모니터링보고서 및 검증보고서 내 보안유지 필요부분 구체화 필요 | AG9: 내부방침
A10: =D10&H10 -> 아프리카 고효율 쿡스토브 보급 PoA 사업 : CPA 00007(가나)(한국 지원)2차 | B10: 9 | C10: 단일감축사업 | D10: 아프리카 고효율 쿡스토브 보급 PoA 사업 : CPA 00007(가나)(한국 지원) | E10: 씨이알피디(주) | F10: 2019-04-12~2029-04-11 | G10: 2차 (2019-07-01~2019-07-01) | H10: =LEFT(G10,FIND("차",G10)) -> 2차 | I10: =MID(G10,FINDB("(",G10),10) -> 2019-07-01 | J10: 반려 | K10: 2022-09-06 | L10: =LEFT(VLOOKUP(D10,'국외인증(ORS)'!L:BA,33,0),10) -> 2022-04-22 | M10: =IF(L10=K10,"O","X") -> X | N10: 산업통상자원부 | O10: 2022-09-14 | P10: =VLOOKUP(A10,'국외인증(ORS)'!A:AQ, 43, 0) -> 심의승인 | Q10: 검토필요 | R10: 반려 | S10: 종결 | T10: =IF(AND(J10<>"반려",P10<>"검토반려"),"검토가능","") | U10: 반려완료 | V10: 종결 | W10: 10월 13일 | X10: 에코시안_기샛별 | Y10: 모니터링보고서 및 검증보고서 내 보안유지 필요부분 구체화 필요 | AG10: 내부방침
A11: =D11&H11 -> 서하남 사막 이남의 아프리카-말라위에 향상된 쿡스토브 보급 CPA-006사업1차 | B11: 10 | C11: 단일감축사업 | D11: 서하남 사막 이남의 아프리카-말라위에 향상된 쿡스토브 보급 CPA-006사업 | E11: 주식회사 한국임팩카본 | F11: 2019-06-05~2026-06-04 | G11: 1차 (2019-06-05~2019-06-05) | H11: =LEFT(G11,FIND("차",G11)) -> 1차 | I11: =MID(G11,FINDB("(",G11),10) -> 2019-06-05 | J11: 보완요청 | K11: 2021-10-06 | L11: =LEFT(VLOOKUP(D11,'국외인증(ORS)'!L:BA,33,0),10) -> 2022-07-14 | M11: =IF(L11=K11,"O","X") -> X | N11: 산업통상자원부 | O11: 2022-10-19 | P11: =VLOOKUP(A11,'국외인증(ORS)'!A:AQ, 43, 0) -> 심의승인 | Q11: 검토필요 | R11: 보완요청 | S11: 사업자 | T11: =IF(AND(J11<>"반려",P11<>"검토반려"),"검토가능","") -> 검토가능 | U11: 보완요청 | V11: 사업자 | W11: 10월 13일 | X11: 에코시안 | Y11: 모니터링보고서 및 검증보고서 내 보안유지 필요부분 구체화 필요 | AG11: 내부방침
A12: =D12&H12 -> 안전한 식수 공급을 위한 정수기 보급 사업 : CPA 102(한국 지원)2차 | B12: 11 | C12: 단일감축사업 | D12: 안전한 식수 공급을 위한 정수기 보급 사업 : CPA 102(한국 지원) | E12: 씨이알피디(주) | F12: 2019-04-26~2026-04-25 | G12: 2차 (2019-05-23~2019-05-23) | H12: =LEFT(G12,FIND("차",G12)) -> 2차 | I12: =MID(G12,FINDB("(",G12),10) -> 2019-05-23 | J12: 반려 | K12: 2022-09-06 | L12: =LEFT(VLOOKUP(D12,'국외인증(ORS)'!L:BA,33,0),10) -> 2021-10-08 | M12: =IF(L12=K12,"O","X") -> X | N12: 산업통상자원부 | O12: 2022-09-14 | P12: =VLOOKUP(A12,'국외인증(ORS)'!A:AQ, 43, 0) -> 심의승인 | Q12: 검토필요 | R12: 반려 | S12: 종결 | T12: =IF(AND(J12<>"반려",P12<>"검토반려"),"검토가능","") | U12: 반려완료 | V12: 종결 | W12: 10월 13일 | X12: KECM_임하진 | Y12: 모니터링보고서 및 검증보고서 내 보안유지 필요부분 구체화 필요 | Z12: X | AA12: X | AB12: X | AC12: O | AD12: X | AE12: X | AF12: X | AG12: 내부방침
A13: =D13&H13 -> 안전한 식수 공급을 위한 정수기 보급 사업 : CPA 101(한국 지원)2차 | B13: 12 | C13: 단일감축사업 | D13: 안전한 식수 공급을 위한 정수기 보급 사업 : CPA 101(한국 지원) | E13: 씨이알피디(주) | F13: 2019-04-26~2026-04-25 | G13: 2차 (2019-05-23~2019-05-23) | H13: =LEFT(G13,FIND("차",G13)) -> 2차 | I13: =MID(G13,FINDB("(",G13),10) -> 2019-05-23 | J13: 반려 | K13: 2022-09-06 | L13: =LEFT(VLOOKUP(D13,'국외인증(ORS)'!L:BA,33,0),10) -> 2021-10-08 | M13: =IF(L13=K13,"O","X") -> X | N13: 산업통상자원부 | O13: 2022-09-14 | P13: =VLOOKUP(A13,'국외인증(ORS)'!A:AQ, 43, 0) -> 심의승인 | Q13: 검토필요 | R13: 반려 | S13: 종결 | T13: =IF(AND(J13<>"반려",P13<>"검토반려"),"검토가능","") | U13: 반려완료 | V13: 종결 | W13: 10월 13일 | X13: KECM_임하진 | Y13: 모니터링보고서 및 검증보고서 내 보안유지 필요부분 구체화 필요 | Z13: X | AA13: X | AB13: X | AC13: O | AD13: X | AE13: X | AF13: X | AG13: 내부방침
A14: =D14&H14 -> 안전한 식수 공급을 위한 정수기 보급 사업 : CPA 100(한국 지원)2차 | B14: 13 | C14: 단일감축사업 | D14: 안전한 식수 공급을 위한 정수기 보급 사업 : CPA 100(한국 지원) | E14: 씨이알피디(주) | F14: 2019-04-26~2026-04-25 | G14: 2차 (2019-05-23~2019-05-23) | H14: =LEFT(G14,FIND("차",G14)) -> 2차 | I14: =MID(G14,FINDB("(",G14),10) -> 2019-05-23 | J14: 반려 | K14: 2022-09-06 | L14: =LEFT(VLOOKUP(D14,'국외인증(ORS)'!L:BA,33,0),10) -> 2021-10-08 | M14: =IF(L14=K14,"O","X") -> X | N14: 산업통상자원부 | O14: 2022-09-14 | P14: =VLOOKUP(A14,'국외인증(ORS)'!A:AQ, 43, 0) -> 심의승인 | Q14: 검토필요 | R14: 반려 | S14: 종결 | T14: =IF(AND(J14<>"반려",P14<>"검토반려"),"검토가능","") | U14: 반려완료 | V14: 종결 | W14: 10월 13일 | X14: KECM_임하진 | Y14: 모니터링보고서 및 검증보고서 내 보안유지 필요부분 구체화 필요 | Z14: X | AA14: X | AB14: X | AC14: O | AD14: X | AE14: X | AF14: X | AG14: 내부방침
A15: =D15&H15 -> 안전한 식수 공급을 위한 정수기 보급 사업 : CPA 99(한국 지원)2차 | B15: 14 | C15: 단일감축사업 | D15: 안전한 식수 공급을 위한 정수기 보급 사업 : CPA 99(한국 지원) | E15: 씨이알피디(주) | F15: 2019-04-26~2026-04-25 | G15: 2차 (2019-05-23~2019-05-23) | H15: =LEFT(G15,FIND("차",G15)) -> 2차 | I15: =MID(G15,FINDB("(",G15),10) -> 2019-05-23 | J15: 반려 | K15: 2022-09-06 | L15: =LEFT(VLOOKUP(D15,'국외인증(ORS)'!L:BA,33,0),10) -> 2021-10-08 | M15: =IF(L15=K15,"O","X") -> X | N15: 산업통상자원부 | O15: 2022-09-14 | P15: =VLOOKUP(A15,'국외인증(ORS)'!A:AQ, 43, 0) -> 심의승인 | Q15: 검토필요 | R15: 반려 | S15: 종결 | T15: =IF(AND(J15<>"반려",P15<>"검토반려"),"검토가능","") | U15: 반려완료 | V15: 종결 | W15: 10월 13일 | X15: KECM_임하진 | Y15: 모니터링보고서 및 검증보고서 내 보안유지 필요부분 구체화 필요 | Z15: X | AA15: X | AB15: X | AC15: O | AD15: X | AE15: X | AF15: X | AG15: 내부방침
A16: =D16&H16 -> 안전한 식수 공급을 위한 정수기 보급 사업 : CPA 98(한국 지원)2차 | B16: 15 | C16: 단일감축사업 | D16: 안전한 식수 공급을 위한 정수기 보급 사업 : CPA 98(한국 지원) | E16: 씨이알피디(주) | F16: 2019-04-26~2026-04-25 | G16: 2차 (2019-05-23~2019-05-23) | H16: =LEFT(G16,FIND("차",G16)) -> 2차 | I16: =MID(G16,FINDB("(",G16),10) -> 2019-05-23 | J16: 반려 | K16: 2022-09-06 | L16: =LEFT(VLOOKUP(D16,'국외인증(ORS)'!L:BA,33,0),10) -> 2021-10-08 | M16: =IF(L16=K16,"O","X") -> X | N16: 산업통상자원부 | O16: 2022-09-14 | P16: =VLOOKUP(A16,'국외인증(ORS)'!A:AQ, 43, 0) -> 심의승인 | Q16: 검토필요 | R16: 반려 | S16: 종결 | T16: =IF(AND(J16<>"반려",P16<>"검토반려"),"검토가능","") | U16: 반려완료 | V16: 종결 | W16: 10월 13일 | X16: KECM_임하진 | Y16: 모니터링보고서 및 검증보고서 내 보안유지 필요부분 구체화 필요 | Z16: X | AA16: X | AB16: X | AC16: O | AD16: X | AE16: X | AF16: X | AG16: 내부방침
